Workbook

Sheet Contratos aprendizaje
A1: ASIGNACIÓN DE INSTRUCTOR DE SEGUIMIENTO A APRENDICES CON CONTRATO DE APRENDIZAJE
A2: INSTRUCTOR | B2: NIT | C2: Razon Social | D2: Departamento empresa | E2: Ciudad empresa | F2: Dirección | G2: Teléfono empresa | H2: Correo electrónico | I2: Tipo documento | J2: Numero documento | K2: Apellidos | L2: Nombres | M2: Fecha Nacimiento | N2: Género | O2: Discapacidad | P2: Teléfono | Q2: Correo electónico | R2: Departamento código | S2: Departamento | T2: Municipio código | U2: Municipio | V2: Centro ID | W2: Centro | X2: Especialidad | Y2: Ficha | Z2: Inicio lectiva | AA2: Fin lectiva | AB2: Inicio productiva | AC2: Fin productiva | AD2: Contrato inicio | AE2: Contrato Fin | AF2: Regional | AG2: Fase | AH2: Nit EPS | AI2: EPS | AJ2: Nit ARL | AK2: ARL | AL2: Fecha registro | AM2: Contrato cedido a | AN2: Causa de finalización del contrato | AO2: Detalle de finalización del contrato | AP2: Ciudad última solicitud
A3: Andres Cataño | B3: 800021137 | C3: AGRICOLA SARA PALMA S.A. | D3: ANTIOQUIA | E3: MEDELLIN | F3: apartado | G3: 3103531316 | H3: Mzapata@sarapalma.com.co | I3: C.C. | J3: 1027948187 | K3: MOSQUERA MARMOLEJO | L3: YURIS LENYS | M3: 20/04/2005 | N3: F | P3: 5713333333 | Q3: yurismosquera124@gmail.com | R3: 5 | S3: ANTIOQUIA | T3: 147 | U3: CAREPA | V3: 950400 | W3: COMPLEJO TECNOLOGICO AGROINDUSTRIAL,PECUARIO Y TURISTICO -URABA- | X3: TECNICO EN PRODUCCION AGROPECUARIA | Y3: 2818005 | Z3: 04/08/2023 | AA3: 04/05/2024 | AB3: 05/05/2024 | AC3: 05/11/2024 | AD3: 25/10/2023 | AE3: 46004 | AF3: REGIONAL ANTIOQUIA | AG3: LECTIVA - PRODUCTIVA | AH3: 800088702 | AI3: EPS SURA | AJ3: 999999999 | AK3: No registrada | AL3: 45229.419 | AN3: Terminación automática por fecha de contrato Automatic Job1
A4: Dina Dorado | B4: 890930060 | C4: AGRICOLA SANTAMARIA S.A.S | D4: ANTIOQUIA | E4: APARTADO | F4: KM 1 SALIDA TURBO, BODEGAS TROPICENTRO | G4: 3197060-8156020-3207252274 | H4: rocio.valencia@gruposantamaria.com.co, comiteintegral@gruposantamaria.com.co | I4: T.I. | J4: 1028012740 | K4: GUZMAN VUELVAS | L4: VALENTINA | M4: 39192 | N4: F | P4: 573126158300 | Q4: valentina2006guz@gmail.com | R4: 5 | S4: ANTIOQUIA | T4: 313 | U4: GRANADA | V4: 950400 | W4: COMPLEJO TECNOLOGICO AGROINDUSTRIAL,PECUARIO Y TURISTICO -URABA- | X4: TECNICO EN PRODUCCION AGROPECUARIA | Y4: 2987617 | Z4: 45426 | AA4: 45743 | AB4: 45744 | AC4: 45926 | AD4: 45824 | AE4: 46006 | AF4: REGIONAL ANTIOQUIA | AG4: PRODUCTIVA | AH4: 890900286 | AI4: SAVIA SALUD E.P.S. | AJ4: 800256161 | AK4: ARP SURA | AL4: 45824.665
A5: Andrés Felipe Henao | B5: 900614404 | C5: BIOPLANTA PALMERA PARA EL DESARROLLO S.A. | D5: ANTIOQUIA | E5: CAREPA | F5: CR 80 CL 80 CENTRO COMERCIAL LAS PLAYAS BL 1 | G5: 8155970 | H5: nomina@bioplanta.co | I5: C.C. | J5: 1027943775 | K5: LOPEZ GARCIA | L5: JUAN DAVID | M5: 06/08/2004 | N5: M | P5: 573117821565 | Q5: juandavidlopezgarcia225@gmail.com | R5: 5 | S5: ANTIOQUIA | T5: 45 | U5: APARTADO | V5: 950400 | W5: COMPLEJO TECNOLOGICO AGROINDUSTRIAL,PECUARIO Y TURISTICO -URABA- | X5: TÉCNICO EN MECANICA DE MAQUINARIA INDUSTRIAL | Y5: 2924270 | Z5: 15/04/2024 | AA5: 28/02/2025 | AB5: 01/03/2025 | AC5: 30/08/2025 | AD5: 27/08/2025 | AE5: 46006 | AF5: REGIONAL ANTIOQUIA | AG5: PRODUCTIVA | AH5: 890900286 | AI5: SAVIA SALUD E.P.S. | AJ5: 860028415 | AK5: SEGUROS LA EQUIDAD | AL5: 45896.458
A6: Andres Cataño | B6: 900089324 | C6: AGRICOLA MAYORCA S.A. | D6: ANTIOQUIA | E6: MEDELLIN | F6: CARRERA 43A No. 19-17 EDIFICIO BLOCK EMPRESARIAL PISO 12 | G6: 4440009 - 8243483 (URABA) | H6: analistacontrataciones@banafrut.com | I6: C.C. | J6: 1028030571 | K6: SEPULVEDA MONROY | L6: GABRIELA MARIA | M6: 35398 | N6: F | P6: 573100472329 | Q6: gabrielasepulveda2024@gmail.com | R6: 5 | S6: ANTIOQUIA | T6: 45 | U6: APARTADO | V6: 950400 | W6: COMPLEJO TECNOLOGICO AGROINDUSTRIAL,PECUARIO Y TURISTICO -URABA- | X6: TECNICO EN PRODUCCION AGROPECUARIA | Y6: 3046758 | Z6: 45520 | AA6: 45793 | AB6: 45794 | AC6: 45976 | AD6: 45824 | AE6: 46007 | AF6: REGIONAL ANTIOQUIA | AG6: PRODUCTIVA | AH6: 800088702 | AI6: EPS SURA | AJ6: 800256161 | AK6: ARP SURA | AL6: 45824.294
A7: Abel Valderrama | B7: 811009784 | C7: BANANERAS FUEGO VERDE S.A. | D7: ANTIOQUIA | E7: MEDELLIN | F7: Cr 99 entre cl 99b 100 | G7: 8156235 - 3162510723 | H7: bienestarlaboral@grupo20sa.com | I7: C.C. | J7: 1040356203 | K7: MARTINEZ CERVANTES | L7: JHEIDER ANTONIO | M7: 08/04/2006 | N7: M | P7: 573107447313 | Q7: martinezjhoimer3@gmail.com | R7: 5 | S7: ANTIOQUIA | T7: 147 | U7: CAREPA | V7: 950400 | W7: COMPLEJO TECNOLOGICO AGROINDUSTRIAL,PECUARIO Y TURISTICO -URABA- | X7: TÉCNICO EN SISTEMAS TELEINFORMÁTICOS | Y7: 3077813 | Z7: 16/09/2024 | AA7: 16/06/2025 | AB7: 17/06/2025 | AC7: 15/12/2025 | AD7: 28/11/2024 | AE7: 46007 | AF7: REGIONAL ANTIOQUIA | AG7: LECTIVA - PRODUCTIVA | AH7: 900156264 | AI7: NUEVA EPS | AJ7: 860013816 | AK7: POSITIVA | AL7: 45624.339
A8: Virtual | B8: 900727452 | C8: ECOLIMPIEZA SOLUCIONES EMPRESARIALES S.A.S. | D8: TOLIMA | E8: IBAGUE | F8: CL 12 N 3 - 65 IN 5 | G8: 3184631920 | H8: ecolimpiezaibague@hotmail.com | I8: C.C. | J8: 1107975931 | K8: URIBE PAEZ | L8: DUVAN ALEXIS | M8: 18/05/2005 | N8: M | P8: 573123115278 | Q8: duvanalexisu@gmail.com | R8: 73 | S8: TOLIMA | T8: 1 | U8: IBAGUE | V8: 950400 | W8: COMPLEJO TECNOLOGICO AGROINDUSTRIAL,PECUARIO Y TURISTICO -URABA- | X8: TÉCNICO EN INTEGRACION DE CONTENIDOS DIGITALES. | Y8: 2721391 | Z8: 27/03/2023 | AA8: 27/12/2023 | AB8: 28/12/2023 | AC8: 26/06/2024 | AD8: 16/06/2025 | AE8: 46007 | AF8: REGIONAL ANTIOQUIA | AG8: PRODUCTIVA | AH8: 900156264 | AI8: NUEVA EPS | AJ8: 800256161 | AK8: ARP SURA | AL8: 45824.569 | AN8: Terminación automática por fecha de contrato Automatic Job1
A9: Virtual | B9: 901420688 | C9: KONFÍE S.A.S. | D9: BOGOTA D.C. | E9: BOGOTA D. C. | F9: Calle 17 A No. 68 D - 17 | G9: 3202256593 | H9: talento.humano@konfie.com | I9: C.C. | J9: 1018485900 | K9: RODRIGUEZ YASNO | L9: DANIELA ALEXANDRA | M9: 35204 | N9: F | P9: 3206253344 | Q9: drodriguez_19@outlook.com | R9: 11 | S9: BOGOTA D.C. | T9: 1 | U9: BOGOTA D. C. | V9: 950400 | W9: COMPLEJO TECNOLOGICO AGROINDUSTRIAL,PECUARIO Y TURISTICO -URABA- | X9: TÉCNICO EN ATENCION INTEGRAL AL CLIENTE | Y9: 3069862 | Z9: 45551 | AA9: 45824 | AB9: 45825 | AC9: 46006 | AD9: 45882 | AE9: 46009 | AF9: REGIONAL ANTIOQUIA | AG9: PRODUCTIVA | AH9: 860066942 | AI9: COMPENSAR E.P.S. | AJ9: 860002503 | AK9: COMPAÑÍA DE SEGUROS BOLIVAR | AL9: 45882.431
A10: Abel Valderrama | B10: 890929329 | C10: SUPERMERCADO LOS IBAÑEZ Y COMPAÑÍA S.A. | D10: ANTIOQUIA | E10: APARTADO | F10: CALLE 99 No 102-55 Barrio Ortiz | G10: 3128322234 | H10: LOSIBANEZSUPER@HOTMAIL.COM | I10: C.C. | J10: 1040381543 | K10: SANCHEZ BURGOS | L10: MERLYS JOHANA | M10: 35992 | N10: F | P10: 3009662320 | Q10: merlissanchez104@gmail.com | R10: 5 | S10: ANTIOQUIA | T10: 147 | U10: CAREPA | V10: 950400 | W10: COMPLEJO TECNOLOGICO AGROINDUSTRIAL,PECUARIO Y TURISTICO -URABA- | X10: TÉCNICO EN SISTEMAS TELEINFORMÁTICOS | Y10: 2975578 | Z10: 45406 | AA10: 45681 | AB10: 45682 | AC10: 45861 | AD10: 45829 | AE10: 46011 | AF10: REGIONAL ANTIOQUIA | AG10: PRODUCTIVA | AH10: 800088702 | AI10: EPS SURA | AJ10: 830025999 | AK10: AGENCIA DE SEGUROS SALUD PLUS LTDA | AL10: 45832.522
A11: Carlos Negrete | B11: 890904996 | C11: EMPRESAS PUBLICAS DE MEDELLIN E.S.P. | D11: ANTIOQUIA | E11: MEDELLIN | F11: Cra. 58 42-125 | G11: 3805178 | H11: Lina.quintero@epm.com.co;maria.yubelli.bolivar@epm.com.co;dep01980552@epm.com.co | I11: C.C. | J11: 1001033198 | K11: ARANGO CABRERA | L11: JOHN ESTEBAN | M11: 36578 | N11: M | P11: 3225394920 | Q11: arangoe741@gmail.com | R11: 5 | S11: ANTIOQUIA | T11: 45 | U11: APARTADO | V11: 950400 | W11: COMPLEJO TECNOLOGICO AGROINDUSTRIAL,PECUARIO Y TURISTICO -URABA- | X11: TECNÓLOGO EN SUPERVISIÓN DE REDES DE DISTRIBUCIÓN DE ENERGÍA ELÉCTRICA | Y11: 2775376 | Z11: 45117 | AA11: 45757 | AB11: 45758 | AC11: 45939 | AD11: 45832 | AE11: 46012 | AF11: REGIONAL ANTIOQUIA | AG11: PRODUCTIVA | AH11: 900156264 | AI11: NUEVA EPS | AJ11: 860013816 | AK11: POSITIVA | AL11: 45834.641
A12: Dina Dorado | B12: 890929589 | C12: INVERSIONES GOMEZ JARAMILLO S.A.S. | D12: ANTIOQUIA | E12: MEDELLIN | F12: LKM4 VIA AEROPUERTO LOS CEDROS FINCA LAS PAMPAS | G12: 3174365306 | H12: info@ingajo.com | I12: C.C. | J12: 1027941264 | K12: GARCÉS VARGAS | L12: MARYORYS | M12: 38066 | N12: F | P12: 3175075734 | Q12: maryorisgarces49@gmail.com | R12: 5 | S12: ANTIOQUIA | T12: 837 | U12: TURBO | V12: 950400 | W12: COMPLEJO TECNOLOGICO AGROINDUSTRIAL,PECUARIO Y TURISTICO -URABA- | X12: TECNICO EN CULTIVOS AGRICOLAS | Y12: 2925489 | Z12: 45355 | AA12: 45630 | AB12: 45631 | AC12: 45811 | AD12: 45834 | AE12: 46014 | AF12: REGIONAL ANTIOQUIA | AG12: PRODUCTIVA | AH12: 800088702 | AI12: EPS SURA | AJ12: 860013816 | AK12: POSITIVA | AL12: 45834.345
A13: Yorger Moreno | B13: 901122707 | C13: HACIENDA SAN BARTOLO S.A.S. ZOMAC | D13: ANTIOQUIA | E13: MEDELLIN | F13: cra 43 a #1a sur -69 | G13: 2664112 | H13: asistentenomina@lahaciendasas.com.co | I13: C.C. | J13: 1037122141 | K13: ECHAVARRIA GALLEGO | L13: STEVEN ALEJANDRO | M13: 10/02/2007 | N13: M | P13: 82820072 | Q13: stivenechavarria019@gmail.com | R13: 5 | S13: ANTIOQUIA | T13: 172 | U13: CHIGORODO | V13: 950400 | W13: COMPLEJO TECNOLOGICO AGROINDUSTRIAL,PECUARIO Y TURISTICO -URABA- | X13: TECNÓLOGO EN GESTION AGROEMPRESARIAL | Y13: 2910664 | Z13: 20/02/2024 | AA13: 20/11/2025 | AB13: 21/11/2025 | AC13: 19/05/2026 | AD13: 22/09/2025 | AE13: 46014 | AF13: REGIONAL ANTIOQUIA | AG13: LECTIVA - PRODUCTIVA | AH13: 800088702 | AI13: EPS SURA | AJ13: 830025999 | AK13: AGENCIA DE SEGUROS SALUD PLUS LTDA | AL13: 45929.379 | AN13: EL APRENDIZ NO CUMPLE CON CONOCIMIENTOS BÁSICOS | AO13: Durante los días 21, 22 de noviembre 2025, 3, 5 y 9 de diciembre de 2025, usted ha dejado de presentarse a su centro de trabajo, sin permiso de su empleador y sin entregar soportes válidos
A14: Abel Valderrama | B14: 900124689 | C14: FUNDACION SOMA | D14: ANTIOQUIA | E14: CHIGORODO | F14: CR 106 CL 95 | G14: 3116095402 | H14: direccionadministrativa@fundacionsoma.com | I14: C.C. | J14: 1077996318 | K14: GUTIERREZ CORDOBA | L14: JHON DARWIN | M14: 06/06/2002 | N14: M | P14: 573138711513 | Q14: jhonsitogutierrez1@gmail.com | R14: 27 | S14: CHOCO | T14: 1 | U14: QUIBDO | V14: 950400 | W14: COMPLEJO TECNOLOGICO AGROINDUSTRIAL,PECUARIO Y TURISTICO -URABA- | X14: TÉCNICO EN SISTEMAS TELEINFORMÁTICOS | Y14: 3077813 | Z14: 16/09/2024 | AA14: 16/06/2025 | AB14: 17/06/2025 | AC14: 15/12/2025 | AD14: 28/06/2025 | AE14: 46018 | AF14: REGIONAL ANTIOQUIA | AG14: PRODUCTIVA | AH14: 901037916 | AI14: ADRES EPS | AJ14: 830025999 | AK14: AGENCIA DE SEGUROS SALUD PLUS LTDA | AL14: 45841.418
A15: Didier Zuñiga | B15: 800158328 | C15: CARDIOESTUDIO S.A.S. | D15: ANTIOQUIA | E15: MEDELLIN | F15: Calle 2 sur # 46 -78 Apt 201 | G15: 3117467687 | H15: luz.ortiz@cardioestudio.com | I15: C.C. | J15: 1001033567 | K15: GOMEZ PALACIO | L15: MARCELA | M15: 36740 | N15: F | P15: 3234788121 | Q15: gjohnjader@gmail.com | R15: 5 | S15: ANTIOQUIA | T15: 45 | U15: APARTADO | V15: 950400 | W15: COMPLEJO TECNOLOGICO AGROINDUSTRIAL,PECUARIO Y TURISTICO -URABA- | X15: TECNÓLOGO EN GESTION ADMINISTRATIVA DEL SECTOR SALUD. | Y15: 2826376 | Z15: 45201 | AA15: 45840 | AB15: 45841 | AC15: 46023 | AD15: 45782 | AE15: 46021 | AF15: REGIONAL ANTIOQUIA | AG15: LECTIVA - PRODUCTIVA | AH15: 800088702 | AI15: EPS SURA | AJ15: 800256161 | AK15: ARP SURA | AL15: 45782.662
A16: Lucy Pernett | B16: 98529410 | C16: SALAZAR VALLEJO JHON JAIRO | D16: ANTIOQUIA | E16: MEDELLIN | F16: cra 45 # 25-39 | G16: 3023589515 | H16: personalnaturalma@gmail.com | I16: T.I. | J16: 1073981403 | K16: FERNANDEZ CUESTA | L16: LUZ NEIDYS | M16: 39188 | N16: F | P16: 5748206463 | Q16: fluz9220@gmail.com | R16: 5 | S16: ANTIOQUIA | T16: 837 | U16: TURBO | V16: 950400 | W16: COMPLEJO TECNOLOGICO AGROINDUSTRIAL,PECUARIO Y TURISTICO -URABA- | X16: TÉCNICO EN SERVICIOS COMERCIALES Y FINANCIEROS | Y16: 2917215 | Z16: 45352 | AA16: 45627 | AB16: 45628 | AC16: 45808 | AD16: 45839 | AE16: 46021 | AF16: REGIONAL ANTIOQUIA | AG16: PRODUCTIVA | AH16: 800088702 | AI16: EPS SURA | AJ16: 860013816 | AK16: POSITIVA | AL16: 45839.593
A17: Maria del Rosari Jaramillo | B17: 890917555 | C17: COOPERATIVA DE EDUCACION DE URABA | D17: ANTIOQUIA | E17: APARTADO | F17: diagonal 105c | G17: 3153066884 | H17: administrativa@educoop.com.co | I17: C.C. | J17: 1007898878 | K17: FLOREZ PEREZ | L17: LILY YULIANA | M17: 37207 | N17: F | P17: 3102116857 | Q17: lilyyulianaflorezperez@gmail.com | R17: 5 | S17: ANTIOQUIA | T17: 45 | U17: APARTADO | V17: 950400 | W17: COMPLEJO TECNOLOGICO AGROINDUSTRIAL,PECUARIO Y TURISTICO -URABA- | X17: TECNICO EN ATENCION INTEGRAL A LA PRIMERA INFANCIA | Y17: 2878845 | Z17: 45313 | AA17: 45587 | AB17: 45588 | AC17: 45768 | AD17: 45839 | AE17: 46021 | AF17: REGIONAL ANTIOQUIA | AG17: PRODUCTIVA | AH17: 890900286 | AI17: SAVIA SALUD E.P.S. | AJ17: 860028415 | AK17: SEGUROS LA EQUIDAD | AL17: 45839.503
A18: Marcelino Gonzalez | B18: 800021137 | C18: AGRICOLA SARA PALMA S.A. | D18: ANTIOQUIA | E18: MEDELLIN | F18: apartado | G18: 3103531316 | H18: Gviera@sarapalma.com.co | I18: C.C. | J18: 1027947047 | K18: POLO CORDERO | L18: JUAN DAVID | M18: 15/02/2005 | N18: M | P18: 3237034237 | Q18: poloj2459@gmail.com | R18: 5 | S18: ANTIOQUIA | T18: 147 | U18: CAREPA | V18: 950400 | W18: COMPLEJO TECNOLOGICO AGROINDUSTRIAL,PECUARIO Y TURISTICO -URABA- | X18: TECNÓLOGO EN GESTION DE LA PRODUCCION AGRICOLA | Y18: 2826366 | Z18: 02/10/2023 | AA18: 02/07/2025 | AB18: 03/07/2025 | AC18: 31/12/2025 | AD18: 20/02/2024 | AE18: 46022 | AF18: REGIONAL ANTIOQUIA | AG18: LECTIVA - PRODUCTIVA | AH18: 900156264 | AI18: NUEVA EPS | AJ18: 800256161 | AK18: ARP SURA | AL18: 45350.369
A19: Marcelino Gonzalez | B19: 800021137 | C19: AGRICOLA SARA PALMA S.A. | D19: ANTIOQUIA | E19: MEDELLIN | F19: apartado | G19: 3103531316 | H19: Gviera@sarapalma.com.co | I19: C.C. | J19: 1037116279 | K19: ROMERO MADARIAGA | L19: SEIDY ALEJANDRA | M19: 08/05/2004 | N19: F | P19: 573045945012 | Q19: seidyalejandraromero@gmail.com | R19: 5 | S19: ANTIOQUIA | T19: 172 | U19: CHIGORODO | V19: 950400 | W19: COMPLEJO TECNOLOGICO AGROINDUSTRIAL,PECUARIO Y TURISTICO -URABA- | X19: TECNÓLOGO EN GESTION DE LA PRODUCCION AGRICOLA | Y19: 2826366 | Z19: 02/10/2023 | AA19: 02/07/2025 | AB19: 03/07/2025 | AC19: 31/12/2025 | AD19: 01/03/2024 | AE19: 46022 | AF19: REGIONAL ANTIOQUIA | AG19: LECTIVA - PRODUCTIVA | AH19: 900156264 | AI19: NUEVA EPS | AJ19: 800256161 | AK19: ARP SURA | AL19: 45358.469
A20: Marcelino Gonzalez | B20: 890917006 | C20: AGROPECUARIA YERBAZAL S.A. | D20: ANTIOQUIA | E20: MEDELLIN | F20: CRA77 N 33 A 83 | G20: 3104536401 | H20: SISO@YERBAZAL.CO | I20: C.C. | J20: 1001030517 | K20: SANCHEZ SANCHEZ | L20: SDRUAL ENRIQUE | M20: 22/02/2002 | N20: M | P20: 3017131013 | Q20: asdrual07897320730937@gmail.com | R20: 5 | S20: ANTIOQUIA | T20: 45 | U20: APARTADO | V20: 950400 | W20: COMPLEJO TECNOLOGICO AGROINDUSTRIAL,PECUARIO Y TURISTICO -URABA- | X20: TECNÓLOGO EN GESTION DE LA PRODUCCION AGRICOLA | Y20: 2826366 | Z20: 02/10/2023 | AA20: 02/07/2025 | AB20: 03/07/2025 | AC20: 31/12/2025 | AD20: 25/04/2024 | AE20: 46022 | AF20: REGIONAL ANTIOQUIA | AG20: LECTIVA - PRODUCTIVA | AH20: 900156264 | AI20: NUEVA EPS | AJ20: 860013816 | AK20: POSITIVA | AL20: 45408.308
A21: Marcelino Gonzalez | B21: 890941851 | C21: INVERSIONES UCRANIA SAS | D21: ANTIOQUIA | E21: MEDELLIN | F21: KM 5 VIA NUEVA COLONIA | G21: 3152537555 | H21: INVERUCRANIA@GUCRANIA.COM | I21: C.C. | J21: 1032176563 | K21: OSORIO PEREZ | L21: LUIS DAVID | M21: 08/08/2004 | N21: M | P21: 5713385374 | Q21: luisosoriop17@gmail.com | R21: 5 | S21: ANTIOQUIA | T21: 45 | U21: APARTADO | V21: 950400 | W21: COMPLEJO TECNOLOGICO AGROINDUSTRIAL,PECUARIO Y TURISTICO -URABA- | X21: TECNÓLOGO EN GESTION DE LA PRODUCCION AGRICOLA | Y21: 2826366 | Z21: 02/10/2023 | AA21: 02/07/2025 | AB21: 03/07/2025 | AC21: 31/12/2025 | AD21: 08/05/2024 | AE21: 46022 | AF21: REGIONAL ANTIOQUIA | AG21: LECTIVA - PRODUCTIVA | AH21: 900156264 | AI21: NUEVA EPS | AJ21: 860013816 | AK21: POSITIVA | AL21: 45420.54
A22: Marcelino Gonzalez | B22: 890101826 | C22: FINCA CIBELES S.A. | D22: ATLANTICO | E22: BARRANQUILLA | F22: CRR 113 N 105C-53 CASA 84 | G22: 8427297 | H22: tesoreria@fincacibeles.com | I22: C.C. | J22: 1001154371 | K22: CALLE COGOLLO | L22: DANIEL | M22: 08/12/2003 | N22: M | P22: 3216926772 | Q22: callejavier@yahoo.com | R22: 5 | S22: ANTIOQUIA | T22: 45 | U22: APARTADO | V22: 950400 | W22: COMPLEJO TECNOLOGICO AGROINDUSTRIAL,PECUARIO Y TURISTICO -URABA- | X22: TECNÓLOGO EN GESTION DE LA PRODUCCION AGRICOLA | Y22: 2826366 | Z22: 02/10/2023 | AA22: 02/07/2025 | AB22: 03/07/2025 | AC22: 31/12/2025 | AD22: 16/08/2024 | AE22: 46022 | AF22: REGIONAL ANTIOQUIA | AG22: LECTIVA - PRODUCTIVA | AH22: 800088702 | AI22: EPS SURA | AJ22: 860013816 | AK22: POSITIVA | AL22: 45532.448 | AN22: Terminación automática por fecha de contrato Automatic Job1
A23: Marcelino Gonzalez | B23: 900296617 | C23: AGRICOLA SAN RIOMAR S.A.S | D23: ANTIOQUIA | E23: APARTADO | F23: CARRERA 109 C NO. 100 - 15 EDIFICIO OCÉANO OFICINA 101 | G23: 3116473007 | H23: AGRICOLASANRIOMAR@HOTMAIL.COM | I23: C.C. | J23: 1040353438 | K23: JERONIMO SIERRA | L23: SANTIAGO | M23: 17/04/2005 | N23: M | P23: 6018285266 | Q23: santiagojeronimosierra@gmail.com | R23: 5 | S23: ANTIOQUIA | T23: 45 | U23: APARTADO | V23: 950400 | W23: COMPLEJO TECNOLOGICO AGROINDUSTRIAL,PECUARIO Y TURISTICO -URABA- | X23: TECNÓLOGO EN GESTION DE LA PRODUCCION AGRICOLA | Y23: 2826366 | Z23: 02/10/2023 | AA23: 02/07/2025 | AB23: 03/07/2025 | AC23: 31/12/2025 | AD23: 01/08/2024 | AE23: 46022 | AF23: REGIONAL ANTIOQUIA | AG23: PRODUCTIVA | AH23: 800088702 | AI23: EPS SURA | AJ23: 860013816 | AK23: POSITIVA | AL23: 45553.664
A24: Aldwin Morelo | B24: 901122707 | C24: HACIENDA SAN BARTOLO S.A.S. ZOMAC | D24: ANTIOQUIA | E24: MEDELLIN | F24: cra 43 a #1a sur -69 | G24: 2664112 | H24: asistentenomina@lahaciendasas.com.co | I24: C.C. | J24: 1038801870 | K24: GOMEZ VERGARA | L24: ANA ISABEL | M24: 38875 | N24: F | P24: 5748254907 | Q24: gomezanaisabel2023@gmail.com | R24: 5 | S24: ANTIOQUIA | T24: 172 | U24: CHIGORODO | V24: 950400 | W24: COMPLEJO TECNOLOGICO AGROINDUSTRIAL,PECUARIO Y TURISTICO -URABA- | X24: TECNICO EN CONSERVACION DE RECURSOS NATURALES | Y24: 3051477 | Z24: 45524 | AA24: 45797 | AB24: 45798 | AC24: 45980 | AD24: 45839 | AE24: 46022 | AF24: REGIONAL ANTIOQUIA | AG24: PRODUCTIVA | AH24: 890900286 | AI24: SAVIA SALUD E.P.S. | AJ24: 800256161 | AK24: ARP SURA | AL24: 45840.738
A25: Yolanda Berrío | B25: 899999034 | C25: SERVICIO NACIONAL DE APRENDIZAJE, SENA | D25: BOGOTA D.C. | E25: BOGOTA D. C. | F25: Carrera 9 71N-60 | G25: 3107056945 | H25: cavendanov@sena.edu.co | I25: C.C. | J25: 1027959844 | K25: GARCES CANO | L25: NALLIBE VIANELA | M25: 19/01/2007 | N25: F | P25: 573192197521 | Q25: nallibegarces0@gmail.com | R25: 5 | S25: ANTIOQUIA | T25: 172 | U25: CHIGORODO | V25: 950400 | W25: COMPLEJO TECNOLOGICO AGROINDUSTRIAL,PECUARIO Y TURISTICO -URABA- | X25: TECNICO EN SISTEMAS AGROPECUARIOS ECOLOGICOS. | Y25: 3004049 | Z25: 05/06/2024 | AA25: 14/04/2025 | AB25: 15/04/2025 | AC25: 13/10/2025 | AD25: 01/07/2025 | AE25: 46022 | AF25: REGIONAL ANTIOQUIA | AG25: PRODUCTIVA | AH25: 890900286 | AI25: SAVIA SALUD E.P.S. | AJ25: 860013816 | AK25: POSITIVA | AL25: 45841.681
A26: Silvia Chaverra | B26: 800197268 | C26: DIAN | D26: RISARALDA | E26: PEREIRA | F26: Cra. 7 # 6C - 54 - Piso 8° - Edifício Sendas | G26: 6017428973 | H26: mvegaa@dian.gov.co | I26: C.C. | J26: 1045524311 | K26: BLANDON GONZALEZ | L26: YARLENNY | M26: 18/11/1996 | N26: F | P26: 573106392117 | Q26: yarlennyblandon3@gmail.com | R26: 5 | S26: ANTIOQUIA | T26: 837 | U26: TURBO | V26: 950400 | W26: COMPLEJO TECNOLOGICO AGROINDUSTRIAL,PECUARIO Y TURISTICO -URABA- | X26: TÉCNICO EN CONTABILIZACION DE OPERACIONES COMERCIALES Y FINANCIERAS. | Y26: 2855479 | Z26: 02/10/2023 | AA26: 02/07/2024 | AB26: 03/07/2024 | AC26: 01/01/2025 | AD26: 03/07/2025 | AE26: 46022 | AF26: REGIONAL ANTIOQUIA | AG26: PRODUCTIVA | AH26: 800249241 | AI26: E.P.S. COOSALUD | AJ26: 860013816 | AK26: POSITIVA | AL26: 45848.655
A27: Yorger Moreno | B27: 900089324 | C27: AGRICOLA MAYORCA S.A. | D27: ANTIOQUIA | E27: MEDELLIN | F27: CARRERA 43A No. 19-17 EDIFICIO BLOCK EMPRESARIAL PISO 12 | G27: 4440009 - 8243483 (URABA) | H27: analistacontrataciones@banafrut.com | I27: C.C. | J27: 1037119314 | K27: BARON PAYARES | L27: ESTEBAN | M27: 38150 | N27: M | P27: 5748254907 | Q27: estevanbaron13@gmail.com | R27: 5 | S27: ANTIOQUIA | T27: 172 | U27: CHIGORODO | V27: 950400 | W27: COMPLEJO TECNOLOGICO AGROINDUSTRIAL,PECUARIO Y TURISTICO -URABA- | X27: TECNICO EN CONSERVACION DE RECURSOS NATURALES | Y27: 3051477 | Z27: 45524 | AA27: 45797 | AB27: 45798 | AC27: 45980 | AD27: 45840 | AE27: 46023 | AF27: REGIONAL ANTIOQUIA | AG27: PRODUCTIVA | AH27: 900156264 | AI27: NUEVA EPS | AJ27: 800256161 | AK27: ARP SURA | AL27: 45840.336
A28: Bernardo Brand | B28: 900296617 | C28: AGRICOLA SAN RIOMAR S.A.S | D28: ANTIOQUIA | E28: APARTADO | F28: CARRERA 109 C NO. 100 - 15 EDIFICIO OCÉANO OFICINA 101 | G28: 3116473007 | H28: AGRICOLASANRIOMAR@HOTMAIL.COM | I28: C.C. | J28: 1129684404 | K28: TORDECILLA PEÑA | L28: JAVIER ANTONIO | M28: 11/08/2006 | N28: M | P28: 3207428412 | Q28: javiertordecilla702@gmail.com | R28: 5 | S28: ANTIOQUIA | T28: 659 | U28: SAN JUAN DE URABA | V28: 950400 | W28: COMPLEJO TECNOLOGICO AGROINDUSTRIAL,PECUARIO Y TURISTICO -URABA- | X28: TECNICO EN PRODUCCION AGROPECUARIA | Y28: 3000012 | Z28: 22/05/2024 | AA28: 22/02/2025 | AB28: 23/02/2025 | AC28: 21/08/2025 | AD28: 03/07/2025 | AE28: 46024 | AF28: REGIONAL ANTIOQUIA | AG28: PRODUCTIVA | AH28: 900156264 | AI28: NUEVA EPS | AJ28: 860013816 | AK28: POSITIVA | AL28: 45841.521
A29: Bernardo Brand | B29: 900296617 | C29: AGRICOLA SAN RIOMAR S.A.S | D29: ANTIOQUIA | E29: APARTADO | F29: CARRERA 109 C NO. 100 - 15 EDIFICIO OCÉANO OFICINA 101 | G29: 3116473007 | H29: AGRICOLASANRIOMAR@HOTMAIL.COM | I29: C.C. | J29: 1037468930 | K29: ALTAMIRANDA VENERA | L29: ZARIHT JUDIHT | M29: 24/11/2004 | N29: F | P29: 3124753556 | Q29: zarithaltamiranda57@gmail.com | R29: 5 | S29: ANTIOQUIA | T29: 659 | U29: SAN JUAN DE URABA | V29: 950400 | W29: COMPLEJO TECNOLOGICO AGROINDUSTRIAL,PECUARIO Y TURISTICO -URABA- | X29: TECNICO EN PRODUCCION AGROPECUARIA | Y29: 3000012 | Z29: 22/05/2024 | AA29: 22/02/2025 | AB29: 23/02/2025 | AC29: 21/08/2025 | AD29: 07/07/2025 | AE29: 46028 | AF29: REGIONAL ANTIOQUIA | AG29: PRODUCTIVA | AH29: 890900286 | AI29: SAVIA SALUD E.P.S. | AJ29: 860013816 | AK29: POSITIVA | AL29: 45848.599
A30: Bernardo Brand | B30: 900296617 | C30: AGRICOLA SAN RIOMAR S.A.S | D30: ANTIOQUIA | E30: APARTADO | F30: CARRERA 109 C NO. 100 - 15 EDIFICIO OCÉANO OFICINA 101 | G30: 3116473007 | H30: AGRICOLASANRIOMAR@HOTMAIL.COM | I30: C.C. | J30: 1007834056 | K30: VILLA MARTINEZ | L30: MANUEL ESTEBAN | M30: 09/05/1996 | N30: M | P30: 573105602486 | Q30: villamartinezmanuelesteban@gmail.com | R30: 5 | S30: ANTIOQUIA | T30: 659 | U30: SAN JUAN DE URABA | V30: 950400 | W30: COMPLEJO TECNOLOGICO AGROINDUSTRIAL,PECUARIO Y TURISTICO -URABA- | X30: TECNICO EN PRODUCCION AGROPECUARIA | Y30: 3016710 | Z30: 15/06/2024 | AA30: 15/03/2025 | AB30: 16/03/2025 | AC30: 14/09/2025 | AD30: 07/07/2025 | AE30: 46028 | AF30: REGIONAL ANTIOQUIA | AG30: PRODUCTIVA | AH30: 890900286 | AI30: SAVIA SALUD E.P.S. | AJ30: 860013816 | AK30: POSITIVA | AL30: 45848.599
A31: Bernardo Brand | B31: 900296617 | C31: AGRICOLA SAN RIOMAR S.A.S | D31: ANTIOQUIA | E31: APARTADO | F31: CARRERA 109 C NO. 100 - 15 EDIFICIO OCÉANO OFICINA 101 | G31: 3116473007 | H31: AGRICOLASANRIOMAR@HOTMAIL.COM | I31: T.I. | J31: 1037471796 | K31: SANCHEZ VEGA | L31: YULISA JUDITH | M31: 19/11/2006 | N31: F | P31: 3192793876 | Q31: luiseduardoespitia11@gmail.com | R31: 5 | S31: ANTIOQUIA | T31: 659 | U31: SAN JUAN DE URABA | V31: 950400 | W31: COMPLEJO TECNOLOGICO AGROINDUSTRIAL,PECUARIO Y TURISTICO -URABA- | X31: TECNICO EN PRODUCCION AGROPECUARIA | Y31: 3016710 | Z31: 15/06/2024 | AA31: 15/03/2025 | AB31: 16/03/2025 | AC31: 14/09/2025 | AD31: 07/07/2025 | AE31: 46028 | AF31: REGIONAL ANTIOQUIA | AG31: PRODUCTIVA | AH31: 890900286 | AI31: SAVIA SALUD E.P.S. | AJ31: 860013816 | AK31: POSITIVA | AL31: 45849.745
A32: Carlos Negrete | B32: 900970799 | C32: + MOTOS + REPUESTOS S.A.S | D32: ANTIOQUIA | E32: MEDELLIN | F32: Cra 43 b 16 95 ofi 204 | G32: 300 3519957 | H32: seleccion@masmotos.com.co | I32: C.C. | J32: 1233692934 | K32: CASTRO DURANGO | L32: EDUARD ARLEY | M32: 29/11/1998 | N32: M | P32: 573163178679 | Q32: castrodurangoeduardarley@gmail.com | R32: 5 | S32: ANTIOQUIA | T32: 172 | U32: CHIGORODO | V32: 950400 | W32: COMPLEJO TECNOLOGICO AGROINDUSTRIAL,PECUARIO Y TURISTICO -URABA- | X32: TÉCNICO EN MANTENIMIENTO DE MOTOCICLETAS Y MOTOCARROS. | Y32: 2937357 | Z32: 08/03/2024 | AA32: 08/12/2024 | AB32: 09/12/2024 | AC32: 06/06/2025 | AD32: 10/07/2025 | AE32: 46031 | AF32: REGIONAL ANTIOQUIA | AG32: PRODUCTIVA | AH32: 890900286 | AI32: SAVIA SALUD E.P.S. | AJ32: 800256161 | AK32: ARP SURA | AL32: 45848.674
A33: Abel Valderrama | B33: 900340993 | C33: ADMINISTRACION DE REDES Y PROYECTOS S A S | D33: BOGOTA D.C. | E33: BOGOTA D. C. | F33: Calle 26 No. 102 - 30 Piso 3 Oficina 303 | G33: 6533909 Ext 829 | H33: adredsas@gmail.com | I33: C.C. | J33: 1027959243 | K33: HERNANDEZ MONTES | L33: KAROL JULIANA | M33: 04/07/2005 | N33: F | P33: 3052789949 | Q33: Karoljulianahernandezmontes04@gmail.com | R33: 5 | S33: ANTIOQUIA | T33: 45 | U33: APARTADO | V33: 950400 | W33: COMPLEJO TECNOLOGICO AGROINDUSTRIAL,PECUARIO Y TURISTICO -URABA- | X33: TECNÓLOGO EN IMPLEMENTACION DE INFRAESTRUCTURA DE TECNOLOGIAS DE LA INFORMACION Y LAS COMUNICACIONES | Y33: 2693983 | Z33: 02/02/2023 | AA33: 02/11/2024 | AB33: 03/11/2024 | AC33: 01/05/2025 | AD33: 11/07/2025 | AE33: 46032 | AF33: REGIONAL ANTIOQUIA | AG33: PRODUCTIVA | AH33: 890900286 | AI33: SAVIA SALUD E.P.S. | AJ33: 800256161 | AK33: ARP SURA | AL33: 45849.35
A34: Silvia Chaverra | B34: 900072303 | C34: AGUAS REGIONALES EPM S.A. E.S.P. | D34: ANTIOQUIA | E34: APARTADO | F34: CALLE 97 A NO. 104 - 13 | G34: 8286657 | H34: ESTEBAN.MADERA@aguasregionales.com;maria.torres@aguasregionales.com | I34: C.C. | J34: 1045491428 | K34: VILLEGAS CORDOBBA | L34: JHON FREDY | M34: 09/01/2005 | N34: M | P34: 573015100130 | Q34: jhonfredisvillegascordoba@gmail.com | R34: 5 | S34: ANTIOQUIA | T34: 837 | U34: TURBO | V34: 950400 | W34: COMPLEJO TECNOLOGICO AGROINDUSTRIAL,PECUARIO Y TURISTICO -URABA- | X34: TÉCNICO EN SERVICIOS COMERCIALES Y FINANCIEROS | Y34: 2995116 | Z34: 04/06/2024 | AA34: 04/03/2025 | AB34: 05/03/2025 | AC34: 03/09/2025 | AD34: 14/07/2025 | AE34: 46035 | AF34: REGIONAL ANTIOQUIA | AG34: PRODUCTIVA | AH34: 891600091 | AI34: EPS COMFACHOCO | AJ34: 800226175 | AK34: COLMENA RIESGOS PROFESIONALES | AL34: 45853.315
A35: Yorger Moreno | B35: 70073635 | C35: SIERRA MORENO RUBEN DARIO | D35: ANTIOQUIA | E35: MEDELLIN | F35: calle 4 sur 43a 195 of 214 | G35: 3128512474 | H35: hdanotecanses@hotmail.com | I35: C.C. | J35: 1037122067 | K35: VILLA URREGO | L35: DILAL ESTENIO | M35: 25/01/2007 | N35: M | P35: 3106371213 | Q35: villadilal44@gmail.com | R35: 5 | S35: ANTIOQUIA | T35: 172 | U35: CHIGORODO | V35: 950400 | W35: COMPLEJO TECNOLOGICO AGROINDUSTRIAL,PECUARIO Y TURISTICO -URABA- | X35: TECNÓLOGO EN GESTION AGROEMPRESARIAL | Y35: 2910664 | Z35: 20/02/2024 | AA35: 20/11/2025 | AB35: 21/11/2025 | AC35: 19/05/2026 | AD35: 13/11/2024 | AE35: 46035 | AF35: REGIONAL ANTIOQUIA | AG35: LECTIVA - PRODUCTIVA | AH35: 890900286 | AI35: SAVIA SALUD E.P.S. | AJ35: 999999999 | AK35: No registrada | AL35: 45609.378 | AN35: MUTUO ACUERDO(debe tener aprobación de la institución de formación)
A36: Aldwin Morelo | B36: 900021323 | C36: UNLAB S.A.S | D36: ANTIOQUIA | E36: APARTADO | F36: CARRERA 104 N 98 A - 03 | G36: 8156090 | H36: auxiliargh@unlab.co | I36: C.C. | J36: 1032178318 | K36: SERNA GARCIA | L36: EDWIN FELIPE | M36: 03/03/2006 | N36: M | P36: 3106317136 | Q36: edwinserna408@gmail.com | R36: 5 | S36: ANTIOQUIA | T36: 45 | U36: APARTADO | V36: 950400 | W36: COMPLEJO TECNOLOGICO AGROINDUSTRIAL,PECUARIO Y TURISTICO -URABA- | X36: TECNÓLOGO EN GESTION DE TESORERIA Y RECURSOS FINANCIEROS | Y36: 2826382 | Z36: 02/10/2023 | AA36: 02/07/2025 | AB36: 03/07/2025 | AC36: 31/12/2025 | AD36: 23/07/2025 | AE36: 46040 | AF36: REGIONAL ANTIOQUIA | AG36: PRODUCTIVA | AH36: 900156264 | AI36: NUEVA EPS | AJ36: 800226175 | AK36: COLMENA RIESGOS PROFESIONALES | AL36: 45861.49
A37: Abel Valderrama | B37: 900124689 | C37: FUNDACION SOMA | D37: ANTIOQUIA | E37: CHIGORODO | F37: CR 106 CL 95 | G37: 3116095402 | H37: direccionadministrativa@fundacionsoma.com | I37: C.C. | J37: 1027954769 | K37: DE LA CRUZ CONTRERAS | L37: JIMENA | M37: 05/05/2006 | N37: F | P37: 573017997826 | Q37: jimenacontreras082@gmail.com | R37: 5 | S37: ANTIOQUIA | T37: 147 | U37: CAREPA | V37: 950400 | W37: COMPLEJO TECNOLOGICO AGROINDUSTRIAL,PECUARIO Y TURISTICO -URABA- | X37: TÉCNICO EN SISTEMAS TELEINFORMÁTICOS | Y37: 3077813 | Z37: 16/09/2024 | AA37: 16/06/2025 | AB37: 17/06/2025 | AC37: 15/12/2025 | AD37: 22/07/2025 | AE37: 46043 | AF37: REGIONAL ANTIOQUIA | AG37: PRODUCTIVA | AH37: 901037916 | AI37: ADRES EPS | AJ37: 830025999 | AK37: AGENCIA DE SEGUROS SALUD PLUS LTDA | AL37: 45863.407
A38: Daisy Quejada | B38: 900929172 | C38: ELECTRODOMESTICOS J2 S.A.S. | D38: ANTIOQUIA | E38: SABANETA | F38: CARRERA 44 NO. 67SUR 28 | G38: 6044796767 | H38: claudia.londono@hdaelparaiso.com | I38: C.C. | J38: 1046527657 | K38: TOBON RUBIO | L38: SANTIAGO ANDRES | M38: 07/03/2006 | N38: M | P38: 5743104588 | Q38: santitobon71@gmail.com | R38: 5 | S38: ANTIOQUIA | T38: 837 | U38: TURBO | V38: 950400 | W38: COMPLEJO TECNOLOGICO AGROINDUSTRIAL,PECUARIO Y TURISTICO -URABA- | X38: TECNOLOGO EN GESTION ADMINISTRATIVA | Y38: 2901823 | Z38: 23/01/2024 | AA38: 23/07/2025 | AB38: 24/07/2025 | AC38: 22/01/2026 | AD38: 25/06/2024 | AE38: 46044 | AF38: REGIONAL ANTIOQUIA | AG38: LECTIVA - PRODUCTIVA | AH38: 900156264 | AI38: NUEVA EPS | AJ38: 860013816 | AK38: POSITIVA | AL38: 45468.615
A39: Daisy Quejada | B39: 800131731 | C39: FUNDACIÓN EDUCATIVA ISAIAS DUARTE CANCINO | D39: ANTIOQUIA | E39: APARTADO | F39: Cl 100 #94A - 109 - La chinita | G39: 3015151887 | H39: auxiliarth@diocesisdeapartado.org | I39: T.I. | J39: 1046528287 | K39: MENDOZA RODRIGUEZ | L39: DILANN ALEJANDRO | M39: 28/12/2006 | N39: M | P39: +57 323 4871713 | Q39: dilannmendoza3@gmail.com | R39: 5 | S39: ANTIOQUIA | T39: 837 | U39: TURBO | V39: 950400 | W39: COMPLEJO TECNOLOGICO AGROINDUSTRIAL,PECUARIO Y TURISTICO -URABA- | X39: TECNOLOGO EN GESTION ADMINISTRATIVA | Y39: 2901823 | Z39: 23/01/2024 | AA39: 23/07/2025 | AB39: 24/07/2025 | AC39: 22/01/2026 | AD39: 24/07/2025 | AE39: 46044 | AF39: REGIONAL ANTIOQUIA | AG39: PRODUCTIVA | AH39: 800088702 | AI39: EPS SURA | AJ39: 800256161 | AK39: ARP SURA | AL39: 45866.582
A40: Andrés Felipe Henao | B40: 901331695 | C40: MONTELLANA INGENIERIAS S.A.S | D40: ANTIOQUIA | E40: APARTADO | F40: BAJO DEL OSO SECTOR FINCA LA PRIMAVERA | G40: 3108268453 | H40: MONTELLANAINGENIERIASAS@GMAIL.COM | I40: C.C. | J40: 1027954226 | K40: RAMIREZ ARGEL | L40: DIEGO ALEJANDRO | M40: 18/03/2006 | N40: M | P40: 3117253668 | Q40: diegoalejandroargelramirez@gmail.com | R40: 5 | S40: ANTIOQUIA | T40: 45 | U40: APARTADO | V40: 950400 | W40: COMPLEJO TECNOLOGICO AGROINDUSTRIAL,PECUARIO Y TURISTICO -URABA- | X40: TÉCNICO EN MECANICA DE MAQUINARIA INDUSTRIAL | Y40: 3004048 | Z40: 06/06/2024 | AA40: 06/03/2025 | AB40: 07/03/2025 | AC40: 05/09/2025 | AD40: 24/07/2025 | AE40: 46045 | AF40: REGIONAL ANTIOQUIA | AG40: PRODUCTIVA | AH40: 800088702 | AI40: EPS SURA | AJ40: 800256161 | AK40: ARP SURA | AL40: 45862.35
A41: Paola Londoño | B41: 900700696 | C41: PROMOTORA PALMERA DE ANTIOQUIA S.A.S. | D41: ANTIOQUIA | E41: MEDELLIN | F41: cra.80 calle 80 L-116 CC. Las Playas | G41: 3007104308 | H41: coordinadora.personal1@gmail.com | I41: C.C. | J41: 1038818257 | K41: MADERA NAVARRO | L41: MATIA JOSE | M41: 10/08/1995 | N41: M | P41: 3170585803 | Q41: Matiasjosemadera@gmail.com | R41: 5 | S41: ANTIOQUIA | T41: 172 | U41: CHIGORODO | V41: 950400 | W41: COMPLEJO TECNOLOGICO AGROINDUSTRIAL,PECUARIO Y TURISTICO -URABA- | X41: TECNICO EN PRODUCCION AGROPECUARIA | Y41: 2870669 | Z41: 24/10/2023 | AA41: 24/07/2024 | AB41: 25/07/2024 | AC41: 25/01/2025 | AD41: 30/10/2025 | AE41: 46049 | AF41: REGIONAL ANTIOQUIA | AG41: PRODUCTIVA | AH41: 900156264 | AI41: NUEVA EPS | AJ41: 860028415 | AK41: SEGUROS LA EQUIDAD | AL41: 45965.698
A42: Virtual | B42: 860513077 | C42: FUNDACION UNIVERSITARIA MONSERRATE - UNIMONSERRATE | D42: BOGOTA D.C. | E42: BOGOTA D. C. | F42: Calle 68 No. 62 - 11 | G42: 3902202 | H42: psicologiagho@unimonserrate.edu.co asistentegestionhumana@unimonserrate.edu.co | I42: C.C. | J42: 1016002473 | K42: MATEUS RODRIGUEZ | L42: ZHADEN NATALIA | M42: 38461 | N42: F | P42: 3209627520 | Q42: kalanacamelandia@gmail.com | R42: 11 | S42: BOGOTA D.C. | T42: 1 | U42: BOGOTA D. C. | V42: 950400 | W42: COMPLEJO TECNOLOGICO AGROINDUSTRIAL,PECUARIO Y TURISTICO -URABA- | X42: TECNÓLOGO EN DESARROLLO DE MEDIOS GRAFICOS VISUALES | Y42: 2721326 | Z42: 45012 | AA42: 45653 | AB42: 45654 | AC42: 45834 | AD42: 45840 | AE42: 46050 | AF42: REGIONAL ANTIOQUIA | AG42: PRODUCTIVA | AH42: 830003564 | AI42: EPS FAMISANAR LTDA | AJ42: 800256161 | AK42: ARP SURA | AL42: 45840.62
A43: Silvia Chaverra | B43: 900207854 | C43: H L COMBUSTIBLES S.A.S. | D43: ANTIOQUIA | E43: MEDELLIN | F43: carrera 52 29 49 | G43: 3013308905 | H43: gestionhumana@hlcombustibles.com | I43: C.C. | J43: 1028660043 | K43: RODRIGUEZ CARTAGENA | L43: JEIRDAN | M43: 07/07/2004 | N43: F | P43: 5718274897 | Q43: jeirdanrodriguezcartagena11@gmail.com | R43: 5 | S43: ANTIOQUIA | T43: 837 | U43: TURBO | V43: 950400 | W43: COMPLEJO TECNOLOGICO AGROINDUSTRIAL,PECUARIO Y TURISTICO -URABA- | X43: TÉCNICO EN CONTABILIZACION DE OPERACIONES COMERCIALES Y FINANCIERAS. | Y43: 2855479 | Z43: 02/10/2023 | AA43: 02/07/2024 | AB43: 03/07/2024 | AC43: 03/01/2025 | AD43: 04/03/2025 | AE43: 46050 | AF43: REGIONAL ANTIOQUIA | AG43: PRODUCTIVA | AH43: 890900286 | AI43: SAVIA SALUD E.P.S. | AJ43: 800226175 | AK43: COLMENA RIESGOS PROFESIONALES | AL43: 45720.337 | AN43: Terminación automática por fecha de contrato Automatic Job1
A44: Abel Valderrama | B44: 900645687 | C44: ECOLITE SAS | D44: VALLE | E44: CALI | F44: Calle 41 # 6 -16 Bodega 2 | G44: 3827064 | H44: admin@ecolite.com.co | I44: C.C. | J44: 1045488150 | K44: VILLA DORIA | L44: SANTIAGO | M44: 23/05/2004 | N44: M | P44: 31438448440 | Q44: santiagovd200423@gmail.com | R44: 5 | S44: ANTIOQUIA | T44: 45 | U44: APARTADO | V44: 950400 | W44: COMPLEJO TECNOLOGICO AGROINDUSTRIAL,PECUARIO Y TURISTICO -URABA- | X44: TECNÓLOGO EN ANALISIS Y DESARROLLO DE SOFTWARE. | Y44: 2673007 | Z44: 23/01/2023 | AA44: 23/10/2024 | AB44: 24/10/2024 | AC44: 22/04/2025 | AD44: 29/07/2025 | AE44: 46051 | AF44: REGIONAL ANTIOQUIA | AG44: PRODUCTIVA | AH44: 900156264 | AI44: NUEVA EPS | AJ44: 800256161 | AK44: ARP SURA | AL44: 45867.623
A45: Andrés Felipe Henao | B45: 900469809 | C45: DISAZUCAR BOTERO SAS | D45: ANTIOQUIA | E45: APARTADO | F45: cl 101 98 54 | G45: 3206747839 | H45: alianzaprosst@gmail.com | I45: C.C. | J45: 1001026641 | K45: MURILLO MOSQUERA | L45: YEINER YESID | M45: 37682 | N45: M | P45: 573108446059 | Q45: yeinerymm@icloud.com | R45: 5 | S45: ANTIOQUIA | T45: 45 | U45: APARTADO | V45: 950400 | W45: COMPLEJO TECNOLOGICO AGROINDUSTRIAL,PECUARIO Y TURISTICO -URABA- | X45: TÉCNICO EN MANTENIMIENTO DE LOS MOTORES DIESEL | Y45: 2924199 | Z45: 45397 | AA45: 45736 | AB45: 45737 | AC45: 45920 | AD45: 45839 | AE45: 46052 | AF45: REGIONAL ANTIOQUIA | AG45: PRODUCTIVA | AH45: 900156264 | AI45: NUEVA EPS | AJ45: 800256161 | AK45: ARP SURA | AL45: 45839.582
A46: Aldwin Morelo | B46: 900566554 | C46: DOMINION COLOMBIA SAS | D46: BOGOTA D.C. | E46: BOGOTA D. C. | F46: Av. Cra 45 # 108 27 Edificio Pararelo 108 Torre 2, Piso 4 | G46: 3212547514 | H46: diana.higinio@dominion-global.com | I46: C.C. | J46: 1038806856 | K46: AYAZO BRAVO | L46: YASENIS | M46: 30/10/1990 | N46: F | P46: 3112092487 | Q46: yasenisayazobravo@gmail.com | R46: 5 | S46: ANTIOQUIA | T46: 1 | U46: MEDELLIN | V46: 950400 | W46: COMPLEJO TECNOLOGICO AGROINDUSTRIAL,PECUARIO Y TURISTICO -URABA- | X46: TÉCNICO EN ASISTENCIA PARA LA INTELIGENCIA EMPRESARIAL | Y46: 2965635 | Z46: 15/04/2024 | AA46: 10/12/2024 | AB46: 11/12/2024 | AC46: 10/06/2025 | AD46: 02/08/2025 | AE46: 46054 | AF46: REGIONAL ANTIOQUIA | AG46: PRODUCTIVA | AH46: 901037916 | AI46: ADRES EPS | AJ46: 830025999 | AK46: AGENCIA DE SEGUROS SALUD PLUS LTDA | AL46: 45872.789
A47: Aldwin Morelo | B47: 800118901 | C47: AGROPECUARIA PRAGA S.A. | D47: ANTIOQUIA | E47: RIONEGRO | F47: Mall Comercial Reserva Plaza Cl 47 # 76 30 Oficina 20249 | G47: 3107035407 | H47: sistemadegestion@apraga.co | I47: C.C. | J47: 39415363 | K47: CARTAGENA MORENO | L47: CARMEN ALICIA | M47: 25/08/1975 | N47: F | P47: 3001534583 | Q47: cartagenacarmenalicia@gmail.com | R47: 5 | S47: ANTIOQUIA | T47: 45 | U47: APARTADO | V47: 950400 | W47: COMPLEJO TECNOLOGICO AGROINDUSTRIAL,PECUARIO Y TURISTICO -URABA- | X47: TECNICO EN PRODUCCION AGROPECUARIA | Y47: 3046758 | Z47: 16/08/2024 | AA47: 16/05/2025 | AB47: 17/05/2025 | AC47: 15/11/2025 | AD47: 05/08/2025 | AE47: 46055 | AF47: REGIONAL ANTIOQUIA | AG47: PRODUCTIVA | AH47: 900156264 | AI47: NUEVA EPS | AJ47: 800256161 | AK47: ARP SURA | AL47: 45896.421
A48: Aldwin Morelo | B48: 800032846 | C48: AGROPECUARIA LA GIRA S.A.S. | D48: ANTIOQUIA | E48: MEDELLIN | F48: CALLE 4 SUR NO. 43 A 195 OFICINA 243 | G48: 5247028 | H48: Lagiragrupo@gmail.com | I48: C.C. | J48: 1027949431 | K48: QUIÑONEZ IBARGUEN | L48: NAWIL MATEO | M48: 38563 | N48: M | P48: +57-3126535100 | Q48: mateoquinonez6@gmail.com | R48: 5 | S48: ANTIOQUIA | T48: 45 | U48: APARTADO | V48: 950400 | W48: COMPLEJO TECNOLOGICO AGROINDUSTRIAL,PECUARIO Y TURISTICO -URABA- | X48: TECNÓLOGO EN GESTION DE TESORERIA Y RECURSOS FINANCIEROS | Y48: 2826382 | Z48: 45201 | AA48: 45840 | AB48: 45841 | AC48: 46022 | AD48: 45873 | AE48: 46056 | AF48: REGIONAL ANTIOQUIA | AG48: PRODUCTIVA | AH48: 900156264 | AI48: NUEVA EPS | AJ48: 860013816 | AK48: POSITIVA | AL48: 45888.669
A49: Aldwin Morelo | B49: 811009754 | C49: AGROPECUARIA EL CAPORAL S.A. | D49: ANTIOQUIA | E49: MEDELLIN | F49: Transversal 39B #70-137 | G49: 6044281010 | H49: gestionhumana@avicolacaporal.com | I49: C.C. | J49: 1027953701 | K49: FARIA PEÑA | L49: MICHELL LORENA | M49: 06/02/2006 | N49: F | P49: 573108479060 | Q49: LOREMI0206@GMAIL.COM | R49: 5 | S49: ANTIOQUIA | T49: 45 | U49: APARTADO | V49: 950400 | W49: COMPLEJO TECNOLOGICO AGROINDUSTRIAL,PECUARIO Y TURISTICO -URABA- | X49: TECNÓLOGO EN GESTION DE TESORERIA Y RECURSOS FINANCIEROS | Y49: 2826382 | Z49: 02/10/2023 | AA49: 02/07/2025 | AB49: 03/07/2025 | AC49: 31/12/2025 | AD49: 17/07/2025 | AE49: 46057 | AF49: REGIONAL ANTIOQUIA | AG49: PRODUCTIVA | AH49: 900156264 | AI49: NUEVA EPS | AJ49: 800256161 | AK49: ARP SURA | AL49: 45860.342
A50: Paola Londoño | B50: 900188593 | C50: PUERTO BAHIA COLOMBIA DE URABA S.A. | D50: ANTIOQUIA | E50: TURBO | F50: CENTRO EMPRESARIAL SANTA MARIA PISO 9 | G50: 3043875165 | H50: jrocha@puertoantioquia.com | I50: C.C. | J50: 1002107413 | K50: VELASQUEZ MOLINA | L50: YURLEIDIS | M50: 37912 | N50: F | P50: 573136511038 | Q50: sediegocas@gmail.com | R50: 5 | S50: ANTIOQUIA | T50: 837 | U50: TURBO | V50: 950400 | W50: COMPLEJO TECNOLOGICO AGROINDUSTRIAL,PECUARIO Y TURISTICO -URABA- | X50: TÉCNICO EN RECURSOS HUMANOS . | Y50: 2817199 | Z50: 45146 | AA50: 45420 | AB50: 45421 | AC50: 45603 | AD50: 45874 | AE50: 46057 | AF50: REGIONAL ANTIOQUIA | AG50: PRODUCTIVA | AH50: 900156264 | AI50: NUEVA EPS | AJ50: 800256161 | AK50: ARP SURA | AL50: 45881.688
A51: Jaime Ruiz | B51: 901655062 | C51: KILOTELAS SAS | D51: CORDOBA | E51: MONTERIA | F51: CLL 34 # 1 - 48 CENTRO | G51: 7802613; 3174013553 | H51: INFO@KILO-TELAS.COM.CO - facturacion@kilo-telas.com.co | I51: C.C. | J51: 1028020316 | K51: CARDENAS ECHAVARRIA | L51: DIANA CAROLINA | M51: 14/12/1994 | N51: F | P51: 3117166114 | Q51: cardernascarolina2314@gmail.com | R51: 5 | S51: ANTIOQUIA | T51: 45 | U51: APARTADO | V51: 950400 | W51: COMPLEJO TECNOLOGICO AGROINDUSTRIAL,PECUARIO Y TURISTICO -URABA- | X51: TECNICO EN COMERCIALIZACION DE PRODUCTOS MASIVOS | Y51: 3276936 | Z51: 08/07/2025 | AA51: 08/01/2026 | AB51: 09/01/2026 | AC51: 08/07/2026 | AD51: 26/12/2025 | AE51: 46057 | AF51: REGIONAL ANTIOQUIA | AG51: PRODUCTIVA | AH51: 890900286 | AI51: SAVIA SALUD E.P.S. | AJ51: 860013816 | AK51: POSITIVA | AL51: 46017.394 | AN51: MUTUO ACUERDO(debe tener aprobación de la institución de formación) | AO51: El aprendiz manifiesta no sentirse en condiciones de salud, se solicita visita y aprobacion del funcionario por parte del sena jaime ruiz quien aprueba la terminacion del contrato por mutuo acuerdo.
A52: Daisy Quejada | B52: 830095213 | C52: ORGANIZACION TERPEL S A | D52: BOGOTA D.C. | E52: BOGOTA D. C. | F52: CARRERA 7 # 75-51 | G52: 3183238397 | H52: suray.tovar@terpel.com | I52: C.C. | J52: 1075098099 | K52: PALACIOS BELTRAN | L52: MERILYS YINETH | M52: 20/09/2006 | N52: F | P52: 3205784929-3205966063 | Q52: merilispalacios@gmail.com | R52: 5 | S52: ANTIOQUIA | T52: 837 | U52: TURBO | V52: 950400 | W52: COMPLEJO TECNOLOGICO AGROINDUSTRIAL,PECUARIO Y TURISTICO -URABA- | X52: TECNOLOGO EN GESTION ADMINISTRATIVA | Y52: 2901823 | Z52: 23/01/2024 | AA52: 23/07/2025 | AB52: 24/07/2025 | AC52: 22/01/2026 | AD52: 12/02/2025 | AE52: 46058 | AF52: REGIONAL ANTIOQUIA | AG52: LECTIVA - PRODUCTIVA | AH52: 900156264 | AI52: NUEVA EPS | AJ52: 830025999 | AK52: AGENCIA DE SEGUROS SALUD PLUS LTDA | AL52: 45702.598
A53: Yolanda Berrío | B53: 8426173 | C53: MIGUEL CEREN TRESPALACIOS | D53: ANTIOQUIA | E53: TURBO | F53: kl 8 via turbo necocli | G53: 3105262151 | H53: reginoceren@gmail.com | I53: C.C. | J53: 1045527238 | K53: ROSARIO MARTINEZ | L53: SINDY PAOLA | M53: 36199 | N53: F | P53: 3214510011 | Q53: martinezsindipaola804@gmail.com | R53: 5 | S53: ANTIOQUIA | T53: 837 | U53: TURBO | V53: 950400 | W53: COMPLEJO TECNOLOGICO AGROINDUSTRIAL,PECUARIO Y TURISTICO -URABA- | X53: TECNICO EN PRODUCCION AGROPECUARIA | Y53: 3012698 | Z53: 45460 | AA53: 45733 | AB53: 45734 | AC53: 45916 | AD53: 45875 | AE53: 46058 | AF53: REGIONAL ANTIOQUIA | AG53: PRODUCTIVA | AH53: 900156264 | AI53: NUEVA EPS | AJ53: 860013816 | AK53: POSITIVA | AL53: 45877.565
A54: Yolanda Berrío | B54: 8426173 | C54: MIGUEL CEREN TRESPALACIOS | D54: ANTIOQUIA | E54: TURBO | F54: kl 8 via turbo necocli | G54: 3105262151 | H54: reginoceren@gmail.com | I54: C.C. | J54: 1028019357 | K54: MORENO OQUENDO | L54: MARINELLA | M54: 34552 | N54: F | P54: 317 7407732 | Q54: mmorenooquendo@gmail.com | R54: 5 | S54: ANTIOQUIA | T54: 45 | U54: APARTADO | V54: 950400 | W54: COMPLEJO TECNOLOGICO AGROINDUSTRIAL,PECUARIO Y TURISTICO -URABA- | X54: TECNICO EN PRODUCCION AGROPECUARIA | Y54: 3012698 | Z54: 45460 | AA54: 45733 | AB54: 45734 | AC54: 45916 | AD54: 45875 | AE54: 46058 | AF54: REGIONAL ANTIOQUIA | AG54: PRODUCTIVA | AH54: 890900286 | AI54: SAVIA SALUD E.P.S. | AJ54: 860013816 | AK54: POSITIVA | AL54: 45877.567
A55: Abel Valderrama | B55: 901263737 | C55: CELUCENTRAL TELECOMUNICACIONES ZOMAC S.A.S. | D55: ANTIOQUIA | E55: APARTADO | F55: CR 99 96-30 | G55: 3217740878 | H55: nidiadolomarquez@gmail.com | I55: C.C. | J55: 1027950746 | K55: OSPINO MOSQUERA | L55: LUISA FERNANDA | M55: 38571 | N55: F | P55: 3012791891 | Q55: luisafernandaospinomosquera@gmail.com | R55: 5 | S55: ANTIOQUIA | T55: 45 | U55: APARTADO | V55: 950400 | W55: COMPLEJO TECNOLOGICO AGROINDUSTRIAL,PECUARIO Y TURISTICO -URABA- | X55: TECNÓLOGO EN ANALISIS Y DESARROLLO DE SOFTWARE. | Y55: 2826357 | Z55: 45201 | AA55: 45840 | AB55: 45841 | AC55: 46022 | AD55: 45881 | AE55: 46064 | AF55: REGIONAL ANTIOQUIA | AG55: PRODUCTIVA | AH55: 890900286 | AI55: SAVIA SALUD E.P.S. | AJ55: 800256161 | AK55: ARP SURA | AL55: 45881.431
A56: Abel Valderrama | B56: 811018568 | C56: FUNDACION DIOCESANA COMPARTIR | D56: ANTIOQUIA | E56: APARTADO | F56: Apartadó Antioquia, barrio Chinita, Cra. 98 # 100 - 51 | G56: 3136738408 | H56: recursoshumanoscompartir@gmail.com | I56: C.C. | J56: 1063276094 | K56: RODRIGUEZ BELLO | L56: ALEJANDRA | M56: 37462 | N56: F | P56: 5718587521 | Q56: rodribelalexa@gmail.com | R56: 5 | S56: ANTIOQUIA | T56: 837 | U56: TURBO | V56: 950400 | W56: COMPLEJO TECNOLOGICO AGROINDUSTRIAL,PECUARIO Y TURISTICO -URABA- | X56: TECNICO EN ATENCION INTEGRAL A LA PRIMERA INFANCIA | Y56: 2878845 | Z56: 45313 | AA56: 45587 | AB56: 45588 | AC56: 45768 | AD56: 45839 | AE56: 46065 | AF56: REGIONAL ANTIOQUIA | AG56: PRODUCTIVA | AH56: 890900286 | AI56: SAVIA SALUD E.P.S. | AJ56: 860013816 | AK56: POSITIVA | AL56: 45839.342
A57: Lucy Pernett | B57: 901022172 | C57: SOLANO ESCUDERO S.A.S. | D57: CORDOBA | E57: MONTERIA | F57: AV CIRCUNVALAR 8 A 110 | G57: 7923414 | H57: gestionhumana@disprolacteos.com.co | I57: C.C. | J57: 1028032175 | K57: RIVERA IZQUIERDO | L57: NEIDER | M57: 17/08/1997 | N57: M | P57: 573218437559 | Q57: neiderrivera199@gmail.com | R57: 5 | S57: ANTIOQUIA | T57: 45 | U57: APARTADO | V57: 950400 | W57: COMPLEJO TECNOLOGICO AGROINDUSTRIAL,PECUARIO Y TURISTICO -URABA- | X57: TECNICO EN COMERCIALIZACION DE PRODUCTOS MASIVOS | Y57: 2973694 | Z57: 24/04/2024 | AA57: 24/10/2024 | AB57: 25/10/2024 | AC57: 23/04/2025 | AD57: 13/02/2025 | AE57: 46065 | AF57: REGIONAL ANTIOQUIA | AG57: PRODUCTIVA | AH57: 901037916 | AI57: ADRES EPS | AJ57: 830025999 | AK57: AGENCIA DE SEGUROS SALUD PLUS LTDA | AL57: 45707.452
A58: Yorger Moreno | B58: 901122707 | C58: HACIENDA SAN BARTOLO S.A.S. ZOMAC | D58: ANTIOQUIA | E58: MEDELLIN | F58: cra 43 a #1a sur -69 | G58: 2664112 | H58: asistentenomina@lahaciendasas.com.co | I58: C.C. | J58: 32293347 | K58: ROCHA GONZALEZ | L58: YADITH MILENA | M58: 28802 | N58: F | P58: 3225593172 | Q58: rochisa32@hotmail.com | R58: 5 | S58: ANTIOQUIA | T58: 172 | U58: CHIGORODO | V58: 950400 | W58: COMPLEJO TECNOLOGICO AGROINDUSTRIAL,PECUARIO Y TURISTICO -URABA- | X58: TECNICO EN CONSERVACION DE RECURSOS NATURALES | Y58: 3051477 | Z58: 45524 | AA58: 45797 | AB58: 45798 | AC58: 45980 | AD58: 45883 | AE58: 46066 | AF58: REGIONAL ANTIOQUIA | AG58: PRODUCTIVA | AH58: 800088702 | AI58: EPS SURA | AJ58: 800256161 | AK58: ARP SURA | AL58: 45890.467
A59: Carlos Negrete | B59: 901124653 | C59: REFRIWILLIAM SAS | D59: ATLANTICO | E59: BARRANQUILLA | F59: calle 24 # 11-83 | G59: 3155711928 | H59: asistente.admin@refriwilliams.com | I59: C.C. | J59: 1045491145 | K59: VITOLA NISPERUZA | L59: MARIA FERNANDA | M59: 38356 | N59: F | P59: 3218858731 | Q59: Vitolamaria491@gmail.com | R59: 5 | S59: ANTIOQUIA | T59: 837 | U59: TURBO | V59: 950400 | W59: COMPLEJO TECNOLOGICO AGROINDUSTRIAL,PECUARIO Y TURISTICO -URABA- | X59: TÉCNICO EN MANTENIMIENTO DE EQUIPOS DE AIRE ACONDICIONADO Y REFRIGERACION | Y59: 2877679 | Z59: 45313 | AA59: 45587 | AB59: 45588 | AC59: 45768 | AD59: 45884 | AE59: 46068 | AF59: REGIONAL ANTIOQUIA | AG59: PRODUCTIVA | AH59: 901037916 | AI59: ADRES EPS | AJ59: 830025999 | AK59: AGENCIA DE SEGUROS SALUD PLUS LTDA | AL59: 45884.711
A60: Marcelino Gonzalez | B60: 900700696 | C60: PROMOTORA PALMERA DE ANTIOQUIA S.A.S. | D60: ANTIOQUIA | E60: MEDELLIN | F60: cra.80 calle 80 L-116 CC. Las Playas | G60: 3007104308 | H60: coordinadora.personal1@gmail.com | I60: C.C. | J60: 1037119470 | K60: PALACIO REGINO | L60: MARIA JOSE | M60: 06/09/2004 | N60: F | P60: 3218379227 | Q60: SARAPALACIO2016@GMAIL.COM | R60: 5 | S60: ANTIOQUIA | T60: 172 | U60: CHIGORODO | V60: 950400 | W60: COMPLEJO TECNOLOGICO AGROINDUSTRIAL,PECUARIO Y TURISTICO -URABA- | X60: TECNÓLOGO EN GESTION DE LA PRODUCCION AGRICOLA | Y60: 2826366 | Z60: 18/07/2022 | AA60: 18/04/2024 | AB60: 19/04/2024 | AC60: 17/10/2024 | AD60: 13/08/2025 | AE60: 46069 | AF60: REGIONAL ANTIOQUIA | AG60: PRODUCTIVA | AH60: 900156264 | AI60: NUEVA EPS | AJ60: 860028415 | AK60: SEGUROS LA EQUIDAD | AL60: 45889.519
A61: Julian Moreno | B61: 811024238 | C61: BANAEXPORT S.A.S. | D61: ANTIOQUIA | E61: MEDELLIN | F61: Crr 101 N 73A-09 | G61: 3117487867 | H61: iris.david@banaexport.co | I61: C.C. | J61: 1001028872 | K61: TUBERQUIA MAZO | L61: LUISA ALEJANDRA | M61: 16/09/2002 | N61: F | P61: 3043618773 | Q61: luisatuberquia6090@gmail.com | R61: 5 | S61: ANTIOQUIA | T61: 45 | U61: APARTADO | V61: 950400 | W61: COMPLEJO TECNOLOGICO AGROINDUSTRIAL,PECUARIO Y TURISTICO -URABA- | X61: TÉCNICO EN SALUD PUBLICA | Y61: 3047491 | Z61: 19/08/2024 | AA61: 19/08/2025 | AB61: 20/08/2025 | AC61: 18/02/2026 | AD61: 14/07/2025 | AE61: 46071 | AF61: REGIONAL ANTIOQUIA | AG61: PRODUCTIVA | AH61: 890900286 | AI61: SAVIA SALUD E.P.S. | AJ61: 800256161 | AK61: ARP SURA | AL61: 45852.602
A62: Julian Moreno | B62: 900044503 | C62: AGRICOLA IBIZA S.A. | D62: ANTIOQUIA | E62: MEDELLIN | F62: CARRERA 43A No. 19-17 EDIFICIO BLOCK EMPRESARIAL PISO 12 | G62: 3110433 2683407 | H62: dir.gestionhumana@banafrut.com | I62: C.C. | J62: 1028009158 | K62: MARTINEZ PINEDA | L62: LINA BEATRIZ | M62: 09/09/1992 | N62: F | P62: 3105359093 -3113605550 | Q62: linamartinezpineda18@gmail.com | R62: 5 | S62: ANTIOQUIA | T62: 45 | U62: APARTADO | V62: 950400 | W62: COMPLEJO TECNOLOGICO AGROINDUSTRIAL,PECUARIO Y TURISTICO -URABA- | X62: TÉCNICO EN SALUD PUBLICA | Y62: 3047491 | Z62: 19/08/2024 | AA62: 19/08/2025 | AB62: 20/08/2025 | AC62: 18/02/2026 | AD62: 24/07/2025 | AE62: 46071 | AF62: REGIONAL ANTIOQUIA | AG62: LECTIVA - PRODUCTIVA | AH62: 800088702 | AI62: EPS SURA | AJ62: 800256161 | AK62: ARP SURA | AL62: 45862.583
A63: Dina Dorado | B63: 890926412 | C63: LA HACIENDA S.A.S. | D63: ANTIOQUIA | E63: MEDELLIN | F63: cra 43 a 1a sur 69 | G63: 3103891346 - 3207971897 | H63: nomina@lahaciendasas.com.co | I63: C.C. | J63: 1063717959 | K63: AVILA RANGEL | L63: LEANDRA MARIA | M63: 16/04/2003 | N63: F | P63: 3234339826 | Q63: leandravila26@gmail.com | R63: 23 | S63: CORDOBA | T63: 670 | U63: SAN ANDRES DE SOTAVENTO | V63: 950400 | W63: COMPLEJO TECNOLOGICO AGROINDUSTRIAL,PECUARIO Y TURISTICO -URABA- | X63: TECNOLOGO EN PRODUCCION AGROPECUARIA ECOLOGICA | Y63: 2914179 | Z63: 19/02/2024 | AA63: 19/08/2025 | AB63: 20/08/2025 | AC63: 19/02/2026 | AD63: 22/07/2024 | AE63: 46072 | AF63: REGIONAL ANTIOQUIA | AG63: LECTIVA - PRODUCTIVA | AH63: 800088702 | AI63: EPS SURA | AJ63: 800256161 | AK63: ARP SURA | AL63: 45539.324
A64: Dina Dorado | B64: 890903329 | C64: BANANERAS DE URABA S.A.S | D64: ANTIOQUIA | E64: MEDELLIN | F64: calle 4 sur 43a-195 | G64: 5608350 | H64: nomina@bananeras.com | I64: C.C. | J64: 1027952936 | K64: GEORGE LOAIZA | L64: YORLADYS | M64: 27/02/2006 | N64: F | P64: 3136410132 | Q64: ruizyorladys507@gmail.com | R64: 5 | S64: ANTIOQUIA | T64: 45 | U64: APARTADO | V64: 950400 | W64: COMPLEJO TECNOLOGICO AGROINDUSTRIAL,PECUARIO Y TURISTICO -URABA- | X64: TECNOLOGO EN PRODUCCION AGROPECUARIA ECOLOGICA | Y64: 2914179 | Z64: 19/02/2024 | AA64: 19/08/2025 | AB64: 20/08/2025 | AC64: 19/02/2026 | AD64: 17/07/2024 | AE64: 46072 | AF64: REGIONAL ANTIOQUIA | AG64: LECTIVA - PRODUCTIVA | AH64: 890900286 | AI64: SAVIA SALUD E.P.S. | AJ64: 860013816 | AK64: POSITIVA | AL64: 45540.619
A65: Dina Dorado | B65: 890906148 | C65: LOS HALCONES S.A | D65: ANTIOQUIA | E65: MEDELLIN | F65: Cl 3 # 66 - 63 Hangar 79 | G65: 3113420957 | H65: auxiliarcontable.nomina@halcones.co | I65: C.C. | J65: 1027940208 | K65: ZAPATA BRAN | L65: YAN CARLOS | M65: 03/12/2003 | N65: M | P65: 5718280512 | Q65: yancarloszapatabran@gmail.com | R65: 5 | S65: ANTIOQUIA | T65: 45 | U65: APARTADO | V65: 950400 | W65: COMPLEJO TECNOLOGICO AGROINDUSTRIAL,PECUARIO Y TURISTICO -URABA- | X65: TECNOLOGO EN PRODUCCION AGROPECUARIA ECOLOGICA | Y65: 2914179 | Z65: 19/02/2024 | AA65: 19/08/2025 | AB65: 20/08/2025 | AC65: 19/02/2026 | AD65: 01/07/2024 | AE65: 46072 | AF65: REGIONAL ANTIOQUIA | AG65: LECTIVA - PRODUCTIVA | AH65: 890900286 | AI65: SAVIA SALUD E.P.S. | AJ65: 800256161 | AK65: ARP SURA | AL65: 45540.673
A66: Dina Dorado | B66: 811009784 | C66: BANANERAS FUEGO VERDE S.A. | D66: ANTIOQUIA | E66: MEDELLIN | F66: Cr 99 entre cl 99b 100 | G66: 8156235 - 3162510723 | H66: bienestarlaboral@grupo20sa.com | I66: C.C. | J66: 1027946467 | K66: SUAREZ PUERTA | L66: LEIDY MARCELA | M66: 17/01/2005 | N66: F | P66: 3137804222 | Q66: luisfelipeleudoparra@gmail.com | R66: 5 | S66: ANTIOQUIA | T66: 837 | U66: TURBO | V66: 950400 | W66: COMPLEJO TECNOLOGICO AGROINDUSTRIAL,PECUARIO Y TURISTICO -URABA- | X66: TECNOLOGO EN PRODUCCION AGROPECUARIA ECOLOGICA | Y66: 2914179 | Z66: 19/02/2024 | AA66: 19/08/2025 | AB66: 20/08/2025 | AC66: 19/02/2026 | AD66: 18/11/2024 | AE66: 46072 | AF66: REGIONAL ANTIOQUIA | AG66: LECTIVA - PRODUCTIVA | AH66: 900156264 | AI66: NUEVA EPS | AJ66: 860013816 | AK66: POSITIVA | AL66: 45616.372
A67: Paola Londoño | B67: 901678347 | C67: MAXIMAX SUPERMERCADOS ASOCIADOS ZOMAC SAS | D67: ANTIOQUIA | E67: TURBO | F67: CALLE 101 11 23 | G67: 3044903372 | H67: maximaxauxiliarthsst@gmail.com | I67: C.C. | J67: 1033367029 | K67: OVIEDO DIAZ | L67: MAYRA ANDREA | M67: 38237 | N67: F | P67: 3246229214 | Q67: Mayraandreaoviedodiaz294@gmail.com | R67: 5 | S67: ANTIOQUIA | T67: 51 | U67: ARBOLETES | V67: 950400 | W67: COMPLEJO TECNOLOGICO AGROINDUSTRIAL,PECUARIO Y TURISTICO -URABA- | X67: TÉCNICO EN ASISTENCIA PARA LA INTELIGENCIA EMPRESARIAL | Y67: 2989290 | Z67: 45426 | AA67: 45640 | AB67: 45641 | AC67: 45821 | AD67: 45888 | AE67: 46072 | AF67: REGIONAL ANTIOQUIA | AG67: PRODUCTIVA | AH67: 890900286 | AI67: SAVIA SALUD E.P.S. | AJ67: 800256161 | AK67: ARP SURA | AL67: 45888.951
A68: Yolanda Berrío | B68: 890906148 | C68: LOS HALCONES S.A | D68: ANTIOQUIA | E68: MEDELLIN | F68: Cl 3 # 66 - 63 Hangar 79 | G68: 3113420957 | H68: auxiliarcontable.nomina@halcones.co | I68: C.C. | J68: 1131619076 | K68: BAILARIN BAILARIN | L68: LUIS ALBERTO | M68: 31391 | N68: M | P68: 3146299428 | Q68: bailarinbailarinluisalberto@gmail.com | R68: 5 | S68: ANTIOQUIA | T68: 45 | U68: APARTADO | V68: 950400 | W68: COMPLEJO TECNOLOGICO AGROINDUSTRIAL,PECUARIO Y TURISTICO -URABA- | X68: TECNOLOGO EN PRODUCCION AGROPECUARIA ECOLOGICA | Y68: 2914179 | Z68: 45341 | AA68: 45888 | AB68: 45889 | AC68: 46072 | AD68: 45882 | AE68: 46072 | AF68: REGIONAL ANTIOQUIA | AG68: LECTIVA - PRODUCTIVA | AH68: 800249241 | AI68: E.P.S. COOSALUD | AJ68: 800256161 | AK68: ARP SURA | AL68: 45888.528
A69: Abel Valderrama | B69: 901122707 | C69: HACIENDA SAN BARTOLO S.A.S. ZOMAC | D69: ANTIOQUIA | E69: MEDELLIN | F69: cra 43 a #1a sur -69 | G69: 2664112 | H69: asistentenomina@lahaciendasas.com.co | I69: C.C. | J69: 1138074335 | K69: PESTANA GALLEGO | L69: ANGELLY SOFIA | M69: 03/02/2005 | N69: F | P69: 3116063577 | Q69: tsuarez774@gmail.com | R69: 5 | S69: ANTIOQUIA | T69: 172 | U69: CHIGORODO | V69: 950400 | W69: COMPLEJO TECNOLOGICO AGROINDUSTRIAL,PECUARIO Y TURISTICO -URABA- | X69: TECNICO EN SISTEMAS | Y69: 2775351 | Z69: 10/07/2023 | AA69: 10/04/2024 | AB69: 11/04/2024 | AC69: 09/10/2024 | AD69: 28/01/2025 | AE69: 46075 | AF69: REGIONAL ANTIOQUIA | AG69: PRODUCTIVA | AH69: 890900286 | AI69: SAVIA SALUD E.P.S. | AJ69: 830025999 | AK69: AGENCIA DE SEGUROS SALUD PLUS LTDA | AL69: 45720.419 | AN69: Terminación automática por fecha de contrato Automatic Job1
A70: Carlos Negrete | B70: 900970799 | C70: + MOTOS + REPUESTOS S.A.S | D70: ANTIOQUIA | E70: MEDELLIN | F70: Cra 43 b 16 95 ofi 204 | G70: 300 3519957 | H70: seleccion@masmotos.com.co | I70: C.C. | J70: 1027959770 | K70: VARGAS CORREA | L70: JUNIOR ANDRES | M70: 25/11/2006 | N70: M | P70: 573147362427 | Q70: juniorvargas1905@gmail.com | R70: 5 | S70: ANTIOQUIA | T70: 45 | U70: APARTADO | V70: 950400 | W70: COMPLEJO TECNOLOGICO AGROINDUSTRIAL,PECUARIO Y TURISTICO -URABA- | X70: TÉCNICO EN MANTENIMIENTO DE MOTOCICLETAS Y MOTOCARROS. | Y70: 3059404 | Z70: 26/08/2024 | AA70: 25/07/2025 | AB70: 26/07/2025 | AC70: 24/01/2026 | AD70: 25/08/2025 | AE70: 46077 | AF70: REGIONAL ANTIOQUIA | AG70: PRODUCTIVA | AH70: 900156264 | AI70: NUEVA EPS | AJ70: 800256161 | AK70: ARP SURA | AL70: 45895.735
A71: Carlos Negrete | B71: 901513108 | C71: SEA WORK ZOMAC S.A.S | D71: ANTIOQUIA | E71: APARTADO | F71: clle 106c#108-55 | G71: 3148203580 | H71: bomontoya@protel.com.co | I71: C.C. | J71: 1193589212 | K71: CARO SANCHEZ | L71: JHOSUAR SANTIAGO | M71: 17/04/2002 | N71: M | P71: 3225617996 | Q71: elisacuadrado12@gmail.com | R71: 5 | S71: ANTIOQUIA | T71: 45 | U71: APARTADO | V71: 950400 | W71: COMPLEJO TECNOLOGICO AGROINDUSTRIAL,PECUARIO Y TURISTICO -URABA- | X71: TÉCNICO EN MANTENIMIENTO DE EQUIPOS DE AIRE ACONDICIONADO Y REFRIGERACION | Y71: 2998431 | Z71: 08/07/2024 | AA71: 08/04/2025 | AB71: 09/04/2025 | AC71: 07/10/2025 | AD71: 26/08/2025 | AE71: 46079 | AF71: REGIONAL ANTIOQUIA | AG71: PRODUCTIVA | AH71: 800088702 | AI71: EPS SURA | AJ71: 800256161 | AK71: ARP SURA | AL71: 45896.697
A72: Yolanda Berrío | B72: 890926938 | C72: AGROPECUARIA GRUPO 20 S.A | D72: ANTIOQUIA | E72: ENVIGADO | F72: Cr 99 entre cl 99b 100 | G72: 8156235 - 3162510723 | H72: bienestarlaboral@grupo20sa.com | I72: C.C. | J72: 1045494847 | K72: DURANGO RADA | L72: BRANDY YULEISY | M72: 19/05/2003 | N72: F | P72: 3246707877 | Q72: durangoradayuleisy@gmail.com | R72: 5 | S72: ANTIOQUIA | T72: 837 | U72: TURBO | V72: 950400 | W72: COMPLEJO TECNOLOGICO AGROINDUSTRIAL,PECUARIO Y TURISTICO -URABA- | X72: TECNICO EN PRODUCCION AGROPECUARIA | Y72: 3012698 | Z72: 17/06/2024 | AA72: 17/03/2025 | AB72: 18/03/2025 | AC72: 16/10/2025 | AD72: 27/08/2025 | AE72: 46079 | AF72: REGIONAL ANTIOQUIA | AG72: PRODUCTIVA | AH72: 800249241 | AI72: E.P.S. COOSALUD | AJ72: 860013816 | AK72: POSITIVA | AL72: 45898.387
A73: Daisy Quejada | B73: 900165604 | C73: L.A.S. SUCESORES S.A.S | D73: ANTIOQUIA | E73: MEDELLIN | F73: carrera 25a # 1-31 ofi 915 | G73: +5743213209 | H73: lassucesores@gmail.com | I73: C.C. | J73: 1124049183 | K73: RUIZ RODRIGUEZ | L73: JULIETH PAOLA | M73: 31/07/1994 | N73: F | P73: 3003571312 | Q73: JALIIMETHTORORUIZ@HOTMAIL.COM | R73: 5 | S73: ANTIOQUIA | T73: 172 | U73: CHIGORODO | V73: 950400 | W73: COMPLEJO TECNOLOGICO AGROINDUSTRIAL,PECUARIO Y TURISTICO -URABA- | X73: TECNOLOGO GESTION CONTABLE Y DE INFORMACION FINANCIERA | Y73: 2877824 | Z73: 22/01/2024 | AA73: 21/10/2025 | AB73: 22/10/2025 | AC73: 21/04/2026 | AD73: 01/05/2024 | AE73: 46079 | AF73: REGIONAL ANTIOQUIA | AG73: LECTIVA - PRODUCTIVA | AH73: 900156264 | AI73: NUEVA EPS | AJ73: 860013816 | AK73: POSITIVA | AL73: 45428.697
A74: Silvia Chaverra | B74: 811018568 | C74: FUNDACION DIOCESANA COMPARTIR | D74: ANTIOQUIA | E74: APARTADO | F74: Apartadó Antioquia, barrio Chinita, Cra. 98 # 100 - 51 | G74: 3136738408 | H74: recursoshumanoscompartir@gmail.com | I74: C.C. | J74: 1028032295 | K74: CALDERON PALACIOS | L74: MELISA | M74: 14/04/1997 | N74: F | P74: 3128432587 - 3145281136 | Q74: m-lisa06@hotmail.com | R74: 5 | S74: ANTIOQUIA | T74: 45 | U74: APARTADO | V74: 950400 | W74: COMPLEJO TECNOLOGICO AGROINDUSTRIAL,PECUARIO Y TURISTICO -URABA- | X74: TECNICO EN ATENCION INTEGRAL A LA PRIMERA INFANCIA | Y74: 2932599 | Z74: 15/04/2024 | AA74: 15/01/2025 | AB74: 16/01/2025 | AC74: 14/07/2025 | AD74: 27/09/2025 | AE74: 46080 | AF74: REGIONAL ANTIOQUIA | AG74: PRODUCTIVA | AH74: 890900286 | AI74: SAVIA SALUD E.P.S. | AJ74: 860013816 | AK74: POSITIVA | AL74: 45929.638
A75: Andres Cataño | B75: 800021137 | C75: AGRICOLA SARA PALMA S.A. | D75: ANTIOQUIA | E75: MEDELLIN | F75: apartado | G75: 3103531316 | H75: Mzapata@sarapalma.com.co | I75: C.C. | J75: 1121526493 | K75: SALGADO VILLADIEGO | L75: YERELIS PAOLA | M75: 15/01/2004 | N75: F | P75: 3217241759 | Q75: yerelispaolasalgadovilladiego@gmail.com | R75: 5 | S75: ANTIOQUIA | T75: 147 | U75: CAREPA | V75: 950400 | W75: COMPLEJO TECNOLOGICO AGROINDUSTRIAL,PECUARIO Y TURISTICO -URABA- | X75: TECNICO EN PRODUCCION AGROPECUARIA | Y75: 2822839 | Z75: 10/08/2023 | AA75: 10/05/2024 | AB75: 11/05/2024 | AC75: 11/11/2024 | AD75: 01/09/2025 | AE75: 46080 | AF75: REGIONAL ANTIOQUIA | AG75: PRODUCTIVA | AH75: 800249241 | AI75: E.P.S. COOSALUD | AJ75: 800256161 | AK75: ARP SURA | AL75: 45901.381
A76: Maria del Rosari Jaramillo | B76: 890900842 | C76: CAJA DE COMPENSACION FAMILIAR COMFENALCO ANTIOQUIA | D76: ANTIOQUIA | E76: MEDELLIN | F76: Cr 50 #53-43 | G76: 3183700787 | H76: natalia.montes@comfenalcoantioquia.com | I76: C.C. | J76: 39429113 | K76: MADRID IZQUIERDO | L76: MADELEINE | M76: 19/08/1984 | N76: F | P76: 3042219457-------- 3024517365 | Q76: izquierdomadrid5@gmail.com | R76: 5 | S76: ANTIOQUIA | T76: 837 | U76: TURBO | V76: 950400 | W76: COMPLEJO TECNOLOGICO AGROINDUSTRIAL,PECUARIO Y TURISTICO -URABA- | X76: TECNICO EN ATENCION INTEGRAL A LA PRIMERA INFANCIA | Y76: 3030218 | Z76: 05/08/2024 | AA76: 05/05/2025 | AB76: 06/05/2025 | AC76: 04/11/2025 | AD76: 01/09/2025 | AE76: 46081 | AF76: REGIONAL ANTIOQUIA | AG76: PRODUCTIVA | AH76: 800088702 | AI76: EPS SURA | AJ76: 860002503 | AK76: COMPAÑÍA DE SEGUROS BOLIVAR | AL76: 45903.36
A77: Maria del Rosari Jaramillo | B77: 890900842 | C77: CAJA DE COMPENSACION FAMILIAR COMFENALCO ANTIOQUIA | D77: ANTIOQUIA | E77: MEDELLIN | F77: Cr 50 #53-43 | G77: 3183700787 | H77: natalia.montes@comfenalcoantioquia.com | I77: C.C. | J77: 1001021690 | K77: GONZALES ARTEAGA | L77: NEYDI NAYHELLY | M77: 29/07/2001 | N77: F | P77: 573116968683 | Q77: gherell01@gmail.com | R77: 5 | S77: ANTIOQUIA | T77: 45 | U77: APARTADO | V77: 950400 | W77: COMPLEJO TECNOLOGICO AGROINDUSTRIAL,PECUARIO Y TURISTICO -URABA- | X77: TECNICO EN ATENCION INTEGRAL A LA PRIMERA INFANCIA | Y77: 3030218 | Z77: 05/08/2024 | AA77: 05/05/2025 | AB77: 06/05/2025 | AC77: 04/11/2025 | AD77: 01/09/2025 | AE77: 46081 | AF77: REGIONAL ANTIOQUIA | AG77: PRODUCTIVA | AH77: 800088702 | AI77: EPS SURA | AJ77: 860002503 | AK77: COMPAÑÍA DE SEGUROS BOLIVAR | AL77: 45903.361
A78: Carlos Negrete | B78: 890904224 | C78: C I UNION DE BANANEROS DE URABA S A. UNIBAN | D78: ANTIOQUIA | E78: MEDELLIN | F78: calle 52 #47-42 Edf Coltejer Piso 15 | G78: 3165398213 | H78: hquirogal@uniban.com.co; jgonzaleze@uniban.com.co; jmaya@uniban.com.co | I78: C.C. | J78: 1039652540 | K78: PANESSO MORENO | L78: DANIEL STIVEN | M78: 07/01/2006 | N78: M | P78: 3225430452 | Q78: panessomorenodanielstiven@gmail.com | R78: 5 | S78: ANTIOQUIA | T78: 45 | U78: APARTADO | V78: 950400 | W78: COMPLEJO TECNOLOGICO AGROINDUSTRIAL,PECUARIO Y TURISTICO -URABA- | X78: TÉCNICO EN MANTENIMIENTO DE EQUIPOS DE AIRE ACONDICIONADO Y REFRIGERACION | Y78: 2998431 | Z78: 08/07/2024 | AA78: 08/04/2025 | AB78: 09/04/2025 | AC78: 07/10/2025 | AD78: 01/09/2025 | AE78: 46081 | AF78: REGIONAL ANTIOQUIA | AG78: PRODUCTIVA | AH78: 890900286 | AI78: SAVIA SALUD E.P.S. | AJ78: 830025999 | AK78: AGENCIA DE SEGUROS SALUD PLUS LTDA | AL78: 45902.846
A79: Paola Londoño | B79: 900519645 | C79: INVERSIONES Y SUMINISTROS ASTRAL DEL CARIBE S.A.S. | D79: ANTIOQUIA | E79: TURBO | F79: cll 30 cra 28 miramar | G79: 3183349605 | H79: isacar1981@hotmail.com | I79: C.C. | J79: 1035152924 | K79: PINTO MARTINEZ | L79: JUAN DIEGO | M79: 06/03/2006 | N79: M | P79: 573144586935 | Q79: juanpinto1035@gmail.com | R79: 5 | S79: ANTIOQUIA | T79: 51 | U79: ARBOLETES | V79: 950400 | W79: COMPLEJO TECNOLOGICO AGROINDUSTRIAL,PECUARIO Y TURISTICO -URABA- | X79: TÉCNICO EN ASISTENCIA PARA LA INTELIGENCIA EMPRESARIAL | Y79: 2989290 | Z79: 14/05/2024 | AA79: 14/12/2024 | AB79: 15/12/2024 | AC79: 13/06/2025 | AD79: 01/09/2025 | AE79: 46081 | AF79: REGIONAL ANTIOQUIA | AG79: PRODUCTIVA | AH79: 890900286 | AI79: SAVIA SALUD E.P.S. | AJ79: 8600021846 | AK79: AXA COLPATRIA | AL79: 45901.392
A80: Julian Moreno | B80: 901615181 | C80: AGROGREENLAND S.A.S. | D80: ANTIOQUIA | E80: ENVIGADO | F80: KM1 Salida Medellín | G80: 8280422-exte6446 | H80: luisa.estrada@greenland.co | I80: C.C. | J80: 1032178256 | K80: MENDOZA URREGO | L80: MARELVIS | M80: 20/03/2006 | N80: F | P80: 3242691107 | Q80: mendozaurregomarelvis@gmail.com | R80: 5 | S80: ANTIOQUIA | T80: 45 | U80: APARTADO | V80: 950400 | W80: COMPLEJO TECNOLOGICO AGROINDUSTRIAL,PECUARIO Y TURISTICO -URABA- | X80: TÉCNICO EN SALUD PUBLICA | Y80: 3047491 | Z80: 19/08/2024 | AA80: 19/08/2025 | AB80: 20/08/2025 | AC80: 18/02/2026 | AD80: 01/09/2025 | AE80: 46081 | AF80: REGIONAL ANTIOQUIA | AG80: PRODUCTIVA | AH80: 900156264 | AI80: NUEVA EPS | AJ80: 800256161 | AK80: ARP SURA | AL80: 45902.67
A81: Yolanda Berrío | B81: 800003697 | C81: RESTREPO ESTRADA S.A.S. | D81: ANTIOQUIA | E81: MEDELLIN | F81: Carrera 43 a #1 sur 31 EDIFICIO BBVA | G81: 3008944043 | H81: auxnomina@agricolamonaco.com | I81: C.C. | J81: 1007413532 | K81: CORREA HERNANDEZ | L81: OSCAR ANDRES | M81: 28/08/2002 | N81: M | P81: 3226055336 | Q81: oscarandres2808@icloud.com | R81: 5 | S81: ANTIOQUIA | T81: 172 | U81: CHIGORODO | V81: 950400 | W81: COMPLEJO TECNOLOGICO AGROINDUSTRIAL,PECUARIO Y TURISTICO -URABA- | X81: TECNICO EN SISTEMAS AGROPECUARIOS ECOLOGICOS. | Y81: 3004049 | Z81: 05/06/2024 | AA81: 14/04/2025 | AB81: 15/04/2025 | AC81: 13/10/2025 | AD81: 01/09/2025 | AE81: 46081 | AF81: REGIONAL ANTIOQUIA | AG81: PRODUCTIVA | AH81: 900156264 | AI81: NUEVA EPS | AJ81: 860013816 | AK81: POSITIVA | AL81: 45901.448
... A89: Paola Londoño | B89: 18532717 | C89: GUILLERMO ANTONIO AGUDELO GIRALDO | D89: ANTIOQUIA | E89: ARBOLETES | F89: ARBOLETES | G89: 3015030150 | H89: vymderechointegral@gmail.com | I89: C.C. | J89: 45691466 | K89: PACHECO VARGAS | L89: MAYRA ESTHER | M89: 21/12/1978 | N89: F | P89: 3138661901 | Q89: mayrapachecovargas78@gmail.com | R89: 5 | S89: ANTIOQUIA | T89: 51 | U89: ARBOLETES | V89: 950400 | W89: COMPLEJO TECNOLOGICO AGROINDUSTRIAL,PECUARIO Y TURISTICO -URABA- | X89: TÉCNICO EN CONTABILIZACION DE OPERACIONES COMERCIALES Y FINANCIERAS. | Y89: 2851382 | Z89: 26/09/2023 | AA89: 26/06/2024 | AB89: 27/06/2024 | AC89: 27/12/2024 | AD89: 09/09/2025 | AE89: 46089 | AF89: REGIONAL ANTIOQUIA | AG89: PRODUCTIVA | AH89: 800088702 | AI89: EPS SURA | AJ89: 800226175 | AK89: COLMENA RIESGOS PROFESIONALES | AL89: 45914.82
A90: Daisy Quejada | B90: 811009784 | C90: BANANERAS FUEGO VERDE S.A. | D90: ANTIOQUIA | E90: MEDELLIN | F90: Cr 99 entre cl 99b 100 | G90: 8156235 - 3162510723 | H90: bienestarlaboral@grupo20sa.com | I90: C.C. | J90: 1027955353 | K90: QUIROZ DELGADO | L90: MELISA DAYANNA | M90: 39103 | N90: F | P90: 3106062963 | Q90: melisadayannaquirozdelgado@gmail.com | R90: 5 | S90: ANTIOQUIA | T90: 837 | U90: TURBO | V90: 950400 | W90: COMPLEJO TECNOLOGICO AGROINDUSTRIAL,PECUARIO Y TURISTICO -URABA- | X90: TECNOLOGO GESTION CONTABLE Y DE INFORMACION FINANCIERA | Y90: 2924348 | Z90: 45397 | AA90: 46037 | AB90: 46038 | AC90: 46217 | AD90: 45782 | AE90: 46090 | AF90: REGIONAL ANTIOQUIA | AG90: LECTIVA - PRODUCTIVA | AH90: 890903407 | AI90: EPS MEDICINA PREPAGADA SURAMERICANA | AJ90: 860013816 | AK90: POSITIVA | AL90: 45782.327
A91: Abel Valderrama | B91: 811018869 | C91: SUBASTAS GANADERAS DEL URABÁ GRANDE S.A. SUGANAR S,A, | D91: ANTIOQUIA | E91: CHIGORODO | F91: Km1 vía al mar | G91: 8253699 | H91: recursoshumanos@suganar.com | I91: T.I. | J91: 1027961624 | K91: ALEMAN SILGADO | L91: FERNANDA YULIETH | M91: 15/01/2007 | N91: F | P91: 573207265631 | Q91: alemanfernanda225@gmail.com | R91: 5 | S91: ANTIOQUIA | T91: 147 | U91: CAREPA | V91: 950400 | W91: COMPLEJO TECNOLOGICO AGROINDUSTRIAL,PECUARIO Y TURISTICO -URABA- | X91: TÉCNICO EN SISTEMAS TELEINFORMÁTICOS | Y91: 2974583 | Z91: 23/04/2024 | AA91: 23/01/2025 | AB91: 24/01/2025 | AC91: 22/07/2025 | AD91: 10/09/2025 | AE91: 46091 | AF91: REGIONAL ANTIOQUIA | AG91: PRODUCTIVA | AH91: 900156264 | AI91: NUEVA EPS | AJ91: 800256161 | AK91: ARP SURA | AL91: 45929.357
A92: Jaime Ruiz | B92: 901106003 | C92: LM INVESTMENT HOUSE S A S | D92: BOGOTA D.C. | E92: BOGOTA D. C. | F92: Avenida Calle 26 No. 102 - 20 Edificio Buró 26 Oficia 303 | G92: 3162660891 | H92: lm.talentohumano@outlook.com | I92: C.C. | J92: 1001029094 | K92: NEGRETE FABRA | L92: YERLY | M92: 29/06/1996 | N92: F | P92: 3234980306 | Q92: yerlisn22@gmail.com | R92: 5 | S92: ANTIOQUIA | T92: 45 | U92: APARTADO | V92: 950400 | W92: COMPLEJO TECNOLOGICO AGROINDUSTRIAL,PECUARIO Y TURISTICO -URABA- | X92: TECNICO EN COMERCIALIZACION DE PRODUCTOS MASIVOS | Y92: 3276936 | Z92: 08/07/2025 | AA92: 08/01/2026 | AB92: 09/01/2026 | AC92: 08/07/2026 | AD92: 23/09/2025 | AE92: 46093 | AF92: REGIONAL ANTIOQUIA | AG92: PRODUCTIVA | AH92: 900156264 | AI92: NUEVA EPS | AJ92: 860013816 | AK92: POSITIVA | AL92: 45923.396
A93: Silvia Chaverra | B93: 800032846 | C93: AGROPECUARIA LA GIRA S.A.S. | D93: ANTIOQUIA | E93: MEDELLIN | F93: CALLE 4 SUR NO. 43 A 195 OFICINA 243 | G93: 5247028 | H93: Lagiragrupo@gmail.com | I93: C.C. | J93: 1032178979 | K93: PATIÑO CARDONA | L93: YEISON JAVIER | M93: 26/09/2006 | N93: M | P93: 573122481902 | Q93: patinoyeison63@gmail.com | R93: 5 | S93: ANTIOQUIA | T93: 45 | U93: APARTADO | V93: 950400 | W93: COMPLEJO TECNOLOGICO AGROINDUSTRIAL,PECUARIO Y TURISTICO -URABA- | X93: TECNOLOGO GESTION CONTABLE Y DE INFORMACION FINANCIERA | Y93: 2901802 | Z93: 15/12/2023 | AA93: 15/09/2025 | AB93: 16/09/2025 | AC93: 14/03/2026 | AD93: 23/07/2025 | AE93: 46095 | AF93: REGIONAL ANTIOQUIA | AG93: LECTIVA - PRODUCTIVA | AH93: 890900286 | AI93: SAVIA SALUD E.P.S. | AJ93: 860013816 | AK93: POSITIVA | AL93: 45862.605
A94: Silvia Chaverra | B94: 800198020 | C94: CARNES CASABLANCA S.A.S. | D94: ANTIOQUIA | E94: MEDELLIN | F94: CALLE 72 NO. 64 - 155 | G94: 4416777 ext. 125 | H94: laura.gonzalez@carnescasablanca.com | I94: C.C. | J94: 1027962016 | K94: GARCIA QUEJADA | L94: NICOLE ANDREA | M94: 22/05/2007 | N94: F | P94: 3128324013 | Q94: nicolegarciagarciaquejada@gmail.com | R94: 5 | S94: ANTIOQUIA | T94: 45 | U94: APARTADO | V94: 950400 | W94: COMPLEJO TECNOLOGICO AGROINDUSTRIAL,PECUARIO Y TURISTICO -URABA- | X94: TECNOLOGO GESTION CONTABLE Y DE INFORMACION FINANCIERA | Y94: 2901802 | Z94: 15/12/2023 | AA94: 15/09/2025 | AB94: 16/09/2025 | AC94: 14/03/2026 | AD94: 01/09/2025 | AE94: 46095 | AF94: REGIONAL ANTIOQUIA | AG94: LECTIVA - PRODUCTIVA | AH94: 900156264 | AI94: NUEVA EPS | AJ94: 8600021846 | AK94: AXA COLPATRIA | AL94: 45902.33
A95: Silvia Chaverra | B95: 800046226 | C95: HEINSOHN BUSINESS TECHNOLOGY S.A BIC - HEINSOHN S.A BIC | D95: BOGOTA D.C. | E95: BOGOTA D. C. | F95: Carrera 13 No. 82 - 49 Piso 6 | G95: 9172172 - 3112408499 | H95: contabilidad@heinsohn.com.co | I95: C.C. | J95: 1027959016 | K95: LOPEZ HIDALGO | L95: ANA ALEXANDRA | M95: 16/11/2006 | N95: F | P95: 3042643422 | Q95: alelopez16ema@gmail.com | R95: 5 | S95: ANTIOQUIA | T95: 45 | U95: APARTADO | V95: 950400 | W95: COMPLEJO TECNOLOGICO AGROINDUSTRIAL,PECUARIO Y TURISTICO -URABA- | X95: TECNOLOGO GESTION CONTABLE Y DE INFORMACION FINANCIERA | Y95: 2901802 | Z95: 15/12/2023 | AA95: 15/09/2025 | AB95: 16/09/2025 | AC95: 14/03/2026 | AD95: 16/09/2025 | AE95: 46095 | AF95: REGIONAL ANTIOQUIA | AG95: PRODUCTIVA | AH95: 890900286 | AI95: SAVIA SALUD E.P.S. | AJ95: 800256161 | AK95: ARP SURA | AL95: 45916.495
A96: Andrés Felipe Henao | B96: 890937195 | C96: RODAR Y RODAR LTDA | D96: ANTIOQUIA | E96: MEDELLIN | F96: Cl. 45a #60 37 | G96: 3022131828 | H96: gestionhumana@gruporodar.com / contabilidad2@gruporodar.com | I96: C.C. | J96: 1045511877 | K96: VELASQUEZ PADILLA | L96: ANA MARIA | M96: 20/08/1992 | N96: F | P96: 3104307134 | Q96: lunamarcela2106@gmail.com | R96: 5 | S96: ANTIOQUIA | T96: 45 | U96: APARTADO | V96: 950400 | W96: COMPLEJO TECNOLOGICO AGROINDUSTRIAL,PECUARIO Y TURISTICO -URABA- | X96: TÉCNICO EN MECANICA DE MAQUINARIA INDUSTRIAL | Y96: 2924270 | Z96: 15/04/2024 | AA96: 28/02/2025 | AB96: 01/03/2025 | AC96: 01/09/2025 | AD96: 16/09/2025 | AE96: 46095 | AF96: REGIONAL ANTIOQUIA | AG96: PRODUCTIVA | AH96: 900156264 | AI96: NUEVA EPS | AJ96: 800256161 | AK96: ARP SURA | AL96: 45945.706
A97: Silvia Chaverra | B97: 890903329 | C97: BANANERAS DE URABA S.A.S | D97: ANTIOQUIA | E97: MEDELLIN | F97: calle 4 sur 43a-195 | G97: 5608350 | H97: nomina@bananeras.com | I97: C.C. | J97: 1040358401 | K97: GENES VILLAR | L97: YONIER DAVID | M97: 27/12/2006 | N97: M | P97: 5712222222 | Q97: yonierdavidgenesvillar@gmail.com | R97: 5 | S97: ANTIOQUIA | T97: 147 | U97: CAREPA | V97: 950400 | W97: COMPLEJO TECNOLOGICO AGROINDUSTRIAL,PECUARIO Y TURISTICO -URABA- | X97: TECNOLOGO GESTION CONTABLE Y DE INFORMACION FINANCIERA | Y97: 2901802 | Z97: 15/12/2023 | AA97: 15/09/2025 | AB97: 16/09/2025 | AC97: 16/03/2026 | AD97: 11/02/2025 | AE97: 46095 | AF97: REGIONAL ANTIOQUIA | AG97: LECTIVA - PRODUCTIVA | AH97: 900156264 | AI97: NUEVA EPS | AJ97: 860013816 | AK97: POSITIVA | AL97: 45702.481
A98: Silvia Chaverra | B98: 811009784 | C98: BANANERAS FUEGO VERDE S.A. | D98: ANTIOQUIA | E98: MEDELLIN | F98: Cr 99 entre cl 99b 100 | G98: 8156235 - 3162510723 | H98: bienestarlaboral@grupo20sa.com | I98: C.C. | J98: 1027958247 | K98: PEREZ USUGA | L98: JUAN CAMILO | M98: 38998 | N98: M | P98: 3106414826 | Q98: perezusugajuancamilo@gmail.com | R98: 5 | S98: ANTIOQUIA | T98: 147 | U98: CAREPA | V98: 950400 | W98: COMPLEJO TECNOLOGICO AGROINDUSTRIAL,PECUARIO Y TURISTICO -URABA- | X98: TECNOLOGO GESTION CONTABLE Y DE INFORMACION FINANCIERA | Y98: 2901802 | Z98: 45275 | AA98: 45915 | AB98: 45916 | AC98: 46095 | AD98: 45782 | AE98: 46096 | AF98: REGIONAL ANTIOQUIA | AG98: LECTIVA - PRODUCTIVA | AH98: 900156264 | AI98: NUEVA EPS | AJ98: 860013816 | AK98: POSITIVA | AL98: 45782.326
A99: Abel Valderrama | B99: 900654696 | C99: NUEVO MUNDO OLEICO SAS | D99: ANTIOQUIA | E99: MEDELLIN | F99: CRA 48A # 16SUR-86 | G99: 3137070 | H99: AUXNOMINA5@CITROPICAL.COM | I99: C.C. | J99: 1046528764 | K99: MORENO BARRIOS | L99: YAIR | M99: 29/05/2007 | N99: M | P99: 573008325670 | Q99: yairmoreno2020a2@gmail.com | R99: 5 | S99: ANTIOQUIA | T99: 147 | U99: CAREPA | V99: 950400 | W99: COMPLEJO TECNOLOGICO AGROINDUSTRIAL,PECUARIO Y TURISTICO -URABA- | X99: TÉCNICO EN SISTEMAS TELEINFORMÁTICOS | Y99: 2923819 | Z99: 15/04/2024 | AA99: 15/01/2025 | AB99: 16/01/2025 | AC99: 14/07/2025 | AD99: 26/08/2025 | AE99: 46097 | AF99: REGIONAL ANTIOQUIA | AG99: PRODUCTIVA | AH99: 900156264 | AI99: NUEVA EPS | AJ99: 800256161 | AK99: ARP SURA | AL99: 45897.397
A100: Abel Valderrama | B100: 890929329 | C100: SUPERMERCADO LOS IBAÑEZ Y COMPAÑÍA S.A. | D100: ANTIOQUIA | E100: APARTADO | F100: CALLE 99 No 102-55 Barrio Ortiz | G100: 3128322234 | H100: IBANEZORTIZ103@GMAIL.COM | I100: C.C. | J100: 1045517678 | K100: GALINDO PADILLA | L100: LUNIS PATRICIA | M100: 05/10/1994 | N100: F | P100: 3161768377 | Q100: yairantoniperez1237@gmail.com | R100: 5 | S100: ANTIOQUIA | T100: 837 | U100: TURBO | V100: 950400 | W100: COMPLEJO TECNOLOGICO AGROINDUSTRIAL,PECUARIO Y TURISTICO -URABA- | X100: TÉCNICO EN SISTEMAS TELEINFORMÁTICOS | Y100: 2975578 | Z100: 24/04/2024 | AA100: 24/01/2025 | AB100: 25/01/2025 | AC100: 23/07/2025 | AD100: 19/09/2025 | AE100: 46099 | AF100: REGIONAL ANTIOQUIA | AG100: PRODUCTIVA | AH100: 901037916 | AI100: ADRES EPS | AJ100: 830025999 | AK100: AGENCIA DE SEGUROS SALUD PLUS LTDA | AL100: 45919.385
A101: Yolanda Berrío | B101: 800021137 | C101: AGRICOLA SARA PALMA S.A. | D101: ANTIOQUIA | E101: MEDELLIN | F101: apartado | G101: 3103531316 | H101: Mzapata@sarapalma.com.co | I101: C.C. | J101: 1192740073 | K101: REYES BERRIO | L101: CRISTINA | M101: 21/01/2002 | N101: F | P101: 573117429292 | Q101: reyesberriocristina02@gmail.com | R101: 5 | S101: ANTIOQUIA | T101: 837 | U101: TURBO | V101: 950400 | W101: COMPLEJO TECNOLOGICO AGROINDUSTRIAL,PECUARIO Y TURISTICO -URABA- | X101: TECNICO EN PRODUCCION AGROPECUARIA | Y101: 3012698 | Z101: 17/06/2024 | AA101: 17/03/2025 | AB101: 18/03/2025 | AC101: 16/09/2025 | AD101: 15/09/2025 | AE101: 46100 | AF101: REGIONAL ANTIOQUIA | AG101: PRODUCTIVA | AH101: 900156264 | AI101: NUEVA EPS | AJ101: 800256161 | AK101: ARP SURA | AL101: 45915.425
A102: Andres Cataño | B102: 811024238 | C102: BANAEXPORT S.A.S. | D102: ANTIOQUIA | E102: MEDELLIN | F102: Crr 101 N 73A-09 | G102: 3117487867 | H102: iris.david@banaexport.co | I102: C.C. | J102: 1040357799 | K102: BERNA SÁNCHEZ | L102: WENDY VALERIA | M102: 27/10/2006 | N102: F | P102: 573104373077 | Q102: valeriaberna7@gmail.com | R102: 5 | S102: ANTIOQUIA | T102: 147 | U102: CAREPA | V102: 950400 | W102: COMPLEJO TECNOLOGICO AGROINDUSTRIAL,PECUARIO Y TURISTICO -URABA- | X102: TECNICO EN PRODUCCION AGROPECUARIA | Y102: 3185541 | Z102: 25/03/2025 | AA102: 25/12/2025 | AB102: 26/12/2025 | AC102: 24/06/2026 | AD102: 15/09/2025 | AE102: 46101 | AF102: REGIONAL ANTIOQUIA | AG102: LECTIVA - PRODUCTIVA | AH102: 900156264 | AI102: NUEVA EPS | AJ102: 800256161 | AK102: ARP SURA | AL102: 45916.467
A103: Virtual | B103: 899999094 | C103: EMPRESA DE ACUEDUCTO Y ALCANTARILLADO DE BOGOTA - E.S.P. - E.A.A.B - E.S.P | D103: BOGOTA D.C. | E103: BOGOTA D. C. | F103: Calle 24 No. 37 - 15 | G103: 3447000 ext. 4543 | H103: anieves@acueducto.com.co | I103: C.C. | J103: 1019007799 | K103: SALAZAR NAVARRETE | L103: DIANA CAROLINA | M103: 05/07/1986 | N103: F | P103: 3214291248 | Q103: aronda1986@live.com | R103: 11 | S103: BOGOTA D.C. | T103: 1 | U103: BOGOTA D. C. | V103: 950400 | W103: COMPLEJO TECNOLOGICO AGROINDUSTRIAL,PECUARIO Y TURISTICO -URABA- | X103: TÉCNICO EN ATENCION INTEGRAL AL CLIENTE | Y103: 2977539 | Z103: 14/05/2024 | AA103: 14/02/2025 | AB103: 15/02/2025 | AC103: 13/08/2025 | AD103: 22/09/2025 | AE103: 46102 | AF103: REGIONAL ANTIOQUIA | AG103: PRODUCTIVA | AH103: 83011383 | AI103: ALIANSALUD EPS | AJ103: 860013816 | AK103: POSITIVA | AL103: 45923.658
A104: Andres Cataño | B104: 900795390 | C104: INVERAGRO EL CÁMBULO S.A.S. | D104: ANTIOQUIA | E104: MEDELLIN | F104: Cra 48A # 16sur-86, Ed Plex, P-11 | G104: 3147943830 | H104: auxnomina5@citropical.com | I104: C.C. | J104: 1001027820 | K104: ALVAREZ MANCO | L104: ANIS ELENA | M104: 26/03/2002 | N104: F | P104: 3218952848 | Q104: aniselenaa@gmail.com | R104: 5 | S104: ANTIOQUIA | T104: 147 | U104: CAREPA | V104: 950400 | W104: COMPLEJO TECNOLOGICO AGROINDUSTRIAL,PECUARIO Y TURISTICO -URABA- | X104: TECNICO EN TECNICO EN PRODUCCION AGROPECUARIA | Y104: 3047204 | Z104: 19/08/2024 | AA104: 19/05/2025 | AB104: 20/05/2025 | AC104: 18/11/2025 | AD104: 23/09/2025 | AE104: 46103 | AF104: REGIONAL ANTIOQUIA | AG104: PRODUCTIVA | AH104: 890900286 | AI104: SAVIA SALUD E.P.S. | AJ104: 860013816 | AK104: POSITIVA | AL104: 45924.743
A105: Abel Valderrama | B105: 900207854 | C105: H L COMBUSTIBLES S.A.S. | D105: ANTIOQUIA | E105: MEDELLIN | F105: carrera 52 29 49 | G105: 3013308905 | H105: gestionhumana@hlcombustibles.com | I105: C.C. | J105: 1040353619 | K105: JIMENEZ RODRIGUEZ | L105: VALENTINA | M105: 30/04/2005 | N105: F | P105: 573136491196 | Q105: valentina.jr3005@gmail.com | R105: 5 | S105: ANTIOQUIA | T105: 147 | U105: CAREPA | V105: 950400 | W105: COMPLEJO TECNOLOGICO AGROINDUSTRIAL,PECUARIO Y TURISTICO -URABA- | X105: TÉCNICO EN SISTEMAS TELEINFORMÁTICOS | Y105: 2974583 | Z105: 23/04/2024 | AA105: 23/01/2025 | AB105: 24/01/2025 | AC105: 22/07/2025 | AD105: 23/09/2025 | AE105: 46103 | AF105: REGIONAL ANTIOQUIA | AG105: PRODUCTIVA | AH105: 890900286 | AI105: SAVIA SALUD E.P.S. | AJ105: 800226175 | AK105: COLMENA RIESGOS PROFESIONALES | AL105: 45923.317
A106: Paola Londoño | B106: 900206408 | C106: TEAM COMUNICATIONS S.A. | D106: ANTIOQUIA | E106: MEDELLIN | F106: Cl 33 65c 47 | G106: 3145380679 | H106: nomina@teamcomunicaciones.com | I106: C.C. | J106: 1007872957 | K106: BERROCAL MENA | L106: BRAYAN ANDRES | M106: 07/03/2003 | N106: M | P106: 3206198014 | Q106: brayanberrocal2024@gmail.com | R106: 5 | S106: ANTIOQUIA | T106: 45 | U106: APARTADO | V106: 950400 | W106: COMPLEJO TECNOLOGICO AGROINDUSTRIAL,PECUARIO Y TURISTICO -URABA- | X106: TÉCNICO EN SERVICIOS COMERCIALES Y FINANCIEROS | Y106: 3013096 | Z106: 13/06/2024 | AA106: 30/04/2025 | AB106: 01/05/2025 | AC106: 30/10/2026 | AD106: 24/09/2025 | AE106: 46104 | AF106: REGIONAL ANTIOQUIA | AG106: PRODUCTIVA | AH106: 890900286 | AI106: SAVIA SALUD E.P.S. | AJ106: 800256161 | AK106: ARP SURA | AL106: 45925.578
A107: Silvia Chaverra | B107: 900428395 | C107: EXPERTOS TECNOLOGICOS S.A.S. | D107: ANTIOQUIA | E107: MEDELLIN | F107: cra 63 c 42 39 | G107: 5011991 | H107: auxcontable@expertech.com.co | I107: C.C. | J107: 1025887251 | K107: OSORIO SIERRA | L107: JACKELINE ANDREA | M107: 21/02/2006 | N107: F | P107: 3226654149 | Q107: osoriojackeline020@gmail.com | R107: 5 | S107: ANTIOQUIA | T107: 45 | U107: APARTADO | V107: 950400 | W107: COMPLEJO TECNOLOGICO AGROINDUSTRIAL,PECUARIO Y TURISTICO -URABA- | X107: TECNOLOGO GESTION CONTABLE Y DE INFORMACION FINANCIERA | Y107: 2901802 | Z107: 15/12/2023 | AA107: 15/09/2025 | AB107: 16/09/2025 | AC107: 14/03/2026 | AD107: 24/09/2025 | AE107: 46104 | AF107: REGIONAL ANTIOQUIA | AG107: PRODUCTIVA | AH107: 901037916 | AI107: ADRES EPS | AJ107: 830025999 | AK107: AGENCIA DE SEGUROS SALUD PLUS LTDA | AL107: 45937.641
...

Sheet Diferente a contrato
A1: ASIGNACIÓN DE INSTRUCTOR DE SEGUIMIENTO A APRENDICES CON ETAPA PRÁCTICA REGISTRADA DIFERENTE DE CONTRATO DE APRENDIZAJE | C1: ISABELA
A3: INSTRUCTOR SEGUIMIENTO | B3: ALTERNATIVA | C3: CORREO ELECTRONICO APRENDIZ | D3: TIPO DE DOCUMENTO | E3: NUMERO DE DOCUMENTO | F3: PRIMER APELLIDO | G3: SEGUNDO APELLIDO | H3: NOMBRES | I3: NOMBRE APRENDIZ | J3: SEXO (M ó F) | K3: DEPARTAMENTO RESIDENCIA | L3: MUNICIPIO RESIDENCIA | M3: DIRECCION RESIDENCIA APRENDIZ | N3: CELULAR O TELÉFONO FIJO | O3: EPS APRENDIZ | P3: FICHA | Q3: NOMBRE PROGRAMA | R3: MODALIDAD | S3: FECHA INICIO ETAPA PRODUCTIVA | T3: FECHA FIN ETAPA PRODUCTIVA | U3: NOMBRE DE LA EMPRESA | V3: DIRECCIÓN DE LA EMPRESA | W3: CIUDAD O MUNICIPIO | X3: CORREO ELECTRONICO EMPRESA | Y3: RESPONSABLE APRENDIZ | Z3: CELULAR O TELÉFOO FIJO
A4: Virtual | B4: Pasantía | C4: YUGOBU18@HOTMAIL.COM | D4: cc | E4: 1047417092 | F4: GOMEZ | G4: BURGOS | H4: YURLEIDIS | I4: Yurleidis Gomez Burgos | J4: F | K4: BOLÍVAR | L4: APARTADÓ | M4: BARRIO SANTANDER | N4: 3145818737 | O4: MUTUAL SER | P4: 2977539 | Q4: ATENCION INTEGRAL AL CLIENTE | R4: VIRTUAL | S4: 0 | T4: 0 | U4: ESE HOSPITAL LOCAL MAHATES | V4: BARRIO CENTELLA CALLE 1 N° 42-124 | W4: MAHATES | X4: HLMAHATES@OUTLOOK.COM | Y4: ROSANA MEDINA PEREZ | Z4: 3205446997
A5: Virtual | B5: Pasantía | C5: juanpablo08d@yahoo.es | D5: CC | E5: 74083718 | F5: ROA | G5: MONTAÑEZ | H5: JUAN PABLO | I5: Juan Pablo Roa Montañez | J5: M | K5: BOYACÁ | L5: APARTADÓ | M5: Calle 2 # 7 - 93 | N5: 3115652438 | O5: SANITAS | P5: 2834805 | Q5: ANALISIS Y DESARROLLO DE SOFTWARE. | R5: VIRTUAL | S5: 0 | T5: 0 | U5: REWDEV SAS | V5: Cr 73 57 R 15 sur | W5: BOGOTÁ | X5: management.rewdev@gmail.com | Y5: HAROLD DUQUE CASTAÑEDA | Z5: 3193342993
A6: Virtual | B6: Vinc. Lab. | C6: isalu1983@hotmail.com | D6: CC | E6: 30668995 | F6: CABRERA | G6: DE HOYOS | H6: YURIS PAOLA | I6: Yuris Paola Cabrera De Hoyos | J6: F | K6: ANTIOQUIA | L6: APARTADÓ | M6: CR 99C # 48B - 40 | N6: 3103507849 | O6: Sura | P6: 3185840 | Q6: ATENCION INTEGRAL AL CLIENTE | R6: VIRTUAL | S6: 0 | T6: 0 | U6: Colombia Móvil S.A. E.S.P | V6: Crra 50 # 96-12 | W6: BOGOTA | X6: adm.personal@tigo.com.co | Y6: SAIDA BENITEZ ARRIETA | Z6: 6046251505
A7: Carlos Negrete | B7: Pasantía | C7: neyrubiodavid@gmail.com | D7: cc | E7: 1028030695 | F7: RUBIO | G7: DAVID | H7: YISNEY | I7: Yisney Rubio David | J7: F | K7: ANTIOQUIA | L7: APARTADÓ | M7: calle 104D Carrera 96B | N7: 3106534305 | O7: Savia | P7: 2775376 | Q7: SUPERVISIÓN DE REDES DE DISTRIBUCIÓN DE ENERGÍA ELÉCTRICA | R7: PRESENCIAL | S7: 0 | T7: 0 | U7: STANDARD CONNECTION SAS | V7: CALLE 49B #99B-115 INTERIOR 205 | W7: MEDELLIN | X7: standardconnectionsas@gmail.com | Y7: Nacira Jimenez | Z7: 3126421889
A8: Virtual | B8: Vinc. Lab. | C8: juanmedina0718@gmail.com | D8: CC | E8: 1017181818 | F8: MEDINA | G8: VALENCIA | H8: JUAN CAMILO | I8: Juan Camilo Medina Valencia | J8: M | K8: VALLE DEL CAUCA | L8: CALI | M8: CR 46A # 43-79 | N8: 3214563431 | O8: NUEVA EPS | P8: 3069862 | Q8: ATENCION INTEGRAL AL CLIENTE | R8: VIRTUAL | S8: 16/09/2024 | T8: 45753 | U8: vinilos y estucos del valle | V8: Cra. 8 #72b-12 | W8: valle del cauca | X8: marketingdigital@vinilosyestucos.com | Y8: Edwin Moreno | Z8: 3122907680
A9: Silvia Chaverra | B9: Pasantía | C9: tatiibernal1998@gmail.com | D9: CC | E9: 1028035150 | F9: BERNAL | G9: TERAN | H9: INGRID TATIANA | I9: Ingrid Tatiana Bernal Teran | J9: F | K9: ANTIOQUIA | L9: APARTADO | M9: BARRIO OBRERO, BLOQUE 4 MANZANA 43 CASA 19 | N9: 3003269959 | O9: SURA | P9: 3013096 | Q9: SERVICIOS COMERCIALES Y FINANCIEROS | R9: PRESENCIAL | S9: 45839 | T9: 45992 | U9: PROMOTORA HOTELES URABA S.A.S | V9: CRA 100 # 88-21 EDIFICIO SANTA MARIA | W9: APARTADO | X9: JUAN.PALENCIA@ACCOR.COM | Y9: JUAN PALENCIA | Z9: 3205449784
A10: Lucy Pernett | B10: Vinc. Lab. | C10: daypa.delacruz@accor.com | D10: CC | E10: 1001033146 | F10: PALACIOS | G10: DE LA CRUZ | H10: DAYANA | I10: =PROPER(H10&" "&F10&" "&G10) -> Dayana Palacios De La Cruz | J10: F | K10: ANTIOQUIA | L10: APARTADÓ | M10: CIUDADELA COMFAMA | N10: 3145518402 | O10: NUEVA EPS | P10: 2924204 | Q10: COORDINACION DE SERVICIOS HOTELEROS | R10: PRESENCIAL | S10: 45817 | T10: 46000 | U10: PROMOTERA HOTELES URABA SAS | V10: CRA 100 # 88 21 | W10: APARTADO | X10: JUAN.PALENCIA@ACCOR.COM | Y10: JUAN DIEGO PALENCIA CORREA | Z10: 3205449784
A11: Maria del Rosari Jaramillo | B11: Pasantía | C11: acostagarcianinijhoana0@gmail.com | D11: CC | E11: 1007131264 | F11: ACOSTA | G11: GARCIA | H11: NINY JOHANA | I11: Niny Johana Acosta Garcia | J11: F | K11: ANTIOQUIA | L11: TURBO | M11: BARRIO 7 DE AGOSTO | N11: 323 482 02 52 | O11: SURA | P11: 3026343 | Q11: .ATENCION INTEGRAL A LA PRIMERA INFANCIA | R11: PRESENCIAL | S11: 45839 | T11: 46021 | U11: FUNDACIÓN DIOCESANA COMPARTIR | V11: BARRIO CHINITA, CARRERA 98 # 100 - 51 | W11: APARTADÓ ANTIOQUIA | X11: compartisedeturbo@gmailcom | Y11: DIANA TIRADO HERNANDEZ | Z11: 3148943614
A12: Abel Valderrama | B12: Pasantía | C12: valenciadarcln@gmail.com | D12: CC | E12: 1193313407 | F12: VALENCIA | G12: TANICAMA | H12: DARCILIANO | I12: Darciliano Valencia Tanicama | J12: M | K12: Antioquia | L12: Vigia del fuerte | M12: BarrioVenezuela | N12: 3226222247 | O12: Nueva eps | P12: 3001943 | Q12: SISTEMAS TELEINFORMÁTICOS | R12: PRESENCIAL | S12: 45840 | T12: 46022 | U12: I. E Rural Indigenista Embera Atrato Medio-Calle 3 #21-96 | V12: Cra 3 #21-96 Barrio Venezuela | W12: Vigía del Fuerte | X12: luzelenaalzatee960@gmail.com | Y12: Luz Elena Alzate Elejalde | Z12: 3173802004
A13: Virtual | B13: Vinc. Lab. | C13: leidylucas2007@gmail.com | D13: CC | E13: 1050958672 | F13: LUCAS | G13: BALTAZAR | H13: LEIDY PAOLA | I13: Leidy Paola Lucas Baltazar | J13: F | K13: BOLÍVAR | L13: APARTADÓ | M13: URB VILLA SANTA CATALINA | N13: 3106724940 | O13: SALUD TOTAL | P13: 3185840 | Q13: ATENCION INTEGRAL AL CLIENTE | R13: VIRTUAL | S13: 45751 | T13: 46023 | U13: MUNICIPIO DE MAHATES | V13: EDIFICIO PALACIO MUNICIPAL, K 37 NO 18-05 | W13: MAHATES | X13: educacion@mahates-bolivar.gov.co | Y13: Gustavo Junior Beleño Llerena | Z13: 3215669944
A14: Abel Valderrama | B14: Pasantía | C14: carmenjimenez.cjm53@gmail.com | D14: CC | E14: 1007131776 | F14: JIMENEZ | G14: MUENTES | H14: CARMEN MARIA | I14: Carmen Maria Jimenez Muentes | J14: F | K14: Antioquia | L14: Turbo | M14: 29 de noviembre nueva colonia | N14: 3135648805 | O14: SURA | P14: 2842920 | Q14: SISTEMAS. | R14: PRESENCIAL | S14: 45667 | T14: 46026 | U14: Municipio de Turbo | V14: Casa de Gobierno, Corr. Nva colonia | W14: Turbo | X14: casadegobiernonvacolonia@turbo-antioquia.gov.co | Y14: Guillermo Lopez Montaño | Z14: 3104300447
A15: Maria del Rosari Jaramillo | B15: Pasantía | C15: sandrasiso1992@gmail.com | D15: CC | E15: 1045511987 | F15: BARCOS | G15: PINEDA | H15: SANDRA YINESA | I15: Sandra Yinesa Barcos Pineda | J15: F | K15: Antioquia | L15: Turbo | M15: Barrio Invasion(Bosque) Cll.86 - Crr.21 | N15: 3103685499 | O15: Savia salud | P15: 2861388 | Q15: .ATENCION INTEGRAL A LA PRIMERA INFANCIA | R15: PRESENCIAL | S15: 45845 | T15: 46029 | U15: Centro Educativo Jardin Infantil Aqualuna. | V15: Barrio- Las delicias Calle99 Detrás de la Bombonera. | W15: Turbo Antioquia. | X15: AlejandraOviedo29@gmail.com | Y15: Alejandra Castro Oviedo. | Z15: 3232108949
A16: Abel Valderrama | B16: Pasantía | C16: samuelmonterrosagonzalez@gmail.com | D16: TI | E16: 1067897605 | F16: MONTERROSA | G16: GONZALEZ | H16: SAMUEL | I16: =PROPER(H16&" "&F16&" "&G16) -> Samuel Monterrosa Gonzalez | J16: M | K16: ANTIOQUIA | L16: ARBOLETTES | M16: B/VILLA LUZ | N16: 3218299276 | O16: SURAMERICANA S.A.-CM | P16: 2877398 | Q16: PROGRAMACION DE SOFTWARE . | R16: PRESENCIAL | S16: 45852 | T16: 46035 | U16: CONCEJO MUNICIPAL | V16: CALLE 31N°29-08. | W16: ARBOLETES | X16: Concejo@arboletes-antioquia.gov.co | Y16: ISABEL CRISTINA SUAREZ BAUTISTA | Z16: 320 6362948
A17: Julian Moreno | B17: Pasantía | C17: adrianvertel2007@gmail.com | D17: CC | E17: 1039087574 | F17: CAMPO | G17: VERTEL | H17: ADRIAN | I17: Adrian Campo Vertel | J17: M | K17: ANTIOQUIA | L17: NECOCLI | M17: Cra 45 #49-109 | N17: 3206843156 | O17: NUEVA EPS S.A. | P17: 2923976 | Q17: SERVICIOS FARMACEUTICOS | R17: PRESENCIAL | S17: 45853 | T17: 46037 | U17: ESE HOSPITAL SAN SEBASTIAN NECOCLI | V17: Km 1 vía Necoclí - Turbo | W17: Necoclí | X17: dmhospitalnecocli@gmail.com | Y17: Aris Cecilia Ayala | Z17: 3206625066
A18: Julian Moreno | B18: Pasantía | C18: zinedinequintero1@gmail.com | D18: CC | E18: 1075090276 | F18: QUINTERO | G18: TAPIA | H18: ZINEDINE | I18: Zinedine Quintero Tapia | J18: M | K18: ANTIOQUIA | L18: NECOCLI | M18: Calle 50 #47-13 | N18: 3207853833 | O18: SAVIA SALUD | P18: 2923976 | Q18: SERVICIOS FARMACEUTICOS | R18: PRESENCIAL | S18: 45853 | T18: 46037 | U18: ESE HOSPITAL SAN SEBASTIAN NECOCLI | V18: Km 1 vía Necoclí - Turbo | W18: Necoclí | X18: basiliagonzalez@hospitalnecocli.gov.co | Y18: Basilia Medrano González | Z18: 3146797001
A19: Julian Moreno | B19: Pasantía | C19: elianaisabelg543@gmail.com | D19: CC | E19: 1039083990 | F19: GUTIERREZ | G19: RODRIGUEZ | H19: ELIANA ISABEL | I19: Eliana Isabel Gutierrez Rodriguez | J19: F | K19: ANTIOQUIA | L19: NECOCLI | M19: Corregiiento El Mellito | N19: 3234201738 | O19: COOSALUD | P19: 2923976 | Q19: SERVICIOS FARMACEUTICOS | R19: PRESENCIAL | S19: 45853 | T19: 46037 | U19: ESE HOSPITAL SAN SEBASTIAN NECOCLI | V19: Km 1 vía Necoclí - Turbo | W19: Necoclí | X19: patriciaranzetac@hotmail.com | Y19: Erika Patricia Araanzeta Celis | Z19: 3105912589
A20: Maria del Rosari Jaramillo | B20: Pasantía | C20: VEPALACIOS6@MISENA.EDU.CO | D20: CC | E20: 1037120756 | F20: PALACIOS | G20: GUZMAN | H20: VANESSA EDITH | I20: Vanessa Edith Palacios Guzman | J20: F | K20: ANTIOQUIA | L20: CHIGORODO | M20: VEREDA LA BENDICIONES | N20: 3218179434 | O20: NUEVA EPS | P20: 2861415 | Q20: .ATENCION INTEGRAL A LA PRIMERA INFANCIA | R20: PRESENCIAL | S20: 15/07/2025 | T20: 46037 | U20: CORPORACION SILOH - OASIS DE ESPERANZA | V20: CLLE 84 #98-29 B/ El bosque | W20: CHIGORODO | X20: cdi282uraba@gamil.com | Y20: Edilma Contreras | Z20: 3108596574
A21: Abel Valderrama | B21: Pasantía | C21: danpingue@gmail.com | D21: CC | E21: 1067865573 | F21: PINEDA | G21: GUEVARA | H21: DANIEL | I21: Daniel Pineda Guevara | J21: M | K21: ANTIOQUIA | L21: ARBOLETTES | M21: B/DEPORTIVO | N21: 312 8994788 | O21: SAVIA SALUD | P21: 2877398 | Q21: PROGRAMACION DE SOFTWARE . | R21: PRESENCIAL | S21: 45858 | T21: 46042 | U21: SECRETARIA DE VICTIMAS | V21: CALLE 31N°29-08. | W21: ARBOLETES | X21: victimasarboletes2025@gmail.com | Y21: Lina Marcela Montalvo Ballesteros | Z21: 313 3336671
A22: Yerlis Hernández | B22: Pasantía | C22: veronicasibajaespitia@gmail.com | D22: CC | E22: 1041255369 | F22: SIBAJA | G22: ESPITIA | H22: VERONICA | I22: Veronica Sibaja Espitia | J22: F | K22: ANTIOQUIA | L22: SAN PEDRO DE URABÁ | N22: 3188100932 | O22: SAVIA SALUD | P22: 2775399 | Q22: EJECUCION DE PROGRAMAS DEPORTIVOS. | R22: PRESENCIAL | S22: 45862 | T22: 46046 | U22: ALCALDIA MUNICIPAL | W22: SAN PEDRO | X22: spedrouraba@indeportesantioquia.gov.co | Y22: JOSIMAR ANDRADES ESPITIA | Z22: 3044371446
A23: Yerlis Hernández | B23: Pasantía | C23: joseguramar04@gmail.com | D23: CC | E23: 1041260208 | F23: SEGURA | G23: MARTINEZ | H23: JOSE JOSE | I23: Jose Jose Segura Martinez | J23: M | K23: Antioquia | L23: San Pedro de Uraba | M23: B/ Brisas de uraba | N23: 3147684100 - 3113482723 | O23: Savia Salud | P23: 2775399 | Q23: EJECUCION DE PROGRAMAS DEPORTIVOS. | R23: PRESENCIAL | S23: 45839 | T23: 46052 | U23: Alcaldia Municipal - Educacion | V23: 50N° 52-114 B/ El centroo | W23: San Pedro de Uraba | X23: educacion@sanpedrodeuraba-antioquia.gov.co - gobierno@sanpedrodeuraba-antioquia.gov.co | Y23: Gilmor Murillo Murillo | Z23: 8205502 - ex 101 - 3017240730
A24: Nelvis Margoth Barboza Rivera | B24: Pasantía | C24: hernandezcarolinaj1229@gmail.com | D24: CC | E24: 1028002146 | F24: HERNANDEZ | G24: TABORDA | H24: YENI CAROLINA | I24: =PROPER(H24&" "&F24&" "&G24) -> Yeni Carolina Hernandez Taborda | J24: F | K24: ANTIOQUIA | L24: APARTADÓ | M24: CRR 79 B #103-04 | N24: 3137344026 | O24: NUEVA EPS | P24: 3031879 | Q24: SERVICIOS FARMACEUTICOS | R24: PRESENCIAL | S24: 45870 | T24: 46053 | U24: INVERSIONES PROGRESO ECHEVERRI ZOMAC SAS | V24: CRR 101 #95-16 BRR EL AMPARO | W24: APARTADÓ | X24: AUX.CONTABILIDAD@DROGUERIACOMERCIAL.COM | Y24: LUIS GUILLERMO GARCIA | Z24: 3104136592
A25: Yerlis Hernández | B25: Proy. Prod. | C25: j.leonardo10vegas.g@gmail.com | D25: CC | E25: 1127580804 | F25: VEGAS | G25: GONZALEZ | H25: JOSE LEONARDO | I25: Jose Leonardo Vegas Gonzalez | J25: M | K25: ANTIOQUIA | L25: ARBOLETES | M25: BARRIO ACEVEDO | N25: 3007766388 | O25: SAVIA SALUD | P25: 2945489 | Q25: EJECUCION DE PROGRAMAS DEPORTIVOS. | R25: PRESENCIAL | S25: 45299 | T25: 46055
A26: Virtual | B26: Pasantía | C26: karolgomez171@gmail.com | D26: CC | E26: 1000464538 | F26: CHAPARRO | G26: GOMEZ | H26: KAROL JULIANA | I26: Karol Juliana Chaparro Gomez | J26: F | K26: BOGOTÁ D.C. | L26: APARTADÓ | M26: Cra 100a # 135 - 09 | N26: 3013780475 | O26: Compensar | P26: 2834804 | Q26: ANALISIS Y DESARROLLO DE SOFTWARE. | R26: VIRTUAL | S26: 46024 | T26: 46060 | U26: Atomcol S.A.S | V26: Cra. 86 # 146-61 Bloque | W26: Bogota D.C | X26: dirfinanciero@atomcol.com | Y26: Jesus Perea | Z26: +(57)3163839949
A27: Carlos Negrete | B27: Pasantía | C27: shenao812@gmail.com | D27: CC | E27: 1027956691 | F27: HENAO | G27: PULGARIN | H27: JUAN SEBASTIAN | I27: Juan Sebastian Henao Pulgarin | J27: M | K27: ANTIOQUIA | L27: TURBO | M27: B/ LAS FLORES - CURRULAO | N27: 313 720 49 51 | O27: SAVIA SALUD | P27: 2998492 | Q27: INSTALACION Y MANTENIMIENTO DE REDES INTERNAS DE TELECOMUNICACIONES | R27: PRESENCIAL | S27: 45877 | T27: 46062 | U27: INTERVECTOR SAS | V27: CR 65A # 72A - 50 B/ LAS FLORES | W27: CAREPA | X27: intervector300424@gmail.com | Y27: JESUS MARIA GONZALEZ ZAMBRANO | Z27: 320 577 85 98
A28: Yolanda Berrío | B28: Pasantía | C28: jg0563005@gmail.com | D28: CC | E28: 1001670094 | F28: GONZALEZ | G28: CHIQUILLO | H28: JERSON JESUS | I28: Jerson Jesus Gonzalez Chiquillo | J28: M | K28: ANTIOQUIA | L28: TURBO | M28: V/ COLDESA | N28: 3004256110 | O28: SAVIA SALUD | P28: 3012698 | Q28: PRODUCCION AGROPECUARIA | R28: PRESENCIAL | S28: 45880 | T28: 46063 | U28: ASI ES LA VIDA | V28: V/COLDESA | W28: TURBO | X28: mavilgonzalez7@gmail.com | Y28: MAVIL ROSARIO GONZALEZ | Z28: 3146105921
A29: Maria del Rosari Jaramillo | B29: Pasantía | C29: MAYERLYSICUESTA@GMAIL. | D29: CC | E29: 1001026387 | F29: MURILLO | G29: CUESTA | H29: MAYERLYS | I29: Mayerlys Murillo Cuesta | J29: F | K29: ANTIOQUIA | L29: TURBO | M29: OBRERO | N29: 3147293135 | O29: SURA | P29: 3026343 | Q29: .ATENCION INTEGRAL A LA PRIMERA INFANCIA | R29: PRESENCIAL | S29: 45882 | T29: 46066 | U29: FUNDACIÓN DIOCESANA COMPARTIR | V29: BARRIO CHINITA, CARRERA 98 # 100 - 51 | W29: APARTADÓ ANTIOQUIA | X29: compartirturbo@gmail.com | Y29: DIANA TIRADO HERNANDEZ | Z29: 3148943614
A30: Maria del Rosari Jaramillo | B30: Pasantía | C30: amparomartinezpin@gmail.com | D30: CC | E30: 1193587554 | F30: MARTINEZ | G30: PINO | H30: AMPARO | I30: Amparo Martinez Pino | J30: F | K30: ANTIOQUIA | L30: TURBO | M30: BOSQUE | N30: 3136451051 | O30: COOSALUD | P30: 3067834 | Q30: .ATENCION INTEGRAL A LA PRIMERA INFANCIA | R30: PRESENCIAL | S30: 45857 | T30: 46072 | U30: INSTITUCION EDUCATIVA SAN MARTIN | V30: juan xxIII calle 100 crr 15 | W30: TURBO | X30: iesanmartin@turboeducado.edu.coo | Y30: YULIANA ROLDAN | Z30: 3146426803
A31: Virtual | B31: Vinc. Lab. | C31: DRMECADO@SOY.SENA.EDU.CO | D31: CC | E31: 1015425132 | F31: MERCADO | G31: VILLARREAL | H31: DOUGLAS RAFAEL | I31: Douglas Rafael Mercado Villarreal | J31: M | K31: ANTIOQUIA | N31: 3028452504 | O31: SANITAS | P31: 2834803 | Q31: ANALISIS Y DESARROLLO DE SOFTWARE. | R31: VIRTUAL | S31: 45857 | T31: 46072 | U31: HYPER INGENIEROS SAS | V31: CARRERA 97 A - 75 - 26 | W31: BOGOTA D.C | X31: ceo@hyperingenieros.com.co | Y31: LILIANA GUTIERREZ | Z31: 3144740054
A32: Maria del Rosari Jaramillo | B32: Pasantía | C32: chiky.10@hotmail.es | D32: CC | E32: 1038807037 | F32: FLOREZ | G32: MARTINEZ | H32: NERLIS | I32: Nerlis Florez Martinez | J32: F | K32: Antioquia | L32: Chigorodo | M32: Barrio la paz | N32: 3116408323 | O32: Nueva esp | P32: 3067834 | Q32: .ATENCION INTEGRAL A LA PRIMERA INFANCIA | R32: PRESENCIAL | S32: 45889 | T32: 46073 | U32: Jardin Grandes Exploradores | V32: cl-95#109-30 b/ los olivos | W32: chigorodo | X32: jigrandesexploradores@gmail.com | Y32: karen liseth jaramilo - Administradora | Z32: 3148122428
A33: Maria del Rosari Jaramillo | B33: Pasantía | C33: montalvoeli87@gmail.com | D33: CC | E33: 1038806475 | F33: MONTALVO | G33: ORTEGA | H33: ELI JOHANA | I33: Eli Johana Montalvo Ortega | J33: F | K33: Antioquia | L33: Chigorodo | M33: cra 102a calle84a 03 | N33: 3215011590 | O33: savia salud | P33: 3067834 | Q33: .ATENCION INTEGRAL A LA PRIMERA INFANCIA | R33: PRESENCIAL | S33: 45889 | T33: 46073 | U33: Jardin Grandes Axploradores | V33: cl-95#109-30 b/ los olivos | W33: chigorodo | X33: jigrandesexploradores@gmail.com | Y33: karen liseth jaramillo- Administradora | Z33: 3148122428
A34: Virtual | B34: Pasantía | C34: karotr2017@hotmail.com | D34: CC | E34: 52759494 | F34: TRIANA | G34: RODRIGUEZ | H34: SARA CAROLINA | I34: =PROPER(H34&" "&F34&" "&G34) -> Sara Carolina Triana Rodriguez | J34: F | K34: Tolima | L34: Carmen de Apicalá | M34: Cra. 3 #5-52 | N34: 3134003071 | O34: Famisanar | P34: 2879779 | Q34: DESARROLLO PUBLICITARIO | R34: VIRTUAL | S34: 21/08/2025 | T34: 46073 | U34: GUMO INGENIERIA S.A.S. | V34: Cra 16 A # 78 - 55 of. 303 | W34: Bogota D.C. | X34: ing.mogollon27@gmail.com | Y34: Zidderman Mogollon | Z34: 3124457403
A35: Julian Moreno | B35: Pasantía | C35: VALENTINAHERRERAFRANCO3@GMAIL.COM | D35: CC | E35: 1039090627 | F35: HERRERA | G35: FRANCO | H35: VALENTINA | I35: Valentina Herrera Franco | J35: F | K35: ANTIOQUIA | L35: NECOCLI | M35: CRR 43 #51-01 BRR PARROQUIAL | N35: 3135361561 | O35: SAVIA SALUD | P35: 2923976 | Q35: SERVICIOS FARMACEUTICOS | R35: PRESENCIAL | S35: 45896 | T35: 46080 | U35: DROGUERIA COMERCIAL | V35: CRR 44 #51-11 | W35: NECOCLI | X35: AUX.CONTABILIDAD@DROGUERIACOMERCIAL.COM | Y35: LUIS GUILLERMO GARCIA | Z35: 3104136592
A36: Maria del Rosari Jaramillo | B36: Pasantía | C36: danielacortesortiz38@gmail.com | D36: CC | E36: 1038799879 | F36: CORTES | G36: ORTIZ | H36: DANIELA | I36: Daniela Cortes Ortiz | J36: F | K36: Antioquia | L36: Chigorodo | M36: Balsos | N36: 3225235978 | O36: Savia salud | P36: 3067834 | Q36: .ATENCION INTEGRAL A LA PRIMERA INFANCIA | R36: PRESENCIAL | S36: 45896 | T36: 46080 | U36: Jardin Grandes Explradores | V36: Cl-95#109-30B/los Olivos | W36: Chigorodo | X36: jigrandreexploradores@gmail.com | Y36: Karen Liseth Jaramllo - Administradora | Z36: 3148122428
A37: Maria del Rosari Jaramillo | B37: Pasantía | C37: Paolausuga056@gmail.com | D37: CC | E37: 1010130039 | F37: USUGA | G37: OSORIO | H37: YENI PAOLA | I37: Yeni Paola Usuga Osorio | J37: F | K37: ANTIOQUIA | L37: CHIGORODO | M37: Barrio Las Tablitas | N37: 3218031545 | O37: savia salud | P37: 3067834 | Q37: .ATENCION INTEGRAL A LA PRIMERA INFANCIA | R37: PRESENCIAL | S37: 45901 | T37: 46081 | U37: I.E Juan Evangelista Berrio | V37: CALLE 8A B N° 91 -45 | W37: CHIGORODÓ | X37: talleresjuanevangelista@gmail.com | Y37: Leydy Lorena Ibarguen Ledesma | Z37: 3147022155
A38: Abel Valderrama | B38: Proy. Prod. | C38: yiscarpereamorenomosquera@gmail.com | D38: CC | E38: 1003969468 | F38: CORREA | G38: MURILLO | H38: JHON EDISON | I38: Jhon Edison Correa Murillo | J38: M | K38: Antioquia | L38: Vigia del fuerte | M38: barrio achinal | N38: 3226222249 | O38: savia salud | P38: 3001943 | Q38: SISTEMAS TELEINFORMÁTICOS | R38: PRESENCIAL | S38: 45901 | T38: 46081 | U38: ASOFUTEC | V38: CARRERA 2 | W38: VIGIA DEL FUER | X38: Asofutec44@gmail.com | Y38: DEIVER HEREDIA CHA | Z38: 3023636683
A39: Marcelino Gonzalez | B39: Vinc. Lab. | C39: sebasespitia97@gmail.com | D39: CC | E39: 1193553863 | F39: ESPITIA | G39: CAMAÑO | H39: JUAN SEBASTIAN | I39: Juan Sebastian Espitia Camaño | J39: M | K39: Antioquia | L39: Chigorodó | M39: cll86a 104-24 B/ el paraiso | N39: 3012097030 | O39: Sura | P39: 3206188 | Q39: PRODUCCION AGROPECUARIA | R39: PRESENCIAL | S39: 45900 | T39: 46081 | U39: Promotora Palmera de Antioquia | V39: Cr 80 Cl 80 Lc 116 cc Las Playas | W39: Carepa | X39: recepcion.ppa@hotmail.com | Y39: Juan Ballesta | Z39: 3128926382
A40: Marcelino Gonzalez | B40: Vinc. Lab. | C40: edwinmadera3@gmail.com | D40: CC | E40: 1038809619 | F40: MADERA | G40: VELASQUEZ | H40: EDWIN ANTONIO | I40: Edwin Antonio Madera Velasquez | J40: M | K40: Antioquia | L40: Chigorodó | M40: Cll94b nro 108-80 | N40: 3145920178 | O40: Sura | P40: 3206188 | Q40: PRODUCCION AGROPECUARIA | R40: PRESENCIAL | S40: 45697 | T40: 46083 | U40: UNALTRAPEC | V40: Cll 95. Nro 95c - 23 - B/ Linares | W40: Chigorodó Ant | X40: unaltrachigorodo@gmail.com | Y40: Bladimir Perez | Z40: 3122985629
A41: Julian Moreno | B41: Pasantía | C41: STEFANIATEHERAN960@GMAIL.COM | D41: CC | E41: 1001589381 | F41: THERAN | G41: VARGAS | H41: STEFANNIA | I41: Stefannia Theran Vargas | J41: F | K41: ANTIOQUIA | L41: NECOCLI | M41: VEREDA BOTIJUELA | N41: 3004690176 | O41: NUEVA EPS | P41: 2923976 | Q41: SERVICIOS FARMACEUTICOS | R41: PRESENCIAL | S41: 45905 | T41: 46086 | U41: DROGUERIA COMERCIAL | V41: CRR 44 #51-11 | W41: NECOCLI | X41: AUX.CONTABILIDAD@DROGUERIACOMERCIAL.COM | Y41: LUIS GUILLERMO GARCIA | Z41: 3104136592
A42: Julian Moreno | B42: Pasantía | C42: adarvealessandra@gmail.com | D42: CC | E42: 1027941463 | F42: ADARVE | G42: LONDOÑO | H42: AYDEYSSY ALESSANDRA | I42: Aydeyssy Alessandra Adarve Londoño | J42: F | K42: Antioquia | L42: Apartadó | M42: B/Obrero b/ 3 | N42: 3137956350 | O42: Nueva Eps | P42: 3047491 | Q42: SALUD PUBLICA | R42: PRESENCIAL | S42: 45908 | T42: 46089 | U42: Alcaldia | V42: CAR. 100#103A-02 | W42: APARTADÓ | X42: saludpublica@apartado.gov.co | Y42: NATALIA ANDRA GUARIN | Z42: 3117188586
A43: Maria del Rosari Jaramillo | B43: Pasantía | C43: AVILESMONICA32@GMAIL.COM | D43: CC | E43: 1007347395 | F43: AVILES | G43: TIRADO | H43: MONICA PATRICIA | I43: Monica Patricia Aviles Tirado | J43: F | K43: ANTIOQUIA | L43: CHIGORODO | M43: EL PRADO CALLE-80 CASA97-70 | N43: 3117417418 | O43: NUEVA EPS | P43: 2861415 | Q43: .ATENCION INTEGRAL A LA PRIMERA INFANCIA | R43: PRESENCIAL | S43: 45910 | T43: 46090 | U43: FUNDACIÓN DIOCESANA COMPARTIR | V43: BARRIO CHINITA, CARRERA 98 # 100 - 51 | W43: APARTADÓ ANTIOQUIA | X43: compartirturbo@gmail.com | Y43: EVELCY DEL ROSARIO OVIEDO MARIMÓN | Z43: 3123052886
A44: Maria del Rosari Jaramillo | B44: Pasantía | C44: ALEJAPALACIOS48@GMAIL.COM | D44: CC | E44: 1027960003 | F44: PALACIOS | G44: ARANGO | H44: MARIA ALEJANDRA | I44: Maria Alejandra Palacios Arango | J44: F | K44: ANTIOQUIA | L44: APARTADO | M44: CALLE 96 N 87-22 SAN FERNANDO | N44: 3106153921 | O44: NUEVA EPS | P44: 2932599 | Q44: .ATENCION INTEGRAL A LA PRIMERA INFANCIA | R44: PRESENCIAL | S44: 45910 | T44: 46090 | U44: FUNDACIÓN DIOCESANA COMPARTIR | V44: BARRIO CHINITA, CARRERA 98 # 100 - 51 | W44: APARTADÓ ANTIOQUIA | X44: COMPARTIRSEDEHIAPARTADO@GMAIL.COM | Y44: CINDY JOHANA VALENCIA LOPEZ | Z44: 3116284387
A45: Paola Londoño | B45: Pasantía | C45: ALEJANDRAURIBE954@GMAIL.COM | D45: CC | E45: 1001025958 | F45: NUÑEZ | G45: URIBE | H45: VANESSA ALEJANDRA | I45: =PROPER(H45&" "&F45&" "&G45) -> Vanessa Alejandra Nuñez Uribe | J45: F | K45: ANTIOQUIA | L45: CHIGORODO | M45: B/ PARAISO | N45: 3103873751 | O45: NUEVA EPS | P45: 3014613 | Q45: SERVICIOS COMERCIALES Y FINANCIEROS | R45: PRESENCIAL | S45: 45728 | T45: 46092 | U45: INTERRAPIDISIMO | V45: CR 102 N 93-21 | W45: CHIGORODO | X45: GABRIELAHOYOSESPINIOSA@GMAIL.COM | Y45: INGRID TATIANA BORJA | Z45: 3106219355
A46: Instructores formacion | B46: Pasantía | C46: blanquicett1129@gmail.com | D46: CC | E46: 1028016129 | F46: BLANQUICETT | G46: OYOLA | H46: LUIS FERNEY | I46: Luis Ferney Blanquicett Oyola | J46: M | K46: ANTIOQUIA | L46: APARTADO | M46: Cr. 76 Cll. 102B N 38 20 de enero | N46: 3127879874 | O46: SURA | P46: 2932613 | Q46: CONSTRUCCION DE EDIFICACIONES | R46: PRESENCIAL | S46: 45912 | T46: 46093 | U46: JAL 20 DE ENERO | V46: Cll. 101 B Cra. 74 A 20 de enero | W46: APARTADO | X46: wbeirendon0809@gmail.com | Y46: wbeimar Rendón | Z46: 3136590368
A47: Marcelino Gonzalez | B47: Vinc. Lab. | C47: davidnegrete851@gmail.com | D47: CC | E47: 1038819525 | F47: NEGRETE | G47: MEDRANO | H47: DEIMER DAVID | I47: Deimer David Negrete Medrano | J47: M | K47: ANTIOQUIA | L47: CHIGORODO | M47: VEREDA LA GRANJA | N47: 3236370828 | O47: NUEVA EPS | P47: 3206188 | Q47: PRODUCCION AGROPECUARIA | R47: PRESENCIAL | S47: 45917 | T47: 46097 | U47: PROMOTORA PALMERA DE ANTIOQUIA | V47: CRA.80 - CLL80 LOCAL 116 CC.LA PLAYA | W47: CAREPA ANT | X47: recepcion.ppa@hotmail.com | Y47: SAMUEL MARIN | Z47: 3225147573
A48: Marcelino Gonzalez | B48: Vinc. Lab. | C48: edierjoseduran29@gmail.com | D48: CC | E48: 1007722776 | F48: DURAN | G48: ANAYA | H48: EDIER JOSE | I48: Edier Jose Duran Anaya | J48: M | K48: Antioquia | L48: Chigorodo | M48: vereda vohios | N48: 3214525063 | O48: sura | P48: 3206188 | Q48: PRODUCCION AGROPECUARIA | R48: PRESENCIAL | S48: 45920 | T48: 46100 | U48: vallecito zomac | V48: vereda vohios | W48: chigorodo | X48: vallecito.medellin.com | Y48: Catalina Vallejo | Z48: 3242281882
A49: Maria del Rosari Jaramillo | B49: Pasantía | C49: horlindadomicobailarin@gmail.com | D49: CC | E49: 50640345 | F49: BAILARIN | G49: DOMICO | H49: HORLINDA | I49: Horlinda Bailarin Domico | J49: F | K49: ANTIOQUIA | L49: APARTADÓ | M49: Vda Las Playas | N49: 3122882963 | O49: COOSALUD EPS | P49: 2962236 | Q49: .ATENCION INTEGRAL A LA PRIMERA INFANCIA | R49: PRESENCIAL | S49: 45922 | T49: 46104 | U49: RESGUARDO INDIGENA IBUDÓ | V49: Vda Las Playas | W49: APARTADÓ | X49: gobernadorplayas@gmail.com | Y49: Ernesto Bailarín Domicó | Z49: 3126548706
A50: Maria del Rosari Jaramillo | B50: Pasantía | C50: yancihc1989@gmail.com | D50: CC | E50: 1038805974 | F50: HERNANDEZ | G50: CORDOBA | H50: YANCI | I50: Yanci Hernandez Cordoba | J50: F | K50: ANTIOQUIA | L50: CHIGORODO | M50: Barrio el Bosque | N50: 3218031545 | O50: savia salud | P50: 2861415 | Q50: .ATENCION INTEGRAL A LA PRIMERA INFANCIA | R50: PRESENCIAL | S50: 45922 | T50: 46104 | U50: I.E Juan Evangelista Berrio | V50: CALLE 8A B N° 91 -45 | W50: CHIGORODÓ | X50: talleresjuanevangelista@gmail.com | Y50: Leydy Lorena Ibarguen Ledesma | Z50: 3147022155
A51: Abel Valderrama | B51: Pasantía | C51: luisavilarosario6@gmail.com | D51: CC | E51: 1035153661 | F51: AVILA | G51: ROSARIO | H51: LUIS ALBERTO | I51: Luis Alberto Avila Rosario | J51: M | K51: ANTIOQUIA | L51: ARBOLETTES | M51: B/el deportivo | N51: 3225096089 | O51: FAMILIAR DE COLOMBIA | P51: 2973691 | Q51: SISTEMAS TELEINFORMÁTICOS | R51: PRESENCIAL | S51: 45929 | T51: 46110 | U51: PARQUE EDUCATIVO LOS MANGLARES | V51: KR 29 N 30A-14 | W51: ARBOLETES | X51: edusuperior.arboletes@gmail.com | Y51: IVAN RAMIRO MONTES AREVALO | Z51: 3142945033
A52: Silvia Chaverra | B52: Vinc. Lab. | C52: ivandario099@hotmail.com | D52: CC | E52: 1028025888 | F52: JARAMILLO | G52: RODRIGUEZ | H52: IVAN DARIO | I52: Ivan Dario Jaramillo Rodriguez | J52: M | K52: Antioquia | L52: Apartadó | M52: Calle 88b # 82- 26 | N52: 3158514040 | O52: NUEVA EPS | P52: 2924226 | Q52: GESTIÓN ADMINISTRATIVA | R52: PRESENCIAL | S52: 45930 | T52: 46111 | U52: PANADERIA Y CONGELADOS TRIGO DE ORO | V52: Calle 102c n° 81 c- 10 12 | W52: Apartadó | X52: congeladostrigodeoro@gmail.com | Y52: ALBERTO JARAMILLO | Z52: 3502345160
A53: Julian Moreno | B53: Pasantía | C53: YULISSAVARELA07@GMAIL.COM | D53: CC | E53: 1007432996 | F53: VARELAS | G53: CARDONA | H53: YULISSA | I53: Yulissa Varelas Cardona | J53: F | K53: ANTIOQUIA | L53: CHIGORODO | M53: CRA 95C N 95H-66 | N53: 3205048094 | O53: NUEVA EPS | P53: 2932594 | Q53: SALUD PUBLICA | R53: PRESENCIAL | S53: 45931 | T53: 46111 | U53: E.S.E HOSPITAL MARIA AUXILIADORA | V53: CRA 108A N 101A - 57 | W53: CHIGORODO | X53: BLANCABRAND@HOSPITALMA.GOV.CO | Y53: BLANCA BRAND | Z53: 3007888123
A54: Marco García | B54: Vinc. Lab. | C54: ALEJAPINEDA96@GMAL.COM | D54: CC | E54: 1028026882 | F54: PINEDA | G54: MOSQUERA | H54: EIDY ALEJANDRA | I54: Eidy Alejandra Pineda Mosquera | J54: F | K54: ANTIOQUIA | L54: APARTADO | M54: 1RA POLICARPA CALLE 105H | N54: 3147336228 | O54: NUEVA EPS | P54: 2934824 | Q54: ENTRENAMIENTO DEPORTIVO | R54: PRESENCIAL | S54: 45931 | T54: 46112 | U54: IINSTITUCION MUNICIPAL DE DEPORTES Y RECREACION (MDER APARTADO) | V54: Cra 104 - Clle 117- 65 COLISEO CUBIERTO ANTONIO ROLDAN BETANCUR | W54: APARTADO | X54: Asitente@imderapartado.gov.co | Y54: KAREN LORENA ESCOBAR ZAPATA | Z54: 3147288308/6866829
A55: Abel Valderrama | B55: Pasantía | C55: arnedysfajardo@gmail.com | D55: CC | E55: 1039085240 | F55: FAJARDO | G55: EMERY | H55: ARNEDYS | I55: Arnedys Fajardo Emery | J55: F | K55: Antioquia | L55: Necocli | M55: Corregemiento Pueblo Nuevo | N55: 3218744851 | O55: Nueva Eps | P55: 2952319 | Q55: SISTEMAS TELEINFORMÁTICOS | R55: PRESENCIAL | S55: 45931 | T55: 46112 | U55: COMUNIACIONES TAVI | V55: CRA 45 #101-58 | W55: NECOCLI | X55: comunicacionestavi2@gmail.com | Y55: TATIANA SALGADO | Z55: 3104104940
A56: Aldwin Morelo | B56: Pasantía | C56: cortesborjayennis@gmail.com | D56: CC | E56: 1038802992 | F56: CORTES | G56: BORJA | H56: YENNIS | I56: Yennis Cortes Borja | J56: F | K56: ANTIOQUIA | L56: CHIGORODO | M56: CALL 95 #111 - 47 | N56: 3126299671 | O56: NUEVA EPS | P56: 2965635 | Q56: ASISTENCIA PARA LA INTELIGENCIA EMPRESARIAL | R56: PRESENCIAL | S56: 45931 | T56: 46112 | U56: PAPELERIA Y COMUNICACIÓNES TAVI | V56: BARRIO KENNEDY | W56: CHIGOROD | X56: comunicacionestavi3@gmail.com | Y56: LAURA MARCELA TUBERQUIA PADIERNA | Z56: 3205890619
A57: Abel Valderrama | B57: Pasantía | C57: johanmanuelocampo77@gmail.com | D57: CC | E57: 1138074154 | F57: OCAMPO | G57: MARTINEZ | H57: JOHAN MANUEL | I57: Johan Manuel Ocampo Martinez | J57: M | K57: ANTIOQUIA | L57: ARBOLETTES | M57: El palmar | N57: 3233760794 | O57: Nueva Eps | P57: 2877398 | Q57: PROGRAMACION DE SOFTWARE . | R57: PRESENCIAL | S57: 45931 | T57: 46113 | U57: Alcaldia municipal-renta ciudadana | V57: Cra. 29 #30b-2 a 30b-18 | W57: ARBOLETES | X57: alcaldia@arboletes-antioquia.gov.co | Y57: Sandra Cardona | Z57: 300 8928025
A58: Marcelino Gonzalez | B58: Vinc. Lab. | C58: santiagomunetonsanchezs81@gmail.com | D58: CC | E58: 1007872766 | F58: MUÑETON | G58: SANCHEZ | H58: SANTIAGO | I58: Santiago Muñeton Sanchez | J58: M | K58: ANTIOQUIA | L58: CHIGORODO | M58: Crr 96 Cll 97 #97-74 | N58: 3116253609 | O58: NUEVA EPS | P58: 3206188 | Q58: PRODUCCION AGROPECUARIA | R58: PRESENCIAL | S58: 45933 | T58: 46114 | U58: Unaltrapec | V58: Calle 95 N° 95c 23 | W58: Chigorodo | X58: unaltrachigorodo@gmail.com | Y58: Lino Muñoz | Z58: 312 2985642
A59: Andrés Felipe Henao | B59: Pasantía | C59: dannycordobamosquera09@gmail.com | D59: CC | E59: 71242383 | F59: CORDOBA | G59: MOSQUERA | H59: DANIEL | I59: Daniel Cordoba Mosquera | J59: M | K59: Antioquia | L59: Apartadó | M59: B/ obrero | N59: 3107100514 | O59: sura | P59: 2920221 | Q59: INSTALACION DE SISTEMAS ELECTRICOS RESIDENCIALES Y COMERCIALES | R59: PRESENCIAL | S59: 45936 | T59: 46117 | U59: JM SERVIELECTRICOS SOLUCIONES | V59: CR 86 CLL104B CS15 B/ OBRERO | W59: Apartadó | X59: JEROMARIVAS1@HOTMAIL.COM | Y59: JERONIMO RIVAS MOSQUERA | Z59: 3126403317
A60: Abel Valderrama | B60: Pasantía | C60: 1001104510edwin@gmail.com | D60: CC | E60: 1001401510 | F60: ORTEGA | G60: MERCADO | H60: EDWIN | I60: Edwin Ortega Mercado | J60: M | K60: ANTIOQUIA | L60: SAN PEDRO DE URABA | N60: 3122759014 | O60: SAVIA SALUD | P60: 2939054 | Q60: IMPLEMENTACION Y MANTENIMIENTO DE SISTEMAS DE INTERNET DE LAS COSAS | R60: PRESENCIAL | S60: 45937 | T60: 46118 | U60: ALCALDIA MUNICIPAL DE SAN PEDRO DE URABA | W60: SAN PEDRO DE URABA | X60: gobierno@sanpedrodeuraba-antioquia.gov.co
A61: Marcelino Gonzalez | B61: Vinc. Lab. | C61: daironbr37@gmail.com | D61: CC | E61: 1038801600 | F61: BABILONIA | G61: RODRIGUEZ | H61: DYRON | I61: Dyron Babilonia Rodriguez | J61: M | K61: ANTIOQUIA | L61: CHIGORODO | M61: VEREDA LA JOYA | N61: 3206576337 | O61: NUEVA EPS | P61: 3206188 | Q61: PRODUCCION AGROPECUARIA | R61: PRESENCIAL | S61: 45910 | T61: 46121 | U61: PROMOTORA PALMERA DE ANTIOQUIA | V61: cra80 cl80 L 116 CC Las Playas | W61: CAREPA | X61: recepción.ppa@hotmail.com | Y61: DARIO HERNANDEZ | Z61: 3104097686
A62: Virtual | B62: Pasantía | C62: elsarojasgo@hotmail.com | D62: CC | E62: 51625811 | F62: ROJAS | G62: GONZALEZ | H62: ELSA PATRICIA | I62: Elsa Patricia Rojas Gonzalez | J62: F | K62: BOGOTA | L62: BOGOTA | M62: Cra 16 No.36-22 | N62: 3152663714 | O62: NUEVA EPS | P62: 3069912 | Q62: VENTA DE PRODUCTOS EN LINEA | R62: VIRTUAL | S62: 45939 | T62: 46121 | U62: FUNDAR | V62: Cra 16 No.36-22 | W62: BOGOTA | X62: relaciones.publicas@ffundar.org | Y62: Claudia Delgado | Z62: 314 8141388
A63: Marcelino Gonzalez | B63: Vinc. Lab. | C63: luiseduardopinedamanco25@gmail.com | D63: CC | E63: 1007386733 | F63: PINEDA | G63: MANCO | H63: LUIS EDUARDO | I63: Luis Eduardo Pineda Manco | J63: M | K63: ANTIOQUIA | L63: CHIGORODO | M63: Carrera 93 Calle 82-10 | N63: 3113145184 | O63: SAVIA SALUD | P63: 3206188 | Q63: PRODUCCION AGROPECUARIA | R63: PRESENCIAL | S63: 45943 | T63: 46124 | U63: UNALTRAPEC | V63: Calle 95 N°95-23 | W63: CHIGORODO | X63: unaltrachigorodo@gmail.com | Y63: JUAN CAMILO QUIRAMA | Z63: 3116530212
A64: Silvia Chaverra | B64: Pasantía | C64: trillonavarrogloriaaria@gmail.com | D64: CC | E64: 39319341 | F64: TRILLO | G64: NAVARRO | H64: GLORIA MARIA | I64: Gloria Maria Trillo Navarro | J64: F | K64: ANTIOQUIA | L64: APARTADO | M64: mz 46 cs 9 blq 4 | N64: 3247079388 | O64: SAVIA SALUD | P64: 2924226 | Q64: GESTIÓN ADMINISTRATIVA | R64: PRESENCIAL | S64: 45945 | T64: 46126 | U64: SALUD DARIEN IPS | V64: CLL 100 N 94A - 31 | W64: APARTADO | X64: auxiliar.administrativa@saluddarien.com | Y64: LILIBETH PINEDA | Z64: 3128159696
A65: Marcelino Mejia | B65: Pasantía | C65: wendysuescum8@gmail.com | D65: CC | E65: 1028029799 | F65: SUESCUN | G65: HERNANDEZ | H65: WENDY ALEJANDRA | I65: Wendy Alejandra Suescun Hernandez | J65: F | K65: ANTIOQUIA | L65: APARTADÓ | M65: CRA 84C CLL95B-13 | N65: 3207691674 | O65: NUEVA EPS | P65: 2924347 | Q65: GESTION ADMINISTRATIVA DEL SECTOR SALUD. | R65: PRESENCIAL | S65: 15/10/2025 | T65: 46127 | U65: SALUD DARIEN IPS | V65: CLL 100 N 94A - 30 | W65: APARTADO | X65: auxiliar.administrativa@saluddarien.com | Y65: LILIBETH PINEDA | Z65: 3128159696
A66: Julian Moreno | B66: Pasantía | C66: diana.5almario@gmail.com | D66: CC | E66: 1001033156 | F66: DIAZ | G66: ALMARIO | H66: DIANA CAROLINA | I66: Diana Carolina Diaz Almario | J66: F | K66: ANTIOQUIA | L66: SAN PEDRO DE URABA | M66: CLL 49 #44-13 | N66: 3167515180 | O66: NUEVA EPS | P66: 3063936 | Q66: SERVICIOS FARMACEUTICOS | R66: PRESENCIAL | S66: 45951 | T66: 46132 | U66: GRUPO EMPRESARIAL LA FAVORITA SAS ZOMAC - DROGUERIA LA FAVORITA | V66: CRA 50 # 46 - 22 BARRIO CENTRO | W66: SAN PEDRO DE URABA | X66: cadministrativa@grupofavorita.com | Y66: MONICA ALEJANDRA QUICENO GUZAMAN | Z66: 3225694028
A67: Julian Moreno | B67: Pasantía | C67: vane23ceballos@gmail.com | D67: CC | E67: 1007636830 | F67: LORA | G67: CEBALLOS | H67: LEIDYS VANESA | I67: Leidys Vanesa Lora Ceballos | J67: F | K67: ANTIOQUIA | L67: SAN PEDRO DE URABA | M67: CRA 16a # 50c-47 | N67: 3103982698 | O67: SAVIA SALUD | P67: 3063936 | Q67: SERVICIOS FARMACEUTICOS | R67: PRESENCIAL | S67: 45951 | T67: 46132 | U67: GRUPO EMPRESARIAL LA FAVORITA SAS ZOMAC - DROGUERIA LA FAVORITA | V67: CRA 50 # 46 - 22 BARRIO CENTRO | W67: SAN PEDRO DE URABA | X67: cadministrativa@grupofavorita.com | Y67: MONICA ALEJANDRA QUICENO GUZAMAN | Z67: 3225694028
A68: Julian Moreno | B68: Pasantía | C68: hellensoto135@gmail.com | D68: CC | E68: 1035643286 | F68: SOTO | G68: BENJUMEA | H68: HELLEN DAYANA | I68: Hellen Dayana Soto Benjumea | J68: F | K68: ANTIOQUIA | L68: SAN PEDRO DE U. | M68: CLL 46 CRA 40 BARRIO 16 DE MAYO | N68: 3147124957 | O68: SAVIA SALUD | P68: 3063936 | Q68: SERVICIOS FARMACEUTICOS | R68: PRESENCIAL | S68: 45951 | T68: 46132 | U68: GRUPO EMPRESARIAL LA FAVORITA SAS ZOMAC - DROGUERIA LA FAVORITA | V68: CLL 50 # 52-26 BARRIO CENTRO | W68: SAN PEDRO DE URABA | X68: cadministrativa@grupofavorita.com | Y68: MONICA QUICENO GUZMÁN | Z68: 3225694028
A69: Marcelino Gonzalez | B69: Vinc. Lab. | C69: eduardo901221@hotmail.com | D69: CC | E69: 1038806850 | F69: PEÑA | G69: ARRIETA | H69: LUIS EDUARDO | I69: Luis Eduardo Peña Arrieta | J69: M | K69: ANTIOQUIA | L69: CHIGORODO | M69: carrara 94 #87-10 | N69: 3205141349 | O69: SURA | P69: 3206188 | Q69: PRODUCCION AGROPECUARIA | R69: PRESENCIAL | S69: 45952 | T69: 46133 | U69: UNALTRAPEC | V69: Calle 95 N°95-23 | W69: CHIGORODO | X69: unaltrachigorodo@gmail.com | Y69: VIVIANA MARCELA CANO | Z69: 3122204920
A70: Julian Moreno | B70: Pasantía | C70: herreraburgosleanismarcela@gmail.com | D70: CC | E70: 1035640800 | F70: HERRERA | G70: BURGOS | H70: LEANIS MARCELA | I70: Leanis Marcela Herrera Burgos | J70: F | K70: ANTIOQUIA | L70: SAN PEDRO DE URABA | M70: CRA 43 N-43 A-96 | N70: 3235118312 | O70: SAVIA SALUD | P70: 3063936 | Q70: SERVICIOS FARMACEUTICOS | R70: PRESENCIAL | S70: 45953 | T70: 46133 | U70: ZOMAC | V70: CLL 50 # 52-26 BARRIO CENTRO | W70: SAN PEDRO DE URABA | X70: CADMINISTRATIVA@GRUPOFAVORITA.COM | Y70: MONICA QUICENO | Z70: 3225694028
A71: Virtual | B71: Vinc. Lab. | C71: melisacontrera2002@gmail.com | D71: CC | E71: 1072254889 | F71: CONTRERAS | G71: ROQUEME | H71: MELISSA LINEY | I71: Melissa Liney Contreras Roqueme | J71: F | K71: CORDOBA | L71: MONTERIA | M71: KRA 5D CLL 99-20 MOCARI | N71: 3019409166 | O71: MUTUAL SER | P71: 3069862 | Q71: ATENCION INTEGRAL AL CLIENTE | R71: VIRTUAL | S71: 45951 | T71: 46133 | U71: ZIREL | V71: CRA 16 N48A-48 B.MONTEVERDE | W71: MONTERIA CORDOBA | X71: nalocorrea-8902@hotmail.com | Y71: NAILA VANESSA CORREA MARTINEZ | Z71: 3104516424
A72: Maria del Rosari Jaramillo | B72: Pasantía | C72: DIVIS161988@HOTMAIL.COM | D72: CC | E72: 1027956456 | F72: LOPEZ | G72: PALMERA | H72: DIBYS PAOLA | I72: Dibys Paola Lopez Palmera | J72: F | K72: ANTIOQUIA | L72: APARTADÓ | M72: EL BARRIO PORVENIR | N72: 3043816422 | O72: NUEVA EPS | P72: 2932599 | Q72: .ATENCION INTEGRAL A LA PRIMERA INFANCIA | R72: PRESENCIAL | S72: 21/10/2025 | T72: 46133 | U72: FUNDACIÓN DIOCESANA COMPARTIR | V72: BARRIO CHINITA, CARRERA 98 # 100 - 51 | W72: APARTADÓ ANTIOQUIA | X72: COMPARTIRSEDEHIAPARTADO@GMAIL.COM | Y72: CINDY JOHANA VALENCIA LOPEZ | Z72: 3116284387
A73: Marcelino Gonzalez | B73: Vinc. Lab. | C73: gallego201095@hotmail.com | D73: CC | E73: 1038817057 | F73: GALLEGO | G73: AGAMEZ | H73: ARGEMIRO | I73: Argemiro Gallego Agamez | J73: M | K73: Antioquia | L73: Chigorodo | M73: Calle 86a Carrera 94 | N73: 3233328687 | O73: Sura | P73: 2877506 | Q73: GESTION DE LA PRODUCCION AGRICOLA | R73: PRESENCIAL | S73: 45953 | T73: 46134 | U73: Agricola Guapa SAS | V73: vereda la fe | W73: chigorodo | X73: administracion@guapa.com.co | Y73: viviana | Z73: 3122204920
A74: Yolanda Berrío | B74: Pasantía | C74: sebastiancossio24@gmail.com | D74: CC | E74: 1017261484 | F74: COSSIO | G74: SANCHEZ | H74: JUAN SEBASTIAN | I74: Juan Sebastian Cossio Sanchez | J74: M | K74: ANTIOQUIA | L74: APARTADO | M74: CALLE 99 # 97-10 | N74: 3154650620 | O74: SALUD TOTAL | P74: 2914179 | Q74: PRODUCCIÓN AGROPECUARIA ECOLÓGICA | R74: PRESENCIAL | S74: 45953 | T74: 46135 | U74: GANAX SERVICIOS INTEGRALES | V74: KM 3 VIA PIEDRAS BLANCAS- CAREPA | W74: CAREPA | X74: ganaxserviciosintegrales@hotmail.com | Y74: NELSON FERNANDO GOMEZ CASTRILLON | Z74: 3058040075
A75: Virtual | B75: Pasantía | C75: calmocha04@gmail.com | D75: CC | E75: 1097489782 | F75: MORENO | G75: CHAPARRO | H75: CARLOS ALBERTO | I75: Carlos Alberto Moreno Chaparro | J75: M | N75: 3013513017 | O75: SaludMía EPS | P75: 2879778 | Q75: DESARROLLO PUBLICITARIO | R75: VIRTUAL | S75: 45953 | T75: 46135 | U75: GRUPO EMPRESARIAL WAC | V75: Calle 4 #4-50 centro | W75: PAMPLONA | X75: grupoempresarialwac@gmail.com | Y75: WILLIAM FERNANDO PICÓN RODRÍGUEZ | Z75: 3209062016
A76: Campesena | B76: Pasantía | C76: consueloverdeza@gmail.com | D76: CC | E76: 12257461 | F76: TOLEDO | G76: CHARRY | H76: EIDER | I76: Eider Toledo Charry | J76: M | K76: ANTIOQUIA | L76: SAN JUAN DE URABA | M76: BARRIO SAN JUAN ORIENTAL | N76: 3234980229 | O76: NUEVA EPS | P76: 3016710 | Q76: PRODUCCION AGROPECUARIA | R76: PRESENCIAL | S76: 45955 | T76: 46136 | U76: DIEZ HERMANOS | V76: DSAN JUAN ORIENTAL | W76: SAN JUAN DE URABA | X76: jonjankev@hotmail.com | Y76: EDINSO VERDEZA MORA | Z76: 3105151705
A77: Paola Londoño | B77: Pasantía | C77: laurareyes.lr278@gmail.com | D77: CC | E77: 1028033175 | F77: REYES | G77: MURILLO | H77: LAURA CRISTINA | I77: Laura Cristina Reyes Murillo | J77: F | K77: ANTIOQUIA | L77: APARTADO | M77: Barrio obrero bloque 2 | N77: 3015033217 | O77: EPS SURA | P77: 3013096 | Q77: SERVICIOS COMERCIALES Y FINANCIEROS | R77: PRESENCIAL | S77: 45955 | T77: 46136 | U77: ACET MONTERIA S.A.S | V77: CLL 103 B # 100-41 Barrio Vélez | W77: APARTADÓ | X77: acetmonteriasas@gmail.com | Y77: FEDENNY ANDREA VALDES AMUD | Z77: 3116332419
A78: Carlos Negrete | B78: Pasantía | C78: quintocharles37@gmail.com | D78: CC | E78: 71350766 | F78: QUINTO | G78: COSSIO | H78: CHARLES | I78: Charles Quinto Cossio | J78: M | K78: ANTIOQUIA | L78: TURBO | M78: calle 99 cra 8 | N78: 3215527194 | O78: Sanidad Militar | P78: 2983888 | Q78: MANTENIMIENTO DE EQUIPOS DE AIRE ACONDICIONADO Y REFRIGERACION | R78: PRESENCIAL | S78: 45955 | T78: 46136 | U78: SERVICIO NACIONAL DE APRENDIZAJE SENA | V78: Salida Turbo km 1 | W78: APARTADO | X78: aserna@sena.edu.co | Y78: ANDERSON SERNA SALAZAR | Z78: 310 360 4480
A79: Julián Lugo | B79: Proy. Prod. | C79: cogollojuliana55@gmail.com | D79: CC | E79: 1040356873 | F79: COLLOGO | G79: LUNA | H79: JULIANA PATRICIA | I79: Juliana Patricia Collogo Luna | J79: F | K79: ANTIOQUIA | L79: SAN PEDRO DE URABÁ | M79: CORREGIMIENTO EL RAYO | N79: 3114290934 | O79: "SAVIA SALUD EPS" | P79: 3215957 | Q79: PRODUCCION AGROPECUARIA | R79: PRESENCIAL | S79: 45956 | T79: 46137 | U79: Vivero de caco Agrorayo | V79: Vereda el Rayo | W79: San pedro de Urabá
A80: Julián Lugo | B80: Proy. Prod. | C80: vegaperalta472@Ïgmail.com | D80: CC | E80: 1001401600 | F80: VEGA | G80: PERALTA | H80: ERIKA MILENA | I80: Erika Milena Vega Peralta | J80: F | K80: ANTIOQUIA | L80: SAN PEDRO DE URABÁ | M80: CORREGIMIENTO EL RAYO | N80: 3235559368 | O80: "SAVIA SALUD EPS" | P80: 3215957 | Q80: PRODUCCION AGROPECUARIA | R80: PRESENCIAL | S80: 45956 | T80: 46137 | U80: Vivero de caco Agrorayo | V80: Vereda el Rayo | W80: San pedro de Urabá
A81: Julián Lugo | B81: Proy. Prod. | C81: cristiandubangarciajulio@gmail.com | D81: TI | E81: 1035642800 | F81: BLANCO | G81: LOPEZ | H81: ARLIS JOHANA | I81: Arlis Johana Blanco Lopez | J81: F | K81: ANTIOQUIA | L81: SAN PEDRO DE URABÁ | M81: CORREGIMIENTO EL RAYO | N81: 3185054203 | O81: NUEVA EPS S.A. | P81: 3215957 | Q81: PRODUCCION AGROPECUARIA | R81: PRESENCIAL | S81: 45956 | T81: 46137 | U81: Vivero de caco Agrorayo | V81: Vereda el Rayo | W81: San pedro de Urabá
A82: Virtual | B82: Pasantía | C82: johanaren88@gmail.com | D82: CC | E82: 1094896213 | F82: RENDON | G82: ZULUAGA | H82: MONICA JOHANA | I82: Monica Johana Rendon Zuluaga | J82: F | K82: QUINDÍO | L82: ARMENIA | M82: CONJUNTOS PARQUES DE BOLIVAR 1 BLOQUE F APTO 502 BARRIO LA PATRIA | N82: 3156061439 | O82: NUEVA EPS | P82: 2626946 | Q82: DESARROLLO DE MEDIOS GRAFICOS VISUALES | R82: VIRTUAL | S82: 45956 | T82: 46137 | U82: SDATA | V82: CALLE 16 BIS NO.25-19 | W82: ARMENIA | X82: oscardariorendonzuluaga@outlook.es | Y82: ÓSCAR DARIO RENDÓN ZULUAGA | Z82: 3235890164
A83: Julián Lugo | B83: Pasantía | C83: asoagrorayo@gmail.com | D83: CC | E83: 1035643082 | F83: GONZALEZ | G83: MURILLO | H83: JESUS DAVID | I83: Jesus David Gonzalez Murillo | J83: M | K83: ANTIOQUIA | L83: SAN PEDRO DE URABÁ | M83: VEREDA LA MAYUPA | N83: 3206877759 | O83: "SAVIA SALUD EPS" | P83: 3215957 | Q83: PRODUCCION AGROPECUARIA | R83: PRESENCIAL | S83: 26/10/2025 | T83: 46137 | U83: DELIRIO 1 | V83: Vereda El Rayo | W83: San pedro de Urabá | X83: 0 | Z83: 0
A84: Julián Lugo | B84: Pasantía | C84: cogollojuliana55@gmail.com | D84: TI | E84: 1035645952 | F84: ESPITIA | G84: COGOLLO | H84: ANGEL DAVID | I84: Angel David Espitia Cogollo | J84: M | K84: ANTIOQUIA | L84: SAN PEDRO DE URABÁ | M84: CORREGIMIENTO EL RAYO | N84: 3114290934 | O84: "SAVIA SALUD EPS" | P84: 3215957 | Q84: PRODUCCION AGROPECUARIA | R84: PRESENCIAL | S84: 26/10/2025 | T84: 46137 | U84: Vivero de cacao Agrorayo | V84: Corr. El Rayo, San pedro de Urabá | W84: San pedro de Urabá | X84: asoagrorayo@gmail.com | Y84: GABRIEL JOSE ORTIZ MUENTES | Z84: 3114397638
A85: Julián Lugo | B85: Pasantía | C85: asoagrorayo@gmail.com | D85: TI | E85: 1041261210 | F85: RUIZ | G85: QUIÑONES | H85: ENUALDO | I85: Enualdo Ruiz Quiñones | J85: M | K85: ANTIOQUIA | L85: SAN PEDRO DE URABÁ | M85: CORREGIMIENTO EL RAYO | N85: 3114290934 | O85: "SAVIA SALUD EPS" | P85: 3215957 | Q85: PRODUCCION AGROPECUARIA | R85: PRESENCIAL | S85: 26/10/2025 | T85: 46137 | U85: NO HAY COMO DIOS | V85: C.R.O EL RAYO | W85: 0 | X85: 0 | Y85: MANUEL QUIÑONEZ PLAZA | Z85: 316416763
A86: Abel Valderrama | B86: Pasantía | C86: melanybravo2019@gmail.com | D86: CC | E86: 1032178193 | F86: GUERRERO | G86: BRAVO | H86: MELANEE | I86: Melanee Guerrero Bravo | J86: F | K86: Antioquia | L86: Turbo | M86: N/Colonia, Las Flores | N86: 3122076895 | O86: Nueva Eps | P86: 2842920 | Q86: SISTEMAS. | R86: PRESENCIAL | S86: 45957 | T86: 46139 | U86: Casa de Gobierno | V86: Nueva Colonia | W86: Turbo | X86: casadegobienronvacolonia@turbo-antioquia.gov.co | Y86: Guillermo Lopez | Z86: 3104300447
A87: Virtual | B87: Pasantía | C87: ing.viviandiaz@gmail.com | D87: CC | E87: 1033715944 | F87: DIAZ | G87: BORJA | H87: VIVIAN JHOANA | I87: Vivian Jhoana Diaz Borja | J87: F | K87: ANTIOQUIA | L87: APARTADO | N87: 317846764 | O87: Salud Total | P87: 3069909 | Q87: SISTEMAS TELEINFORMÁTICOS | R87: VIRTUAL | S87: 45961 | T87: 46142 | U87: ASOMUMEVIR | V87: Cll 79 N° 16P 48 | W87: Bogotá | X87: asomumevir2108@gmail.com | Y87: Inés Isabel Borja | Z87: 3105790821
A88: Antonio Barrada | B88: Pasantía | C88: fcarrascal@sena.edu.co | D88: CC | E88: 8110766 | F88: CARRASCAL | G88: MALDONADO | H88: FRANCISCO | I88: Francisco Carrascal Maldonado | J88: M | K88: ANTIOQUIA | L88: APARTADÓ | M88: Cra 113C No. 66-79 | N88: 3146278550 | O88: Sura | P88: 2822838 | Q88: CARPINTERIA. | R88: PRESENCIAL | S88: 45962 | T88: 46142 | U88: SERVICIO NACIONAL DE APRENDIZAJE SENA | V88: Km 1 salida a Turbo | W88: Apartadó | X88: jguerrero@sena.edu.co | Y88: Alexis Guerrero | Z88: 3143617739
A89: Abel Valderrama | B89: Pasantía | C89: diana1020r@gmail.com | D89: CC | E89: 1001846618 | F89: ROMAÑA | G89: RODRIGUEZ | H89: NOLBERTA | I89: Nolberta Romaña Rodriguez | J89: F | K89: Antioquia | L89: Vigía del fuerte | M89: B/palmira calle 16 | N89: 3226166647 | O89: Savia Salud | P89: 2999803 | Q89: SISTEMAS TELEINFORMÁTICOS | R89: PRESENCIAL | S89: 45962 | T89: 46142 | U89: Institución Educativa Vigía del fuerte | V89: Transversal 9 N•_ 1_10 barrio pueblo nuevo | W89: Vigía del fuerte | X89: vigia83@hotmail.com | Y89: Alivio Córdoba Maquilon | Z89: 3122968605
A90: Abel Valderrama | B90: Pasantía | C90: andrihujaramillo@gmail.com | D90: TI | E90: 1067164768 | F90: ARTEAGA | G90: BERRIO | H90: TATIANA | I90: Tatiana Arteaga Berrio | J90: F | K90: ANTIOQUIA | L90: CAREPA | M90: 71-63-45 | N90: 314882788 | O90: MUTUAL SER | P90: 3077813 | Q90: SISTEMAS TELEINFORMÁTICOS | R90: PRESENCIAL | S90: 45962 | T90: 46142 | U90: INSTITUCION EDUCATIVA COLOMBIA | V90: JORGE ELIECER GAITAN | W90: CAREPA | X90: iecolombiaurb@hotmail.com | Y90: FREDY MANUEL TEJERA MURILLO | Z90: 3014499871
A91: Virtual | B91: Pasantía | C91: HERRENOMAYE@GMAIL.COM | D91: CC | E91: 1096484806 | F91: HERREÑO | G91: JEREZ | H91: MAYERLIN | I91: Mayerlin Herreño Jerez | J91: F | K91: CUNDINAMARCA | L91: SOACHA | M91: KR 27 A ESTE 56B 122 | N91: 6016988134 | O91: COOSALUD | P91: 3069912 | Q91: VENTA DE PRODUCTOS EN LINEA | R91: VIRTUAL | S91: 45960 | T91: 46142 | U91: CENTRO DE ENSEÑANZA AUTOMOVILISTICA METROCONDUCCIÓN SAS | V91: CALLE 45 A SUR N 52C - 53 PISO 2 Y 3 | W91: BOGOTA | X91: Ceametroconduccion@gmail.com | Y91: JHON ALEJANDRO MAYOR FARFAN | Z91: 301 6934704
A92: Andrés Felipe Henao | B92: Vinc. Lab. | C92: richarfelipearango@gmail.com | D92: CC | E92: 1028027525 | F92: ARANGO | G92: BRAN | H92: RICHARD FELIPE | I92: =PROPER(H92&" "&F92&" "&G92) -> Richard Felipe Arango Bran | J92: M | K92: Antioquía | L92: Turbo | M92: Currulao/Turbay Ayala | N92: 3218424960 | O92: Nueva E.P.S | P92: 2920221 | Q92: INSTALACION DE SISTEMAS ELECTRICOS RESIDENCIALES Y COMERCIALES | R92: PRESENCIAL | S92: 29/10/2025 | T92: 46142 | U92: DINATEL GROUP S.A.S | V92: Cra 60 #75 -107, net. Centro | W92: Atlantico | X92: recursoshumanos@refrisistema.co | Y92: wilmer meza | Z92: 3174404666
A93: Daisy Quejada | B93: Vinc. Lab. | C93: ruth-1243@hotmail.com | D93: CC | E93: 1007691020 | F93: VARELA | G93: VARELA | H93: RUTH DANEIRIS | I93: Ruth Daneiris Varela Varela | J93: F | K93: ANTIOQUIA | L93: APARTADÓ | N93: 3125721435 | P93: 2877824 | Q93: GESTION CONTABLE Y DE INFORMACION FINANCIERA | R93: PRESENCIAL | S93: 45967 | T93: 46147 | U93: TRANSPORTADORES UNIDOS DE URABA-TRANSUNUR S.A.S ZOMAC | V93: KM 5 via Apartadò a Carepa | W93: Apartadò | X93: sgitransunur@gmail.com | Y93: Zoraida Patricia Echavarria Bedoya
A94: Julian Moreno | B94: Vinc. Lab. | C94: lacaro1201@hotmail.com | D94: CC | E94: 1001669158 | F94: AYALA | G94: IBARGUEN | H94: CAROLINA | I94: Carolina Ayala Ibarguen | J94: F | K94: Antioquia | L94: carepa | M94: carrera 73A 70-33 | N94: 3108802450 | O94: nueva eps | P94: 2932594 | Q94: SALUD PUBLICA | R94: PRESENCIAL | S94: 45968 | T94: 46148 | U94: Banafrut | V94: Vereda zarabanda, kilometro 7 via zungo embarcadero carepa antioquia | W94: Carepa | X94: info@banafurt.com
A95: Daisy Quejada | B95: Pasantía | C95: danielaarroyo2506@gmail.com | D95: CC | E95: 1003126449 | F95: ARROYO | G95: CAMPUSANO | H95: MARIA DANIELA | I95: Maria Daniela Arroyo Campusano | J95: F | K95: Antioquia | L95: Carepa | M95: Urbanización nuevo futuro etapa #2 bloque #1 casa #3 | N95: 3107886813 | O95: Sura | P95: 2877824 | Q95: GESTION CONTABLE Y DE INFORMACION FINANCIERA | R95: PRESENCIAL | S95: 45971 | T95: 46151 | U95: Alcaldía de carepa | W95: Carepa/ Antioquia | X95: sst@carepa-antioquia.gov.co | Y95: Rubí Carvajal | Z95: 3107886813
A96: Paola Londoño | B96: Pasantía | C96: luchia3004@gmail.com | D96: CC | E96: 1110534777 | F96: SALINAS | G96: CARDOZO | H96: LUZ MARINA | I96: Luz Marina Salinas Cardozo | J96: F | K96: ANTIOQUIA | L96: CAREPA | M96: CASA VERDE | N96: 3105562194 | O96: NUEVA EPS | P96: 3013096 | Q96: SERVICIOS COMERCIALES Y FINANCIEROS | R96: PRESENCIAL | S96: 45849 | T96: 46152 | U96: TRANSILVER S.A.S | V96: CALLE 70 #78-40 BARRIO LAURELES | W96: CAREPA | X96: transilverauxiliar@gmail.com | Y96: Yuliana Posada Higuita | Z96: 3105866071
A97: Lucy Pernett | B97: Pasantía | C97: martinezperezandres970@gmail.com | D97: CC | E97: 1033370951 | F97: MARTINEZ | G97: PEREZ | H97: ANDRES FELIPE | I97: Andres Felipe Martinez Perez | J97: M | K97: ANTIOQUIA | L97: ARBOLETTES | M97: Cl.25a 302 | N97: 3004664046 | O97: FAMILIAR DE COLOMBIA | P97: 2973692 | Q97: SERVICIOS COMERCIALES Y FINANCIEROS | R97: PRESENCIAL | S97: 45971 | T97: 46152 | U97: CECRETARIA DE ACIENDA | V97: CRA. 29 #30b-18 | W97: ARBOLETES | X97: cecretariadehacienda@ arboletes-antioquia.gov.co | Y97: Oscar Mauricio Gallón perez | Z97: 3103619240
A98: Julián Lugo | B98: Pasantía | C98: kenier566@gmail.com | D98: TI | E98: 1149444631 | F98: MORENO | G98: TORRES | H98: KEINER DAVID | I98: Keiner David Moreno Torres | J98: M | K98: ANTIOQUIA | L98: SAN PEDRO DE URABÁ | M98: CORREGIMIENTO EL RAYO | N98: 3165729977 | O98: "SAVIA SALUD EPS" | P98: 3215957 | Q98: PRODUCCION AGROPECUARIA | R98: PRESENCIAL | S98: 46002 | T98: 46152 | U98: LA CEIBA | V98: C.R.O EL RAYO | W98: 0 | X98: 0 | Y98: ISAAC MORENO REYES | Z98: 3182474665
A99: Virtual | B99: Pasantía | C99: angiepalomino03@gmail.com | D99: CC | E99: 1001820362 | F99: PALOMINO | G99: BERMUDEZ | H99: ANGIE BELEN | I99: Angie Belen Palomino Bermudez | J99: F | K99: ATLÁNTICO | L99: APARTADÓ | M99: CRA 13C # 40-45 | N99: 3128764347 | O99: SANITAS | P99: 2721325 | Q99: DESARROLLO DE MEDIOS GRAFICOS VISUALES | R99: VIRTUAL | S99: 45972 | T99: 46152 | U99: CREADENT ODONTOLOGIA ESPECIALIZADA | V99: CR 43 No 72 - 122 | W99: BARRANQUILLA | X99: creadentbq@gmail.com | Y99: SARMIENTO SARMIENTO ZAIDA LINEY | Z99: 310 2910267
A100: Yolanda Berrío | B100: Pasantía | C100: saboresnacao@gmail.com | D100: CC | E100: 1037612724 | F100: VARGAS | G100: GARCIA | H100: LUISA FERNANDA | I100: Luisa Fernanda Vargas Garcia | J100: F | K100: ANTIOQUIA | L100: CHIGORODÓ | M100: VEREDA TIERRA SANTA | N100: 3176219977 | O100: SURAMERICANA | P100: 3004049 | Q100: SISTEMAS AGROPECUARIOS ECOLOGICOS. | R100: PRESENCIAL | S100: 45973 | T100: 46153 | U100: Yoladis Garcia Madarriaga | V100: Vereda Tierra Santa | W100: Chigorodó | X100: solangelvargasgarcia@gmail.com | Y100: Yoladis Garcia Madariaga | Z100: 3213212598
A101: Abel Valderrama | B101: Pasantía | C101: DELIAJUDITHCANSARICONDE679@GMAIL.COM | D101: CC | E101: 1193501417 | F101: CANSARI | G101: CONDE | H101: DELIA JUDITH | I101: Delia Judith Cansari Conde | J101: F | K101: CHOCO | L101: BOJAYA | M101: LA Y | N101: 3146978002 | O101: NUEVA EPS | P101: 3001943 | Q101: SISTEMAS TELEINFORMÁTICOS | R101: PRESENCIAL | S101: 45973 | T101: 46153 | U101: MUNICIPIO DE BOJAYA | V101: BARRIO LA UNION ALCALDIA MUNICIPAL | W101: BOJAYA | X101: contactenos@bojaya-choco.gov.co | Y101: NEILA PLACIOS MORENO | Z101: 3128951428
...

Sheet Instructores 2026
A1: LISTADO DE INSTRUCTORES DE SEGUIMIENTO A ETAPA PRODUCTIVA DE 2026
A2: Coordinación | B2: Nombre instructor | C2: Formación | D2: Teléfono | E2: Correo corp | F2: Tipo de vinc. | G2: % dedic | H2: Cant Aprend
A3: Aida | B3: Abel De La Cruz Valderrama Palacio | C3: Sistemas | D3: 312 768 8079 | E3: advalderrama@sena.edu.co | F3: Contratista | G3: 100 | H3: 80
A4: Aida | B4: Andrés Felipe Henao Núñez | C4: Motores | D4: 301 280 6637 | E4: afhenao@sena.edu.co | F4: Contratista | G4: 30 | H4: 24
A5: Aida | B5: Cindy Johanna Gualtero Restrepo | C5: Gráficos | D5: 323 567 5626 | E5: cjgualtero@sena.edu.co | F5: Contratista | G5: 100 | H5: 80
A6: Aida | B6: Moises Enrique Garay Castro | C6: Gráficos | D6: 316 851 3077 | E6: mgarayc@sena.edu.co
A7: Aida | B7: Carlos Felipe Negrete Petro | C7: Electricidad | D7: 314 654 9006 | E7: cnegretep@sena.edu.co | F7: Planta | G7: 80 | H7: 52
A8: Aida | B8: Claudia Paricia Villareal Cárdenas | C8: Virtualidad | D8: 310 809 9637 | E8: cpvillareal@sena.edu.co
A9: Yanny Rivas | B9: Paola Andrea Londoño Guzmán | C9: SST | D9: 314 672 5672 | E9: plondono@sena.edu.co | F9: Planta | G9: 100 | H9: 65
A10: Yanny Rivas | B10: Silvia Paola Chaverra Durán | C10: administracion | D10: 314 600 6451 | E10: spchaverra@sena.edu.co | F10: Contratista | G10: 100 | H10: 80
A11: Yanny Rivas | B11: Aldwin Morelo Villa | C11: Adm y logis | D11: 300 254 1479 | E11: amorelo@sena.edu.co | F11: Contratista | G11: 100 | H11: 80
A12: Yanny Rivas | B12: Daisy Suheiry Quejada Durán | C12: Contadora | D12: 313 743 3102 | E12: dquejada@sena.edu.co | F12: Contratista | G12: 100 | H12: 80
A13: Yanny Rivas | B13: Jaime Andrés Ruiz Ortega | C13: Comercio | D13: 310 894 2666 | E13: jaruizo@sena.edu.co | F13: Contratista | G13: 30 | H13: 24
A14: Yanny Rivas | B14: Lucy Liliana Pernett Ospina | C14: Hoteleria | D14: 310 898 1729 | E14: lpernett@sena.edu.co | F14: Planta | G14: 100 | H14: 65
A15: Maricela | B15: Flor Elene Jiménez Lopera | C15: agric sost | D15: 300 632 6923 | E15: fejimenezl@sena.edu.co | F15: Planta | G15: 100 | H15: 65
A16: Maricela | B16: Marcelino González Vertel | C16: Agronomia | D16: 320 724 8288 | E16: mgonzalesve@sena.edu.co | F16: Contratista | G16: 100 | H16: 80
A17: Maricela | B17: Erika Durango Martínez | C17: MVZ | D17: 314 835 7426 | E17: eydurango@sena.edu.co
A18: Maricela | B18: Gustavo Andrés Cataño Cortes | C18: MVZ | D18: 321 626 8578 | E18: gcatanoc@sena.edu.co | F18: Contratista | G18: 60 | H18: 48
A19: Maricela | B19: Nelvis Margoth Barboza Rivera | C19: Farmacia | D19: 302 243 9155 | E19: nmbarboza@sena.edu.co | F19: Contratista | G19: 100 | H19: 80
A20: Maricela | B20: Julián Mauricio Moreno Flórez | C20: Quimico amb | D20: 312 786 4424 | E20: jmmorenof@sena.edu.co | F20: Contratista | G20: 100 | H20: 80
A21: Maricela | B21: Yorger Moreno Agualimpia | C21: Ambiental | D21: 311 322 5327 | E21: ymorenoa@sena.edu.co | F21: Contratista | G21: 100 | H21: 80
A22: Maricela | B22: Maria del Rosari Jaramillo Hernández | C22: Infancia | D22: 314 675 7233 | E22: mjaramillohe@sena.edu.co | F22: Contratista | G22: 25 | H22: 20
A23: Maricela | B23: Viviana Lizeth Robledo Bello | C23: Deportes | D23: 320 666 9480 | E23: vrobledo@sena.edu.co | F23: Contratista | G23: 100 | H23: 80
A24: Osman | B24: Marco Antonio García Peña | C24: Deportes | D24: 320 769 1560 | E24: mgarciap@sena.edu.co | F24: Planta
A25: Osman | B25: Yerlis Hernández Martínez | C25: Deportes | D25: 320 571 1276 | E25: yhernandezm@sena.edu.co | F25: Contratista | G25: 50 | H25: 40
A26: Osman Campesena | B26: Dina Luz Dorado Pérez | D26: 311 683 0354 | E26: ddoradop@sena.edu.co | F26: Contratista
A27: Osman Campesena | B27: Yolanda Berrío | D27: 312 728 2722 | E27: yberrio@sena.edu.co | F27: Contratista
A28: Osman Campesena | B28: Aristides Maturana Ramos | D28: 314 725 2697 | E28: amaturana@sena.edu.co
A29: Osman Campesena | B29: Fabián Andrés Valencia Castrillón | D29: 314 764 6245 | E29: favalenciac@sena.edu.co | F29: Contratista
A30: Osman Campesena | B30: Julián andrés Lugo Castañeda | D30: 313 587 7277 | E30: jlugo@sena.edu.co | F30: Contratista

Sheet Perfilamiento
A1: FORMACIONES POR COORDINACIÓN
A3: FORMACIÓN | B3: PERFILA | C3: COORDINADOR | D3: APOYO DE COORDINACIÓN - CELULAR
A4: ACTIVIDAD FISICA | B4: ssepulvedad@sena.edu.co | C4: OSMAN JOSUE PEREA CASTRO
A5: ANALISIS Y DESARROLLO DE SISTEMAS DE INFORMACION | B5: bjmontoya@sena.edu.co | C5: AIDA LUZ BALLESTEROS | D5: Yorledis Leon Carbrera - 313 248 4064
A6: ANALISIS Y DESARROLLO DE SOFTWARE | B6: bjmontoya@sena.edu.co | C6: AIDA LUZ BALLESTEROS | D6: Yorledis Leon Carbrera - 313 248 4064
A7: APOYO ADMINISTRATIVO EN SALUD. | B7: scalvarez@sena.edu.co | C7: MARICELA BARRERA MONTANEZ | D7: Leidy Borquez - 310 538 7274
A8: ASISTENCIA ADMINISTRATIVA . | B8: jmosquera@sena.edu.co | C8: YANNY RIVAS LONDOÑO | D8: Valentina Viloria - 310 354 6731
A9: ASISTENCIA EN ORGANIZACION DE ARCHIVOS . | B9: jmosquera@sena.edu.co | C9: YANNY RIVAS LONDOÑO | D9: Valentina Viloria - 310 354 6731
A10: ASISTENCIA PARA LA INTELIGENCIA EMPRESARIAL | B10: jmosquera@sena.edu.co | C10: YANNY RIVAS LONDOÑO | D10: Valentina Viloria - 310 354 6731
A11: ATENCION INTEGRAL A LA PRIMERA INFANCIA | B11: scalvarez@sena.edu.co | C11: MARICELA BARRERA MONTANEZ | D11: Leidy Borquez - 310 538 7274
A12: ATENCION INTEGRAL AL CLIENTE | B12: jmosquera@sena.edu.co | C12: YANNY RIVAS LONDOÑO | D12: Valentina Viloria - 310 354 6731
A13: AUXILIAR EN COCINA | B13: jmosquera@sena.edu.co | C13: YANNY RIVAS LONDOÑO | D13: Valentina Viloria - 310 354 6731
A14: COCINA | B14: jmosquera@sena.edu.co | C14: YANNY RIVAS LONDOÑO | D14: Valentina Viloria - 310 354 6731
A15: COMERCIALIZACION DE PRODUCTOS MASIVOS | B15: jmosquera@sena.edu.co | C15: YANNY RIVAS LONDOÑO | D15: Valentina Viloria - 310 354 6731
A16: CONSERVACION DE RECURSOS NATURALES | B16: scalvarez@sena.edu.co | C16: MARICELA BARRERA MONTANEZ | D16: Leidy Borquez - 310 538 7274
... A26: DESARROLLO PUBLICITARIO | B26: bjmontoya@sena.edu.co | C26: AIDA LUZ BALLESTEROS | D26: Yorledis Leon Carbrera - 313 248 4064
A27: EJECUCION DE PROGRAMAS DEPORTIVOS | B27: ssepulvedad@sena.edu.co | C27: OSMAN JOSUE PEREA CASTRO
A28: ENTRENAMIENTO DEPORTIVO | B28: ssepulvedad@sena.edu.co | C28: OSMAN JOSUE PEREA CASTRO
A29: GESTIÓN ADMINISTRATIVA | B29: jmosquera@sena.edu.co | C29: YANNY RIVAS LONDOÑO | D29: Valentina Viloria - 310 354 6731
A30: GESTION ADMINISTRATIVA DEL SECTOR SALUD. | B30: scalvarez@sena.edu.co | C30: MARICELA BARRERA MONTANEZ | D30: Leidy Borquez - 310 538 7274
A31: GESTION AGROEMPRESARIAL | B31: scalvarez@sena.edu.co | C31: MARICELA BARRERA MONTANEZ | D31: Leidy Borquez - 310 538 7274
A32: GESTION CONTABLE Y DE INFORMACION FINANCIERA | B32: jmosquera@sena.edu.co | C32: YANNY RIVAS LONDOÑO | D32: Valentina Viloria - 310 354 6731
A33: GESTION DE EMPRESAS AGROPECUARIAS | B33: scalvarez@sena.edu.co | C33: MARICELA BARRERA MONTANEZ | D33: Leidy Borquez - 310 538 7274
A34: GESTION DE LA PRODUCCION AGRICOLA | B34: scalvarez@sena.edu.co | C34: MARICELA BARRERA MONTANEZ | D34: Leidy Borquez - 310 538 7274
A35: GESTION DE RECURSOS NATURALES | B35: scalvarez@sena.edu.co | C35: MARICELA BARRERA MONTANEZ | D35: Leidy Borquez - 310 538 7274
A36: GESTION DE TESORERIA Y RECURSOS FINANCIEROS | B36: jmosquera@sena.edu.co | C36: YANNY RIVAS LONDOÑO | D36: Valentina Viloria - 310 354 6731
A37: GESTION LOGISTICA | B37: jmosquera@sena.edu.co | C37: YANNY RIVAS LONDOÑO | D37: Valentina Viloria - 310 354 6731
A38: IMPLEMENTACION DE INFRAESTRUCTURA DE TECNOLOGIAS DE LA INFORMACION Y LAS COMUNICACIONES. | B38: bjmontoya@sena.edu.co | C38: AIDA LUZ BALLESTEROS | D38: Yorledis Leon Carbrera - 313 248 4064
A39: IMPLEMENTACION Y MANTENIMIENTO DE SISTEMAS DE INTERNET DE LAS COSAS | B39: bjmontoya@sena.edu.co | C39: AIDA LUZ BALLESTEROS | D39: Yorledis Leon Carbrera - 313 248 4064
A40: INSTALACION DE SISTEMAS ELECTRICOS RESIDENCIALES Y COMERCIALES | B40: bjmontoya@sena.edu.co | C40: AIDA LUZ BALLESTEROS | D40: Yorledis Leon Carbrera - 313 248 4064
... A58: OPERARIO EN LABORES DE CAMPO EN CULTIVOS | B58: scalvarez@sena.edu.co | C58: MARICELA BARRERA MONTANEZ | D58: Leidy Borquez - 310 538 7274
A59: PELUQUERIA. | B59: ssepulvedad@sena.edu.co | C59: OSMAN JOSUE PEREA CASTRO
A60: PRODUCCION AGROPECUARIA | B60: scalvarez@sena.edu.co | C60: MARICELA BARRERA MONTANEZ | D60: Leidy Borquez - 310 538 7274
A61: PRODUCCIÓN AGROPECUARIA ECOLÓGICA | B61: scalvarez@sena.edu.co | C61: MARICELA BARRERA MONTANEZ | D61: Leidy Borquez - 310 538 7274
A62: PRODUCCIÓN GANADERA | B62: scalvarez@sena.edu.co | C62: MARICELA BARRERA MONTANEZ | D62: Leidy Borquez - 310 538 7274
A63: PRODUCCION PECUARIA. | B63: scalvarez@sena.edu.co | C63: MARICELA BARRERA MONTANEZ | D63: Leidy Borquez - 310 538 7274
A64: PUERTO ANTIOQUIA | B64: jmosquera@sena.edu.co | C64: YANNY RIVAS LONDOÑO | D64: Valentina Viloria - 310 354 6731
A65: RECURSOS HUMANOS . | B65: jmosquera@sena.edu.co | C65: YANNY RIVAS LONDOÑO | D65: Valentina Viloria - 310 354 6731
A66: SALUD PUBLICA | B66: scalvarez@sena.edu.co | C66: MARICELA BARRERA MONTANEZ | D66: Leidy Borquez - 310 538 7274
A67: SERVICIO DE RECEPCION HOTELERA | B67: jmosquera@sena.edu.co | C67: YANNY RIVAS LONDOÑO | D67: Valentina Viloria - 310 354 6731
A68: SERVICIOS COMERCIALES Y FINANCIEROS | B68: jmosquera@sena.edu.co | C68: YANNY RIVAS LONDOÑO | D68: Valentina Viloria - 310 354 6731
A69: SERVICIOS FARMACEUTICOS | B69: scalvarez@sena.edu.co | C69: MARICELA BARRERA MONTANEZ | D69: Leidy Borquez - 310 538 7274
A70: SERVICIOS Y OPERACIONES MICROFINANCIERAS | B70: jmosquera@sena.edu.co | C70: YANNY RIVAS LONDOÑO | D70: Valentina Viloria - 310 354 6731
A71: SISTEMAS | B71: bjmontoya@sena.edu.co | C71: AIDA LUZ BALLESTEROS | D71: Yorledis Leon Carbrera - 313 248 4064
... A77: VENTA DE PRODUCTOS EN LINEA | B77: bjmontoya@sena.edu.co | C77: AIDA LUZ BALLESTEROS | D77: Yorledis Leon Carbrera - 313 248 4064
